Workbook
Name Slicer_DepartmentType: #N/A
Name Slicer_Quarters__ExitDate: #N/A
Name Slicer_TerminationType: #N/A
Name Slicer_Training_Type: #N/A
Name Slicer_Years__ExitDate: #N/A

Sheet 1. Retention & Workforce Moveme
A3: Sum of Turnover | B3: Column Labels
A4: Row Labels | B4: 2018 | C4: 2019 | D4: 2020 | E4: 2021 | F4: 2022 | G4: 2023 | H4: Grand Total
A5: Qtr1 | C5: 1263 | D5: 7921 | E5: 20155 | F5: 44699 | G5: 111398 | H5: 185436
A6: Qtr2 | C6: 1468 | D6: 9856 | E6: 30018 | F6: 54765 | G6: 132439 | H6: 228546
A7: Qtr3 | C7: 2455 | D7: 16572 | E7: 42456 | F7: 79924 | G7: 68014 | H7: 209421
A8: Qtr4 | B8: 229 | C8: 6879 | D8: 18456 | E8: 48451 | F8: 88213 | H8: 162228
A9: Grand Total | B9: 229 | C9: 12065 | D9: 52805 | E9: 141080 | F9: 267601 | G9: 311851 | H9: 785631
A18: Department type | B18: Count of Employee ID
A19: Admin Offices | B19: 51
A20: Executive Office | B20: 20
A21: IT/IS | B21: 241
A22: Production | B22: 1054
A23: Sales | B23: 171
A24: Software Engineering | B24: 69
A25: Grand Total | B25: 1606
A33: Count of GenderCode | B33: Column Labels
A34: Row Labels | B34: Female | C34: Male | D34: Grand Total
A35: Admin Offices | B35: 30 | C35: 21 | D35: 51
A36: Executive Office | B36: 1 | C36: 19 | D36: 20
A37: IT/IS | B37: 115 | C37: 126 | D37: 241
A38: Production | B38: 673 | C38: 381 | D38: 1054
A39: Sales | B39: 58 | C39: 113 | D39: 171
A40: Software Engineering | B40: 31 | C40: 38 | D40: 69
A41: Grand Total | B41: 908 | C41: 698 | D41: 1606
A49: State | B49: Count of Employee ID | D49: State | E49: Count of Employee ID
A50: MA | B50: 1427 | D50: =A50 -> MA | E50: =GETPIVOTDATA("Employee ID",$A$49,"State","MA") -> 1427
A51: TX | B51: 32 | D51: =A51 -> TX | E51: =GETPIVOTDATA("Employee ID",$A$49,"State","TX") -> 32
A52: CT | B52: 20 | D52: =A52 -> CT | E52: =GETPIVOTDATA("Employee ID",$A$49,"State","CT") -> 20
A53: ID | B53: 16 | D53: =A53 -> ID | E53: =GETPIVOTDATA("Employee ID",$A$49,"State","ID") -> 16
A54: TN | B54: 14 | D54: =A54 -> TN | E54: =GETPIVOTDATA("Employee ID",$A$49,"State","TN") -> 14
A55: AZ | B55: 14 | D55: =A55 -> AZ | E55: =GETPIVOTDATA("Employee ID",$A$49,"State","AZ") -> 14
A56: KY | B56: 13 | D56: =A56 -> KY | E56: =GETPIVOTDATA("Employee ID",$A$49,"State","KY") -> 13
A57: CO | B57: 11 | D57: =A57 -> CO | E57: =GETPIVOTDATA("Employee ID",$A$49,"State","CO") -> 11
A58: WA | B58: 10 | D58: =A58 -> WA | E58: =GETPIVOTDATA("Employee ID",$A$49,"State","WA") -> 10
A59: IN | B59: 9 | D59: =A59 -> IN | E59: =GETPIVOTDATA("Employee ID",$A$49,"State","IN") -> 9
A60: CA | B60: 6 | D60: =A60 -> CA | E60: =GETPIVOTDATA("Employee ID",$A$49,"State","CA") -> 6
A61: PA | B61: 5 | D61: =A61 -> PA | E61: =GETPIVOTDATA("Employee ID",$A$49,"State","PA") -> 5
A62: NY | B62: 4 | D62: =A62 -> NY | E62: =GETPIVOTDATA("Employee ID",$A$49,"State","NY") -> 4
A63: OR | B63: 4 | D63: =A63 -> OR | E63: =GETPIVOTDATA("Employee ID",$A$49,"State","OR") -> 4
A64: ND | B64: 4 | D64: =A64 -> ND | E64: =GETPIVOTDATA("Employee ID",$A$49,"State","ND") -> 4
A65: AL | B65: 4 | D65: =A65 -> AL | E65: =GETPIVOTDATA("Employee ID",$A$49,"State","AL") -> 4
A66: GA | B66: 2 | D66: =A66 -> GA | E66: =GETPIVOTDATA("Employee ID",$A$49,"State","GA") -> 2
A67: NC | B67: 2 | D67: =A67 -> NC | E67: =GETPIVOTDATA("Employee ID",$A$49,"State","NC") -> 2
A68: UT | B68: 2 | D68: =A68 -> UT | E68: =GETPIVOTDATA("Employee ID",$A$49,"State","UT") -> 2
A69: RI | B69: 2 | D69: =A69 -> RI | E69: =GETPIVOTDATA("Employee ID",$A$49,"State","RI") -> 2
A70: NH | B70: 2 | D70: =A70 -> NH | E70: =GETPIVOTDATA("Employee ID",$A$49,"State","NH") -> 2
A71: VA | B71: 1 | D71: =A71 -> VA | E71: =GETPIVOTDATA("Employee ID",$A$49,"State","VA") -> 1
A72: ME | B72: 1 | D72: =A72 -> ME | E72: =GETPIVOTDATA("Employee ID",$A$49,"State","ME") -> 1
A73: MT | B73: 1 | D73: =A73 -> MT | E73: =GETPIVOTDATA("Employee ID",$A$49,"State","MT") -> 1
A74: Grand Total | B74: 1606

Sheet Employee Turnover & Retention
A1: EmployeeStatus | B1: (Multiple Items)
A3: Row Labels | B3: Count of Employee ID
A4: Involuntary | B4: 153
A5: Resignation | B5: 133
A6: Retirement | B6: 138
A7: Voluntary | B7: 143
A8: Grand Total | B8: 567
A19: Department | B19: Average of Tenure (years)
A20: Executive Office | B20: 1.9450474
A21: Production | B21: 1.3464895
A22: IT/IS | B22: 1.2574558
A23: Sales | B23: 1.1075975
A24: Admin Offices | B24: 1.0839934
A25: Software Engineering | B25: 0.87081907
A26: Grand Total | B26: 1.2972024
A33: EmployeeStatus | B33: (Multiple Items)
A35: Turnover time | B35: Count of Employee ID
A36: 2018 | B36: 1
A37: 2019 | B37: 15
A38: 2020 | B38: 40
A39: 2021 | B39: 68
A40: 2022 | B40: 123
A41: 2023 | B41: 161
A42: Grand Total | B42: 408

Sheet Performance & Employee Engageme
A3: Performance | B3: Average of Satisfaction Score | C3: Average of Engagement Score
A4: Exceeds | B4: 2.7720207 | C4: 2.8134715
A5: Fully Meets | B5: 3.0694006 | C5: 2.9684543
A6: Needs Improvement | B6: 3.0106383 | C6: 2.9361702
A7: PIP | B7: 2.7843137 | C7: 2.7254902
A8: Grand Total | B8: 3.0211706 | C8: 2.9402242
A14: Pay Zone | B14: Average of Satisfaction Score
A15: Zone A | B15: 2.9677419
A16: Zone B | B16: 3.0833333
A17: Zone C | B17: 3.0137795
A18: Grand Total | B18: 3.0211706

Sheet Training & Development Analytic
A3: Tarining Program Name | B3: Sum of Training Cost | C3: Average of Training Duration(Days)
A4: Communication Skills | B4: 192132.22 | C4: 2.9719101
A5: Customer Service | B5: 172887.82 | C5: 2.9013158
A6: Leadership Development | B6: 175129.14 | C6: 3.0662252
A7: Project Management | B7: 174816.37 | C7: 3.0677419
A8: Technical Skills | B8: 184973.25 | C8: 2.8323353
A9: Grand Total | B9: 899938.8 | C9: 2.9657534
A17: Count of Training Outcome | B17: Column Labels
A18: Tarining Program Name | B18: Completed | C18: Failed | D18: Incomplete | E18: Passed | F18: Grand Total
A19: External | B19: 174 | C19: 216 | D19: 213 | E19: 194 | F19: 797
A20: Internal | B20: 214 | C20: 191 | D20: 215 | E20: 189 | F20: 809
A21: Grand Total | B21: 388 | C21: 407 | D21: 428 | E21: 383 | F21: 1606
A30: Buisness Unit | B30: Sum of Training Cost
A31: BPC | B31: 85818.91
A32: EW | B32: 85850.06
A33: PYZ | B33: 86822.93
A34: PL | B34: 87307.03
A35: MSC | B35: 88005.91
A36: CCDR | B36: 88760.66
A37: NEL | B37: 89292
A38: TNS | B38: 92413.29
A39: WBL | B39: 92788.7
A40: SVG | B40: 102879.31
A41: Grand Total | B41: 899938.8

Sheet KPIs
B9: Column Labels
B10: Completed | C10: Failed | D10: Incomplete | E10: Passed | F10: Grand Total
A11: Sum of Employee ID | B11: 993084 | C11: 1031933 | D11: 1079186 | E11: 932290 | F11: 4036493
B12: =GETPIVOTDATA("Employee ID",$A$9,"Training Outcome","Completed")/GETPIVOTDATA("Employee ID",$A$9) -> 0.24602644 | C12: =GETPIVOTDATA("Employee ID",$A$9,"Training Outcome","Failed")/GETPIVOTDATA("Employee ID",$A$9) -> 0.25565088 | D12: =GETPIVOTDATA("Employee ID",$A$9,"Training Outcome","Incomplete")/GETPIVOTDATA("Employee ID",$A$9) -> 0.26735733 | E12: =GETPIVOTDATA("Employee ID",$A$9,"Training Outcome","Passed")/GETPIVOTDATA("Employee ID",$A$9) -> 0.23096535 | F12: =SUM(B12:E12) -> 1
A16: Row Labels | B16: Average of Engagement Score | C16: Average of Satisfaction Score
A17: Female | B17: 2.9262115 | C17: 3.0187225
A18: Male | B18: 2.9584527 | C18: 3.0243553
A19: Grand Total | B19: 2.9402242 | C19: 3.0211706
A23: Row Labels | B23: Count of Employee ID
A24: Involuntary | B24: 407
A25: Resignation | B25: 397
A26: Retirement | B26: 393
A27: Voluntary | B27: 409
A28: Grand Total | B28: 1606
A31: Average of Tenure (years)
A32: 1.3393153
A35: Row Labels | B35: Sum of Employee ID
A36: Exceeds | B36: 0.11894508
A37: Fully Meets | B37: 0.784589
A38: Needs Improvement | B38: 0.058394255
A39: PIP | B39: 0.038071663
A40: Grand Total | B40: 1

Sheet HR_Dashboard (pg 4)

Sheet HR_Dashboard (pg 3)

Sheet HR_Dashboard (pg 2)

Sheet HR_Dashboard
G7: ''''''''''''''''''''''''''''''''''''''''''''''''
J12: =GETPIVOTDATA("Tenure (years)",KPIs!$A$31) -> 1.3393153 | M12: =GETPIVOTDATA("Employee ID",KPIs!$A$9,"Training Outcome","Completed") -> 993084 | P12: =GETPIVOTDATA("Employee ID",KPIs!$A$23) -> 1606 | T12: =GETPIVOTDATA("Average of Satisfaction Score",KPIs!$A$16) -> 3.0211706
G16: ][[][]][][][][[d
G24: ""

Sheet Cleaned_HR_Dataset_Detailed
A1: ID | B1: FirstName | C1: LastName | D1: StartDate | E1: ExitDate | F1: Turnover | G1: Tenure (years) | H1: Title | I1: Supervisor | J1: ADEmail | K1: BusinessUnit | L1: EmployeeStatus | M1: EmployeeType | N1: PayZone | O1: EmployeeClassificationType | P1: TerminationType | Q1: DepartmentType | R1: Division | S1: DOB | T1: State | U1: JobFunctionDescription | V1: GenderCode | W1: LocationCode | X1: Performance Score | Y1: Current Employee Rating | Z1: Employee ID | AA1: Survey Date | AB1: Engagement Score | AC1: Satisfaction Score | AD1: Training Date | AE1: Training Program Name | AF1: Training Type | AG1: Training Outcome | AH1: Location | AI1: Trainer | AJ1: Training Duration(Days) | AK1: Training Cost
A2: 6 | B2: Latia | C2: Costa | D2: 44657 | E2: 45110 | F2: =Table2[[#This Row],[ExitDate]]-Table2[[#This Row],[StartDate]] -> 453 | G2: =(Table2[[#This Row],[ExitDate]]-Table2[[#This Row],[StartDate]])/365.25 -> 1.2402464 | H2: Area Sales Manager | I2: Jacob Braun | J2: latia.costa@bilearner.com | K2: WBL | L2: Active | M2: Full-Time | N2: Zone B | O2: Temporary | P2: Involuntary | Q2: Sales | R2: General - Eng | S2: 15348 | T2: CA | U2: Technician | V2: Female | W2: 90007 | X2: Exceeds | Y2: 4 | Z2: 3433 | AA2: 25-03-2023 | AB2: 1 | AC2: 5 | AD2: 44779 | AE2: Customer Service | AF2: External | AG2: Passed | AH2: Lancehaven | AI2: David Stewart | AJ2: 5 | AK2: 295.08
A3: 7 | B3: Sharlene | C3: Terry | D3: 44141 | E3: 44955 | F3: =Table2[[#This Row],[ExitDate]]-Table2[[#This Row],[StartDate]] -> 814 | G3: =(Table2[[#This Row],[ExitDate]]-Table2[[#This Row],[StartDate]])/365.25 -> 2.2286105 | H3: Area Sales Manager | I3: Tracy Marquez | J3: sharlene.terry@bilearner.com | K3: CCDR | L3: Active | M3: Contract | N3: Zone C | O3: Full-Time | P3: Involuntary | Q3: Sales | R3: Engineers | S3: 21004 | T3: OR | U3: Engineer | V3: Female | W3: 97756 | X3: Fully Meets | Y3: 2 | Z3: 3434 | AA3: 21-04-2023 | AB3: 1 | AC3: 4 | AD3: 44841 | AE3: Leadership Development | AF3: Internal | AG3: Passed | AH3: Jeremyshire | AI3: Stephanie Garza | AJ3: 3 | AK3: 790.15
A4: 9 | B4: Joseph | C4: Martins | D4: 44582 | E4: 45106 | F4: =Table2[[#This Row],[ExitDate]]-Table2[[#This Row],[StartDate]] -> 524 | G4: =(Table2[[#This Row],[ExitDate]]-Table2[[#This Row],[StartDate]])/365.25 -> 1.4346338 | H4: Area Sales Manager | I4: George Jenkins | J4: joseph.martins@bilearner.com | K4: BPC | L4: Active | M4: Part-Time | N4: Zone B | O4: Temporary | P4: Resignation | Q4: Sales | R4: Engineers | S4: 18213 | T4: TX | U4: Engineer | V4: Male | W4: 78207 | X4: Fully Meets | Y4: 5 | Z4: 3436 | AA4: 30-07-2023 | AB4: 5 | AC4: 5 | AD4: 45025 | AE4: Leadership Development | AF4: Internal | AG4: Failed | AH4: Nicolebury | AI4: Megan Wilson | AJ4: 5 | AK4: 192.61
A5: 11 | B5: Dheepa | C5: Nguyen | D5: 43322 | E5: 43773 | F5: =Table2[[#This Row],[ExitDate]]-Table2[[#This Row],[StartDate]] -> 451 | G5: =(Table2[[#This Row],[ExitDate]]-Table2[[#This Row],[StartDate]])/365.25 -> 1.2347707 | H5: Area Sales Manager | I5: Brian Miller | J5: dheepa.nguyen@bilearner.com | K5: MSC | L5: Active | M5: Full-Time | N5: Zone C | O5: Temporary | P5: Retirement | Q5: Sales | R5: General - Con | S5: 17688 | T5: GA | U5: Technician | V5: Female | W5: 30428 | X5: Fully Meets | Y5: 3 | Z5: 3438 | AA5: 28-10-2022 | AB5: 4 | AC5: 2 | AD5: 44839 | AE5: Technical Skills | AF5: Internal | AG5: Failed | AH5: Nunezmouth | AI5: Sharon Flores DDS | AJ5: 2 | AK5: 208.17
A6: 12 | B6: Bartholemew | C6: Khemmich | D6: 44706 | E6: 44892 | F6: =Table2[[#This Row],[ExitDate]]-Table2[[#This Row],[StartDate]] -> 186 | G6: =(Table2[[#This Row],[ExitDate]]-Table2[[#This Row],[StartDate]])/365.25 -> 0.50924025 | H6: Area Sales Manager | I6: Charles Parks | J6: bartholemew.khemmich@bilearner.com | K6: EW | L6: Active | M6: Full-Time | N6: Zone A | O6: Temporary | P6: Involuntary | Q6: Sales | R6: Splicing | S6: 24-11-1981 | T6: CO | U6: Splicer | V6: Male | W6: 80820 | X6: Fully Meets | Y6: 3 | Z6: 3439 | AA6: 30-10-2022 | AB6: 1 | AC6: 2 | AD6: 44994 | AE6: Technical Skills | AF6: External | AG6: Incomplete | AH6: Port Margaretview | AI6: Kimberly Garcia | AJ6: 1 | AK6: 421.07
A7: 13 | B7: Xana | C7: Potts | D7: 43804 | E7: 44974 | F7: =Table2[[#This Row],[ExitDate]]-Table2[[#This Row],[StartDate]] -> 1170 | G7: =(Table2[[#This Row],[ExitDate]]-Table2[[#This Row],[StartDate]])/365.25 -> 3.2032854 | H7: Area Sales Manager | I7: Gregory Walker | J7: xana.potts@bilearner.com | K7: CCDR | L7: Active | M7: Contract | N7: Zone A | O7: Full-Time | P7: Resignation | Q7: Sales | R7: Finance & Accounting | S7: 18790 | T7: KY | U7: Controller | V7: Female | W7: 40220 | X7: Fully Meets | Y7: 3 | Z7: 3440 | AA7: 24-09-2022 | AB7: 1 | AC7: 4 | AD7: 45075 | AE7: Communication Skills | AF7: External | AG7: Failed | AH7: Nancyview | AI7: Christopher Underwood | AJ7: 1 | AK7: 649.03
A8: 15 | B8: Kaylah | C8: Moon | D8: 43655 | E8: 44728 | F8: =Table2[[#This Row],[ExitDate]]-Table2[[#This Row],[StartDate]] -> 1073 | G8: =(Table2[[#This Row],[ExitDate]]-Table2[[#This Row],[StartDate]])/365.25 -> 2.9377139 | H8: Area Sales Manager | I8: Ashley Scott | J8: kaylah.moon@bilearner.com | K8: PYZ | L8: Active | M8: Full-Time | N8: Zone A | O8: Full-Time | P8: Retirement | Q8: IT/IS | R8: Field Operations | S8: 24-11-1952 | T8: MA | U8: Laborer | V8: Male | W8: 2810 | X8: Exceeds | Y8: 2 | Z8: 3442 | AA8: 31-10-2022 | AB8: 2 | AC8: 5 | AD8: 44991 | AE8: Project Management | AF8: External | AG8: Failed | AH8: Port Davidshire | AI8: Victoria Berry | AJ8: 4 | AK8: 286.87
A9: 16 | B9: Kristen | C9: Tate | D9: 44291 | E9: 45058 | F9: =Table2[[#This Row],[ExitDate]]-Table2[[#This Row],[StartDate]] -> 767 | G9: =(Table2[[#This Row],[ExitDate]]-Table2[[#This Row],[StartDate]])/365.25 -> 2.0999316 | H9: Area Sales Manager | I9: Lauren Jones | J9: kristen.tate@bilearner.com | K9: WBL | L9: Active | M9: Full-Time | N9: Zone C | O9: Part-Time | P9: Voluntary | Q9: IT/IS | R9: Project Management - Con | S9: 34550 | T9: KY | U9: Coordinator | V9: Male | W9: 2621 | X9: Fully Meets | Y9: 3 | Z9: 3443 | AA9: 29-04-2023 | AB9: 2 | AC9: 2 | AD9: 44975 | AE9: Technical Skills | AF9: External | AG9: Failed | AH9: East Katie | AI9: Gary Thornton | AJ9: 3 | AK9: 402.13
A10: 17 | B10: Bobby | C10: Rodgers | D10: 44528 | E10: 44596 | F10: =Table2[[#This Row],[ExitDate]]-Table2[[#This Row],[StartDate]] -> 68 | G10: =(Table2[[#This Row],[ExitDate]]-Table2[[#This Row],[StartDate]])/365.25 -> 0.18617385 | H10: Area Sales Manager | I10: Matthew Jackson | J10: bobby.rodgers@bilearner.com | K10: NEL | L10: Active | M10: Contract | N10: Zone A | O10: Part-Time | P10: Voluntary | Q10: Sales | R10: Engineers | S10: 15-11-1983 | T10: KY | U10: Director | V10: Male | W10: 44553 | X10: Fully Meets | Y10: 3 | Z10: 3444 | AA10: 14-12-2022 | AB10: 1 | AC10: 2 | AD10: 44867 | AE10: Technical Skills | AF10: External | AG10: Failed | AH10: Jacobburgh | AI10: William Willis | AJ10: 2 | AK10: 388.84
A11: 20 | B11: Mariela | C11: Schultz | D11: 43977 | E11: 45095 | F11: =Table2[[#This Row],[ExitDate]]-Table2[[#This Row],[StartDate]] -> 1118 | G11: =(Table2[[#This Row],[ExitDate]]-Table2[[#This Row],[StartDate]])/365.25 -> 3.0609172 | H11: Area Sales Manager | I11: Michelle Evans MD | J11: mariela.schultz@bilearner.com | K11: CCDR | L11: Future Start | M11: Part-Time | N11: Zone C | O11: Part-Time | P11: Involuntary | Q11: Sales | R11: General - Con | S11: 17-02-1964 | T11: TX | U11: Technician | V11: Female | W11: 43481 | X11: Fully Meets | Y11: 3 | Z11: 3447 | AA11: 45143 | AB11: 5 | AC11: 1 | AD11: 45018 | AE11: Customer Service | AF11: Internal | AG11: Incomplete | AH11: Kristenton | AI11: Kimberly Doyle | AJ11: 3 | AK11: 353.21
A12: 21 | B12: Angela | C12: Molina | D12: 43739 | E12: 44141 | F12: =Table2[[#This Row],[ExitDate]]-Table2[[#This Row],[StartDate]] -> 402 | G12: =(Table2[[#This Row],[ExitDate]]-Table2[[#This Row],[StartDate]])/365.25 -> 1.100616 | H12: Area Sales Manager | I12: Patricia Cook | J12: angela.molina@bilearner.com | K12: SVG | L12: Future Start | M12: Full-Time | N12: Zone A | O12: Temporary | P12: Retirement | Q12: Sales | R12: Engineers | S12: 21524 | T12: TX | U12: Specialist | V12: Male | W12: 50705 | X12: Fully Meets | Y12: 3 | Z12: 3448 | AA12: 28-03-2023 | AB12: 5 | AC12: 1 | AD12: 45062 | AE12: Communication Skills | AF12: Internal | AG12: Completed | AH12: West Jamesview | AI12: Lindsay Williams | AJ12: 4 | AK12: 911.05
A13: 22 | B13: Gerald | C13: Preston | D13: 45056 | E13: 45073 | F13: =Table2[[#This Row],[ExitDate]]-Table2[[#This Row],[StartDate]] -> 17 | G13: =(Table2[[#This Row],[ExitDate]]-Table2[[#This Row],[StartDate]])/365.25 -> 0.046543463 | H13: Area Sales Manager | I13: Ashley Reeves | J13: gerald.preston@bilearner.com | K13: EW | L13: Future Start | M13: Contract | N13: Zone B | O13: Temporary | P13: Involuntary | Q13: Sales | R13: General - Eng | S13: 18-09-1992 | T13: CO | U13: Technician | V13: Male | W13: 5168 | X13: Fully Meets | Y13: 5 | Z13: 3449 | AA13: 30-06-2023 | AB13: 3 | AC13: 2 | AD13: 44836 | AE13: Communication Skills | AF13: External | AG13: Completed | AH13: Josebury | AI13: Joseph Faulkner | AJ13: 3 | AK13: 242.21
A14: 23 | B14: Reilly | C14: Moyer | D14: 44075 | E14: 44899 | F14: =Table2[[#This Row],[ExitDate]]-Table2[[#This Row],[StartDate]] -> 824 | G14: =(Table2[[#This Row],[ExitDate]]-Table2[[#This Row],[StartDate]])/365.25 -> 2.255989 | H14: Area Sales Manager | I14: Stanley Harvey | J14: reilly.moyer@bilearner.com | K14: MSC | L14: Active | M14: Contract | N14: Zone C | O14: Temporary | P14: Resignation | Q14: Sales | R14: Field Operations | S14: 34646 | T14: CO | U14: Operator | V14: Male | W14: 11765 | X14: Exceeds | Y14: 2 | Z14: 3450 | AA14: 18-01-2023 | AB14: 4 | AC14: 3 | AD14: 44938 | AE14: Technical Skills | AF14: Internal | AG14: Completed | AH14: South Benjaminfurt | AI14: Laura Davis | AJ14: 4 | AK14: 186.07
A15: 24 | B15: Carlee | C15: French | D15: 44245 | E15: 44876 | F15: =Table2[[#This Row],[ExitDate]]-Table2[[#This Row],[StartDate]] -> 631 | G15: =(Table2[[#This Row],[ExitDate]]-Table2[[#This Row],[StartDate]])/365.25 -> 1.7275838 | H15: Area Sales Manager | I15: Michael Bradshaw | J15: carlee.french@bilearner.com | K15: TNS | L15: Active | M15: Contract | N15: Zone C | O15: Full-Time | P15: Voluntary | Q15: Sales | R15: General - Con | S15: 15-01-1968 | T15: CO | U15: Technician | V15: Male | W15: 71071 | X15: Exceeds | Y15: 3 | Z15: 3451 | AA15: 29-04-2023 | AB15: 5 | AC15: 1 | AD15: 45007 | AE15: Technical Skills | AF15: External | AG15: Completed | AH15: Duncanview | AI15: d | AJ15: 1 | AK15: 921.97
A16: 28 | B16: Charity | C16: Miranda | D16: 44376 | E16: 44747 | F16: =Table2[[#This Row],[ExitDate]]-Table2[[#This Row],[StartDate]] -> 371 | G16: =(Table2[[#This Row],[ExitDate]]-Table2[[#This Row],[StartDate]])/365.25 -> 1.0157426 | H16: Area Sales Manager | I16: Daniel Rodriguez | J16: charity.miranda@bilearner.com | K16: WBL | L16: Active | M16: Full-Time | N16: Zone C | O16: Temporary | P16: Resignation | Q16: Sales | R16: Project Management - Eng | S16: 18-01-1999 | T16: KY | U16: Manager | V16: Male | W16: 3763 | X16: Exceeds | Y16: 4 | Z16: 3455 | AA16: 44903 | AB16: 2 | AC16: 1 | AD16: 45002 | AE16: Project Management | AF16: External | AG16: Passed | AH16: Wadefurt | AI16: Timothy Moreno | AJ16: 1 | AK16: 220.41
A17: 31 | B17: Cory | C17: Robinson | D17: 44679 | E17: 45070 | F17: =Table2[[#This Row],[ExitDate]]-Table2[[#This Row],[StartDate]] -> 391 | G17: =(Table2[[#This Row],[ExitDate]]-Table2[[#This Row],[StartDate]])/365.25 -> 1.0704997 | H17: Area Sales Manager | I17: Elizabeth Anderson | J17: cory.robinson@bilearner.com | K17: BPC | L17: Future Start | M17: Contract | N17: Zone A | O17: Full-Time | P17: Voluntary | Q17: Sales | R17: Field Operations | S17: 35407 | T17: TX | U17: Laborer | V17: Female | W17: 5194 | X17: Needs Improvement | Y17: 3 | Z17: 3458 | AA17: 14-02-2023 | AB17: 2 | AC17: 5 | AD17: 44897 | AE17: Communication Skills | AF17: Internal | AG17: Failed | AH17: North Deborahville | AI17: Joseph Ward | AJ17: 2 | AK17: 409.27
A18: 32 | B18: Saniya | C18: Yu | D18: 44304 | E18: 44733 | F18: =Table2[[#This Row],[ExitDate]]-Table2[[#This Row],[StartDate]] -> 429 | G18: =(Table2[[#This Row],[ExitDate]]-Table2[[#This Row],[StartDate]])/365.25 -> 1.174538 | H18: Area Sales Manager | I18: Erin Bailey | J18: saniya.yu@bilearner.com | K18: CCDR | L18: Future Start | M18: Part-Time | N18: Zone A | O18: Full-Time | P18: Retirement | Q18: Sales | R18: General - Con | S18: 16317 | T18: TX | U18: Splicer | V18: Male | W18: 8779 | X18: Exceeds | Y18: 2 | Z18: 3459 | AA18: 26-10-2022 | AB18: 4 | AC18: 4 | AD18: 45091 | AE18: Communication Skills | AF18: Internal | AG18: Passed | AH18: Chapmanbury | AI18: Joseph Thomas | AJ18: 4 | AK18: 168.32
A19: 34 | B19: Lincoln | C19: Compton | D19: 43664 | E19: 44470 | F19: =Table2[[#This Row],[ExitDate]]-Table2[[#This Row],[StartDate]] -> 806 | G19: =(Table2[[#This Row],[ExitDate]]-Table2[[#This Row],[StartDate]])/365.25 -> 2.2067077 | H19: Area Sales Manager | I19: Tammy Conner | J19: lincoln.compton@bilearner.com | K19: EW | L19: Future Start | M19: Full-Time | N19: Zone C | O19: Part-Time | P19: Resignation | Q19: Sales | R19: General - Con | S19: 29-12-1997 | T19: CO | U19: Foreman | V19: Male | W19: 78046 | X19: Needs Improvement | Y19: 1 | Z19: 3461 | AA19: 24-04-2023 | AB19: 1 | AC19: 4 | AD19: 44931 | AE19: Technical Skills | AF19: External | AG19: Completed | AH19: Taylorland | AI19: Micheal Munoz | AJ19: 2 | AK19: 948.43
A20: 35 | B20: Aliana | C20: Nolan | D20: 43356 | E20: 44456 | F20: =Table2[[#This Row],[ExitDate]]-Table2[[#This Row],[StartDate]] -> 1100 | G20: =(Table2[[#This Row],[ExitDate]]-Table2[[#This Row],[StartDate]])/365.25 -> 3.0116359 | H20: Area Sales Manager | I20: Brianna Mathews | J20: aliana.nolan@bilearner.com | K20: MSC | L20: Active | M20: Contract | N20: Zone A | O20: Full-Time | P20: Involuntary | Q20: Sales | R20: Field Operations | S20: 15592 | T20: CO | U20: Coordinator | V20: Male | W20: 27270 | X20: Needs Improvement | Y20: 3 | Z20: 3462 | AA20: 44784 | AB20: 3 | AC20: 3 | AD20: 45126 | AE20: Project Management | AF20: External | AG20: Completed | AH20: Erinville | AI20: Stacey Esparza | AJ20: 1 | AK20: 320.01
A21: 36 | B21: Kayden | C21: Dodson | D21: 43951 | E21: 44395 | F21: =Table2[[#This Row],[ExitDate]]-Table2[[#This Row],[StartDate]] -> 444 | G21: =(Table2[[#This Row],[ExitDate]]-Table2[[#This Row],[StartDate]])/365.25 -> 1.2156057 | H21: Area Sales Manager | I21: Jessica Peters | J21: kayden.dodson@bilearner.com | K21: TNS | L21: Active | M21: Part-Time | N21: Zone A | O21: Temporary | P21: Retirement | Q21: Sales | R21: Field Operations | S21: 21-06-1951 | T21: IN | U21: Tower Hand | V21: Male | W21: 12703 | X21: Fully Meets | Y21: 1 | Z21: 3463 | AA21: 18-09-2022 | AB21: 4 | AC21: 3 | AD21: 44802 | AE21: Technical Skills | AF21: Internal | AG21: Incomplete | AH21: Harperchester | AI21: Heather Edwards | AJ21: 4 | AK21: 926.19
A22: 37 | B22: James | C22: Duke | D22: 43437 | E22: 44813 | F22: =Table2[[#This Row],[ExitDate]]-Table2[[#This Row],[StartDate]] -> 1376 | G22: =(Table2[[#This Row],[ExitDate]]-Table2[[#This Row],[StartDate]])/365.25 -> 3.7672827 | H22: Area Sales Manager | I22: Mark Harris | J22: james.duke@bilearner.com | K22: PYZ | L22: Active | M22: Contract | N22: Zone B | O22: Full-Time | P22: Involuntary | Q22: Sales | R22: Shop (Fleet) | S22: 17-06-1998 | T22: MA | U22: Mechanic | V22: Male | W22: 66835 | X22: Needs Improvement | Y22: 5 | Z22: 3464 | AA22: 29-12-2022 | AB22: 2 | AC22: 5 | AD22: 44878 | AE22: Customer Service | AF22: External | AG22: Passed | AH22: Trevorside | AI22: Michaela Wright | AJ22: 2 | AK22: 290.47
A23: 39 | B23: Clayton | C23: Walker | D23: 44664 | E23: 45026 | F23: =Table2[[#This Row],[ExitDate]]-Table2[[#This Row],[StartDate]] -> 362 | G23: =(Table2[[#This Row],[ExitDate]]-Table2[[#This Row],[StartDate]])/365.25 -> 0.99110198 | H23: Area Sales Manager | I23: Jon Holden | J23: clayton.walker@bilearner.com | K23: PYZ | L23: Active | M23: Part-Time | N23: Zone C | O23: Full-Time | P23: Retirement | Q23: IT/IS | R23: Aerial | S23: 26-01-1979 | T23: KY | U23: Supervisor | V23: Male | W23: 64288 | X23: Exceeds | Y23: 4 | Z23: 3466 | AA23: 45024 | AB23: 1 | AC23: 3 | AD23: 44902 | AE23: Customer Service | AF23: External | AG23: Passed | AH23: West Angelaside | AI23: Erika Jackson | AJ23: 3 | AK23: 447.66
A24: 42 | B24: Ryland | C24: Shepherd | D24: 44041 | E24: 44931 | F24: =Table2[[#This Row],[ExitDate]]-Table2[[#This Row],[StartDate]] -> 890 | G24: =(Table2[[#This Row],[ExitDate]]-Table2[[#This Row],[StartDate]])/365.25 -> 2.4366872 | H24: Area Sales Manager | I24: James Berry | J24: ryland.shepherd@bilearner.com | K24: PL | L24: Future Start | M24: Contract | N24: Zone B | O24: Full-Time | P24: Resignation | Q24: Sales | R24: Field Operations | S24: 21-02-1945 | T24: TX | U24: Driver | V24: Female | W24: 81905 | X24: Needs Improvement | Y24: 3 | Z24: 3469 | AA24: 44934 | AB24: 5 | AC24: 5 | AD24: 44788 | AE24: Communication Skills | AF24: Internal | AG24: Failed | AH24: North Jeanetteville | AI24: Lisa Barnes | AJ24: 2 | AK24: 552.54
A25: 43 | B25: Esteban | C25: Gilbert | D25: 43418 | E25: 43766 | F25: =Table2[[#This Row],[ExitDate]]-Table2[[#This Row],[StartDate]] -> 348 | G25: =(Table2[[#This Row],[ExitDate]]-Table2[[#This Row],[StartDate]])/365.25 -> 0.95277207 | H25: Area Sales Manager | I25: Gail Ali | J25: esteban.gilbert@bilearner.com | K25: BPC | L25: Future Start | M25: Contract | N25: Zone C | O25: Part-Time | P25: Retirement | Q25: Sales | R25: Field Operations | S25: 31-05-1997 | T25: TX | U25: Technician | V25: Female | W25: 12491 | X25: Needs Improvement | Y25: 3 | Z25: 3470 | AA25: 45082 | AB25: 1 | AC25: 2 | AD25: 44830 | AE25: Project Management | AF25: External | AG25: Passed | AH25: New Molly | AI25: Katie Wong MD | AJ25: 1 | AK25: 986.96
A26: 48 | B26: Vance | C26: Trujillo | D26: 44460 | E26: 45029 | F26: =Table2[[#This Row],[ExitDate]]-Table2[[#This Row],[StartDate]] -> 569 | G26: =(Table2[[#This Row],[ExitDate]]-Table2[[#This Row],[StartDate]])/365.25 -> 1.5578371 | H26: Area Sales Manager | I26: Rebecca Simpson | J26: vance.trujillo@bilearner.com | K26: TNS | L26: Active | M26: Full-Time | N26: Zone C | O26: Temporary | P26: Resignation | Q26: Sales | R26: General - Con | S26: 25-12-1957 | T26: IN | U26: Foreman | V26: Male | W26: 90406 | X26: Fully Meets | Y26: 2 | Z26: 3475 | AA26: 25-01-2023 | AB26: 4 | AC26: 3 | AD26: 44867 | AE26: Customer Service | AF26: Internal | AG26: Passed | AH26: South Taylorfurt | AI26: Jenna Sherman | AJ26: 2 | AK26: 648.76
A27: 49 | B27: Charlie | C27: Koch | D27: 45089 | E27: 45113 | F27: =Table2[[#This Row],[ExitDate]]-Table2[[#This Row],[StartDate]] -> 24 | G27: =(Table2[[#This Row],[ExitDate]]-Table2[[#This Row],[StartDate]])/365.25 -> 0.065708419 | H27: Area Sales Manager | I27: Samantha Cardenas | J27: charlie.koch@bilearner.com | K27: PYZ | L27: Active | M27: Part-Time | N27: Zone A | O27: Temporary | P27: Voluntary | Q27: Sales | R27: Fielders | S27: 20-06-1945 | T27: MA | U27: Engineer | V27: Male | W27: 95774 | X27: Needs Improvement | Y27: 2 | Z27: 3476 | AA27: 44988 | AB27: 5 | AC27: 5 | AD27: 44883 | AE27: Leadership Development | AF27: Internal | AG27: Incomplete | AH27: Stephanieshire | AI27: Dr. Margaret Allen | AJ27: 4 | AK27: 533.5
A28: 51 | B28: Thomas | C28: Chandler | D28: 43360 | E28: 43474 | F28: =Table2[[#This Row],[ExitDate]]-Table2[[#This Row],[StartDate]] -> 114 | G28: =(Table2[[#This Row],[ExitDate]]-Table2[[#This Row],[StartDate]])/365.25 -> 0.31211499 | H28: Area Sales Manager | I28: Richard Hodges | J28: thomas.chandler@bilearner.com | K28: WBL | L28: Active | M28: Full-Time | N28: Zone C | O28: Temporary | P28: Resignation | Q28: Sales | R28: Wireline Construction | S28: 21103 | T28: KY | U28: Groundman | V28: Female | W28: 45149 | X28: Fully Meets | Y28: 2 | Z28: 3478 | AA28: 29-11-2022 | AB28: 3 | AC28: 4 | AD28: 44839 | AE28: Technical Skills | AF28: External | AG28: Incomplete | AH28: Port Matthew | AI28: Daniel Solomon | AJ28: 1 | AK28: 526.74
A29: 52 | B29: Sarai | C29: Stone | D29: 44775 | E29: 45018 | F29: =Table2[[#This Row],[ExitDate]]-Table2[[#This Row],[StartDate]] -> 243 | G29: =(Table2[[#This Row],[ExitDate]]-Table2[[#This Row],[StartDate]])/365.25 -> 0.66529774 | H29: Area Sales Manager | I29: Madison Wilson | J29: sarai.stone@bilearner.com | K29: NEL | L29: Active | M29: Contract | N29: Zone A | O29: Part-Time | P29: Involuntary | Q29: Sales | R29: Project Management - Con | S29: 17-05-1962 | T29: TX | U29: Technician | V29: Female | W29: 96336 | X29: Fully Meets | Y29: 2 | Z29: 3479 | AA29: 44631 | AB29: 4 | AC29: 4 | AD29: 44944 | AE29: Communication Skills | AF29: Internal | AG29: Passed | AH29: Stephanieburgh | AI29: Michael Dixon | AJ29: 3 | AK29: 443.45
A30: 53 | B30: Jerimiah | C30: Harmon | D30: 44812 | E30: 44850 | F30: =Table2[[#This Row],[ExitDate]]-Table2[[#This Row],[StartDate]] -> 38 | G30: =(Table2[[#This Row],[ExitDate]]-Table2[[#This Row],[StartDate]])/365.25 -> 0.10403833 | H30: Area Sales Manager | I30: Eric King | J30: jerimiah.harmon@bilearner.com | K30: PL | L30: Future Start | M30: Full-Time | N30: Zone C | O30: Temporary | P30: Retirement | Q30: Sales | R30: Catv | S30: 17053 | T30: TX | U30: Supervisor | V30: Female | W30: 75671 | X30: Fully Meets | Y30: 1 | Z30: 3480 | AA30: 25-07-2023 | AB30: 1 | AC30: 5 | AD30: 44987 | AE30: Leadership Development | AF30: External | AG30: Failed | AH30: North Amyfurt | AI30: Robert Hill | AJ30: 1 | AK30: 887.15
A31: 54 | B31: Leland | C31: Allen | D31: 43531 | E31: 44347 | F31: =Table2[[#This Row],[ExitDate]]-Table2[[#This Row],[StartDate]] -> 816 | G31: =(Table2[[#This Row],[ExitDate]]-Table2[[#This Row],[StartDate]])/365.25 -> 2.2340862 | H31: Area Sales Manager | I31: Brandon Harris | J31: leland.allen@bilearner.com | K31: BPC | L31: Future Start | M31: Full-Time | N31: Zone C | O31: Part-Time | P31: Voluntary | Q31: Sales | R31: Wireline Construction | S31: 24058 | T31: TX | U31: Splicer | V31: Male | W31: 61149 | X31: Fully Meets | Y31: 4 | Z31: 3481 | AA31: 44960 | AB31: 5 | AC31: 2 | AD31: 45075 | AE31: Technical Skills | AF31: External | AG31: Incomplete | AH31: East Charleston | AI31: Glenda Ryan | AJ31: 5 | AK31: 758.95
A32: 55 | B32: Cristal | C32: Bolton | D32: 43767 | E32: 44234 | F32: =Table2[[#This Row],[ExitDate]]-Table2[[#This Row],[StartDate]] -> 467 | G32: =(Table2[[#This Row],[ExitDate]]-Table2[[#This Row],[StartDate]])/365.25 -> 1.2785763 | H32: Area Sales Manager | I32: Matthew Flores | J32: cristal.bolton@bilearner.com | K32: CCDR | L32: Future Start | M32: Full-Time | N32: Zone A | O32: Temporary | P32: Resignation | Q32: Sales | R32: Catv | S32: 33179 | T32: TX | U32: Lineman | V32: Male | W32: 57302 | X32: Needs Improvement | Y32: 2 | Z32: 3482 | AA32: 22-10-2022 | AB32: 4 | AC32: 5 | AD32: 44988 | AE32: Technical Skills | AF32: Internal | AG32: Failed | AH32: Saraland | AI32: Jennifer Brown | AJ32: 1 | AK32: 627.11
A33: 59 | B33: Brendon | C33: Mcconnell | D33: 44865 | E33: 45085 | F33: =Table2[[#This Row],[ExitDate]]-Table2[[#This Row],[StartDate]] -> 220 | G33: =(Table2[[#This Row],[ExitDate]]-Table2[[#This Row],[StartDate]])/365.25 -> 0.60232717 | H33: Area Sales Manager | I33: Victoria Krause | J33: brendon.mcconnell@bilearner.com | K33: TNS | L33: Active | M33: Part-Time | N33: Zone C | O33: Temporary | P33: Involuntary | Q33: Sales | R33: Fielders | S33: 14-11-1990 | T33: IN | U33: Engineer | V33: Male | W33: 19665 | X33: Fully Meets | Y33: 4 | Z33: 3486 | AA33: 27-08-2022 | AB33: 3 | AC33: 1 | AD33: 45130 | AE33: Project Management | AF33: Internal | AG33: Completed | AH33: Lake Angelafort | AI33: Daniel Jones | AJ33: 5 | AK33: 812.59
A34: 68 | B34: Tia | C34: Ellis | D34: 45099 | E34: 45129 | F34: =Table2[[#This Row],[ExitDate]]-Table2[[#This Row],[StartDate]] -> 30 | G34: =(Table2[[#This Row],[ExitDate]]-Table2[[#This Row],[StartDate]])/365.25 -> 0.082135524 | H34: Area Sales Manager | I34: Daniel Cabrera | J34: tia.ellis@bilearner.com | K34: TNS | L34: Active | M34: Part-Time | N34: Zone B | O34: Temporary | P34: Retirement | Q34: Sales | R34: Wireline Construction | S34: 27-01-1993 | T34: IN | U34: Laborer | V34: Male | W34: 1115 | X34: Fully Meets | Y34: 4 | Z34: 3495 | AA34: 44782 | AB34: 4 | AC34: 3 | AD34: 44916 | AE34: Customer Service | AF34: External | AG34: Passed | AH34: Port Andrew | AI34: Christian Higgins | AJ34: 1 | AK34: 701.55
A35: 71 | B35: Joel | C35: Mcmillan | D35: 45042 | E35: 45099 | F35: =Table2[[#This Row],[ExitDate]]-Table2[[#This Row],[StartDate]] -> 57 | G35: =(Table2[[#This Row],[ExitDate]]-Table2[[#This Row],[StartDate]])/365.25 -> 0.15605749 | H35: Area Sales Manager | I35: Peter Harvey | J35: joel.mcmillan@bilearner.com | K35: PYZ | L35: Active | M35: Full-Time | N35: Zone A | O35: Full-Time | P35: Voluntary | Q35: Sales | R35: General - Sga | S35: 17-10-1998 | T35: KY | U35: Laborer | V35: Female | W35: 36087 | X35: Fully Meets | Y35: 2 | Z35: 3498 | AA35: 19-06-2023 | AB35: 3 | AC35: 3 | AD35: 45076 | AE35: Project Management | AF35: External | AG35: Failed | AH35: Yorkport | AI35: Amy Clark | AJ35: 1 | AK35: 208.43
A36: 72 | B36: Maci | C36: Frost | D36: 43368 | E36: 44550 | F36: =Table2[[#This Row],[ExitDate]]-Table2[[#This Row],[StartDate]] -> 1182 | G36: =(Table2[[#This Row],[ExitDate]]-Table2[[#This Row],[StartDate]])/365.25 -> 3.2361396 | H36: Area Sales Manager | I36: Patrick Daniel | J36: maci.frost@bilearner.com | K36: WBL | L36: Active | M36: Part-Time | N36: Zone C | O36: Temporary | P36: Involuntary | Q36: Sales | R36: Field Operations | S36: 16-01-1971 | T36: KY | U36: Technician | V36: Female | W36: 61457 | X36: Fully Meets | Y36: 5 | Z36: 3499 | AA36: 21-07-2023 | AB36: 5 | AC36: 3 | AD36: 44956 | AE36: Technical Skills | AF36: Internal | AG36: Incomplete | AH36: East Bradley | AI36: Angela Lee | AJ36: 2 | AK36: 762.45
A37: 73 | B37: Nevaeh | C37: Lucas | D37: 43424 | E37: 44003 | F37: =Table2[[#This Row],[ExitDate]]-Table2[[#This Row],[StartDate]] -> 579 | G37: =(Table2[[#This Row],[ExitDate]]-Table2[[#This Row],[StartDate]])/365.25 -> 1.5852156 | H37: Area Sales Manager | I37: Bryan Douglas | J37: nevaeh.lucas@bilearner.com | K37: NEL | L37: Active | M37: Full-Time | N37: Zone B | O37: Part-Time | P37: Voluntary | Q37: Sales | R37: Shop (Fleet) | S37: 25-02-2000 | T37: TX | U37: Mechanic | V37: Female | W37: 80424 | X37: Fully Meets | Y37: 1 | Z37: 3500 | AA37: 14-05-2023 | AB37: 4 | AC37: 1 | AD37: 45092 | AE37: Leadership Development | AF37: External | AG37: Incomplete | AH37: Smithchester | AI37: Larry Morales | AJ37: 4 | AK37: 779.79
A38: 74 | B38: Garrett | C38: Zimmerman | D38: 44073 | E38: 44803 | F38: =Table2[[#This Row],[ExitDate]]-Table2[[#This Row],[StartDate]] -> 730 | G38: =(Table2[[#This Row],[ExitDate]]-Table2[[#This Row],[StartDate]])/365.25 -> 1.9986311 | H38: Area Sales Manager | I38: Destiny Hopkins | J38: garrett.zimmerman@bilearner.com | K38: PL | L38: Future Start | M38: Part-Time | N38: Zone A | O38: Part-Time | P38: Retirement | Q38: Sales | R38: General - Con | S38: 19-04-1959 | T38: TX | U38: Technician | V38: Male | W38: 6240 | X38: Fully Meets | Y38: 4 | Z38: 3501 | AA38: 20-02-2023 | AB38: 2 | AC38: 3 | AD38: 45086 | AE38: Project Management | AF38: External | AG38: Passed | AH38: South Kaylachester | AI38: Troy Adams | AJ38: 3 | AK38: 135.95
A39: 79 | B39: Laila | C39: Woodard | D39: 43704 | E39: 45056 | F39: =Table2[[#This Row],[ExitDate]]-Table2[[#This Row],[StartDate]] -> 1352 | G39: =(Table2[[#This Row],[ExitDate]]-Table2[[#This Row],[StartDate]])/365.25 -> 3.7015743 | H39: Area Sales Manager | I39: Jordan Vega | J39: laila.woodard@bilearner.com | K39: MSC | L39: Active | M39: Full-Time | N39: Zone B | O39: Temporary | P39: Voluntary | Q39: Sales | R39: Field Operations | S39: 32301 | T39: IN | U39: Technician | V39: Male | W39: 38740 | X39: Fully Meets | Y39: 2 | Z39: 3506 | AA39: 27-06-2023 | AB39: 2 | AC39: 2 | AD39: 45067 | AE39: Leadership Development | AF39: Internal | AG39: Completed | AH39: Deleonport | AI39: Jonathan Peterson | AJ39: 1 | AK39: 781.81
A40: 80 | B40: Ivan | C40: Huff | D40: 44252 | E40: 45023 | F40: =Table2[[#This Row],[ExitDate]]-Table2[[#This Row],[StartDate]] -> 771 | G40: =(Table2[[#This Row],[ExitDate]]-Table2[[#This Row],[StartDate]])/365.25 -> 2.110883 | H40: Area Sales Manager | I40: John Miller | J40: ivan.huff@bilearner.com | K40: TNS | L40: Active | M40: Full-Time | N40: Zone A | O40: Full-Time | P40: Retirement | Q40: Sales | R40: Project Management - Con | S40: 24-03-1973 | T40: CA | U40: Manager | V40: Male | W40: 9437 | X40: Fully Meets | Y40: 4 | Z40: 3507 | AA40: 31-03-2023 | AB40: 2 | AC40: 5 | AD40: 45071 | AE40: Project Management | AF40: Internal | AG40: Passed | AH40: Loriberg | AI40: Michael Copeland | AJ40: 4 | AK40: 651.77
A41: 84 | B41: Karli | C41: Barker | D41: 44425 | E41: 44561 | F41: =Table2[[#This Row],[ExitDate]]-Table2[[#This Row],[StartDate]] -> 136 | G41: =(Table2[[#This Row],[ExitDate]]-Table2[[#This Row],[StartDate]])/365.25 -> 0.37234771 | H41: Area Sales Manager | I41: Shawn Dudley | J41: karli.barker@bilearner.com | K41: WBL | L41: Active | M41: Part-Time | N41: Zone B | O41: Full-Time | P41: Resignation | Q41: Sales | R41: Finance & Accounting | S41: 18-02-1997 | T41: KY | U41: Director | V41: Female | W41: 41111 | X41: Fully Meets | Y41: 4 | Z41: 3511 | AA41: 45235 | AB41: 5 | AC41: 4 | AD41: 45023 | AE41: Technical Skills | AF41: Internal | AG41: Completed | AH41: Anthonyville | AI41: Juan Peck | AJ41: 3 | AK41: 344.44
A42: 85 | B42: Tyrone | C42: Sosa | D42: 45033 | E42: 45099 | F42: =Table2[[#This Row],[ExitDate]]-Table2[[#This Row],[StartDate]] -> 66 | G42: =(Table2[[#This Row],[ExitDate]]-Table2[[#This Row],[StartDate]])/365.25 -> 0.18069815 | H42: Area Sales Manager | I42: Lindsay Chang | J42: tyrone.sosa@bilearner.com | K42: NEL | L42: Future Start | M42: Contract | N42: Zone C | O42: Temporary | P42: Voluntary | Q42: Sales | R42: Yard (Material Handling) | S42: 25-10-1996 | T42: TX | U42: Coordinator | V42: Female | W42: 58860 | X42: Fully Meets | Y42: 2 | Z42: 3512 | AA42: 20-02-2023 | AB42: 5 | AC42: 1 | AD42: 44890 | AE42: Communication Skills | AF42: Internal | AG42: Failed | AH42: Bryantport | AI42: Sharon Miller | AJ42: 2 | AK42: 206.44
A43: 86 | B43: Damaris | C43: Cisneros | D43: 44806 | E43: 45070 | F43: =Table2[[#This Row],[ExitDate]]-Table2[[#This Row],[StartDate]] -> 264 | G43: =(Table2[[#This Row],[ExitDate]]-Table2[[#This Row],[StartDate]])/365.25 -> 0.72279261 | H43: Area Sales Manager | I43: Sharon Ruiz | J43: damaris.cisneros@bilearner.com | K43: PL | L43: Future Start | M43: Contract | N43: Zone C | O43: Temporary | P43: Involuntary | Q43: Sales | R43: General - Con | S43: 13-11-1959 | T43: TX | U43: Laborer | V43: Male | W43: 93051 | X43: Fully Meets | Y43: 5 | Z43: 3513 | AA43: 45235 | AB43: 4 | AC43: 1 | AD43: 45080 | AE43: Communication Skills | AF43: External | AG43: Completed | AH43: East Adam | AI43: Katie Harrington | AJ43: 1 | AK43: 599
A44: 88 | B44: Kinsley | C44: Flowers | D44: 44629 | E44: 44905 | F44: =Table2[[#This Row],[ExitDate]]-Table2[[#This Row],[StartDate]] -> 276 | G44: =(Table2[[#This Row],[ExitDate]]-Table2[[#This Row],[StartDate]])/365.25 -> 0.75564682 | H44: Area Sales Manager | I44: Mary Reilly | J44: kinsley.flowers@bilearner.com | K44: CCDR | L44: Future Start | M44: Part-Time | N44: Zone A | O44: Part-Time | P44: Retirement | Q44: Sales | R44: Finance & Accounting | S44: 29-04-1997 | T44: CO | U44: Controller | V44: Male | W44: 59593 | X44: Fully Meets | Y44: 4 | Z44: 3515 | AA44: 44992 | AB44: 3 | AC44: 5 | AD44: 44961 | AE44: Customer Service | AF44: Internal | AG44: Completed | AH44: West Keith | AJ44: 1 | AK44: 143.96
A45: 89 | B45: Deborah | C45: Love | D45: 44658 | E45: 44948 | F45: =Table2[[#This Row],[ExitDate]]-Table2[[#This Row],[StartDate]] -> 290 | G45: =(Table2[[#This Row],[ExitDate]]-Table2[[#This Row],[StartDate]])/365.25 -> 0.79397673 | H45: Area Sales Manager | I45: Eric Goodman | J45: deborah.love@bilearner.com | K45: SVG | L45: Active | M45: Contract | N45: Zone B | O45: Part-Time | P45: Retirement | Q45: Sales | R45: Project Management - Con | S45: 25-06-1988 | T45: CO | U45: Coordinator | V45: Male | W45: 96350 | X45: Fully Meets | Y45: 5 | Z45: 3516 | AA45: 15-11-2022 | AB45: 2 | AC45: 3 | AD45: 45099 | AE45: Technical Skills | AF45: Internal | AG45: Incomplete | AH45: Lake Stephen | AI45: Gregory Kramer | AJ45: 1 | AK45: 570.42
A46: 91 | B46: Roberto | C46: Michael | D46: 44296 | E46: 44746 | F46: =Table2[[#This Row],[ExitDate]]-Table2[[#This Row],[StartDate]] -> 450 | G46: =(Table2[[#This Row],[ExitDate]]-Table2[[#This Row],[StartDate]])/365.25 -> 1.2320329 | H46: Area Sales Manager | I46: Cheryl Henry | J46: roberto.michael@bilearner.com | K46: MSC | L46: Active | M46: Contract | N46: Zone B | O46: Part-Time | P46: Involuntary | Q46: Sales | R46: General - Eng | S46: 24-05-1969 | T46: CA | U46: Coordinator | V46: Female | W46: 13249 | X46: Fully Meets | Y46: 2 | Z46: 3518 | AA46: 13-05-2023 | AB46: 4 | AC46: 2 | AD46: 45104 | AE46: Customer Service | AF46: Internal | AG46: Completed | AH46: Port Vanessafort | AI46: Michael Parker | AJ46: 3 | AK46: 826.58
A47: 92 | B47: Elaine | C47: Ewing | D47: 44549 | E47: 44622 | F47: =Table2[[#This Row],[ExitDate]]-Table2[[#This Row],[StartDate]] -> 73 | G47: =(Table2[[#This Row],[ExitDate]]-Table2[[#This Row],[StartDate]])/365.25 -> 0.19986311 | H47: Area Sales Manager | I47: Dan Hernandez | J47: elaine.ewing@bilearner.com | K47: TNS | L47: Active | M47: Part-Time | N47: Zone C | O47: Temporary | P47: Resignation | Q47: Sales | R47: Aerial | S47: 28-03-1951 | T47: CA | U47: Groundman | V47: Male | W47: 17123 | X47: Fully Meets | Y47: 2 | Z47: 3519 | AA47: 45205 | AB47: 1 | AC47: 3 | AD47: 44906 | AE47: Leadership Development | AF47: External | AG47: Incomplete | AH47: Deborahshire | AI47: Patrick Reeves | AJ47: 4 | AK47: 930.69
A48: 93 | B48: Caiden | C48: Munoz | D48: 44178 | E48: 44939 | F48: =Table2[[#This Row],[ExitDate]]-Table2[[#This Row],[StartDate]] -> 761 | G48: =(Table2[[#This Row],[ExitDate]]-Table2[[#This Row],[StartDate]])/365.25 -> 2.0835044 | H48: Area Sales Manager | I48: Teresa Daniel | J48: caiden.munoz@bilearner.com | K48: TNS | L48: Active | M48: Full-Time | N48: Zone C | O48: Temporary | P48: Involuntary | Q48: Sales | R48: Project Management - Con | S48: 23014 | T48: ND | U48: Manager | V48: Female | W48: 18983 | X48: Fully Meets | Y48: 1 | Z48: 3520 | AA48: 17-09-2022 | AB48: 5 | AC48: 1 | AD48: 44815 | AE48: Customer Service | AF48: External | AG48: Incomplete | AH48: North Anthonybury | AI48: Robin Sims | AJ48: 1 | AK48: 607.93
A49: 96 | B49: Rohan | C49: Chapman | D49: 44372 | E49: 44798 | F49: =Table2[[#This Row],[ExitDate]]-Table2[[#This Row],[StartDate]] -> 426 | G49: =(Table2[[#This Row],[ExitDate]]-Table2[[#This Row],[StartDate]])/365.25 -> 1.1663244 | H49: Area Sales Manager | I49: Tony Mcconnell | J49: rohan.chapman@bilearner.com | K49: CCDR | L49: Active | M49: Full-Time | N49: Zone A | O49: Temporary | P49: Resignation | Q49: Sales | R49: General - Con | S49: 19-12-1978 | T49: KY | U49: Laborer | V49: Female | W49: 23092 | X49: Fully Meets | Y49: 2 | Z49: 3523 | AA49: 27-02-2023 | AB49: 3 | AC49: 2 | AD49: 45117 | AE49: Leadership Development | AF49: External | AG49: Incomplete | AH49: South William | AI49: Felicia Berg | AJ49: 2 | AK49: 451.18
A50: 97 | B50: Emmanuel | C50: Franklin | D50: 44403 | E50: 44685 | F50: =Table2[[#This Row],[ExitDate]]-Table2[[#This Row],[StartDate]] -> 282 | G50: =(Table2[[#This Row],[ExitDate]]-Table2[[#This Row],[StartDate]])/365.25 -> 0.77207392 | H50: Area Sales Manager | I50: Adam Gibson | J50: emmanuel.franklin@bilearner.com | K50: EW | L50: Future Start | M50: Contract | N50: Zone B | O50: Full-Time | P50: Resignation | Q50: Sales | R50: Field Operations | S50: 36475 | T50: TX | U50: Laborer | V50: Male | W50: 6074 | X50: Fully Meets | Y50: 2 | Z50: 3524 | AA50: 19-05-2023 | AB50: 3 | AC50: 2 | AD50: 44928 | AE50: Communication Skills | AF50: Internal | AG50: Completed | AH50: Wilsonmouth | AI50: Jessica Vazquez | AJ50: 5 | AK50: 124.65
A51: 98 | B51: Clayton | C51: Mccormick | D51: 44745 | E51: 44936 | F51: =Table2[[#This Row],[ExitDate]]-Table2[[#This Row],[StartDate]] -> 191 | G51: =(Table2[[#This Row],[ExitDate]]-Table2[[#This Row],[StartDate]])/365.25 -> 0.5229295 | H51: Area Sales Manager | I51: Stephanie Duke | J51: clayton.mccormick@bilearner.com | K51: MSC | L51: Future Start | M51: Contract | N51: Zone B | O51: Temporary | P51: Retirement | Q51: Sales | R51: General - Con | S51: 29-01-1967 | T51: TX | U51: Foreman | V51: Male | W51: 72264 | X51: Fully Meets | Y51: 2 | Z51: 3525 | AA51: 44928 | AB51: 1 | AC51: 2 | AD51: 44843 | AE51: Leadership Development | AF51: External | AG51: Incomplete | AH51: East Michaelburgh | AI51: Tara Christensen | AJ51: 4 | AK51: 237.75
A52: 100 | B52: Ahmed | C52: Hawkins | D52: 43952 | E52: 44252 | F52: =Table2[[#This Row],[ExitDate]]-Table2[[#This Row],[StartDate]] -> 300 | G52: =(Table2[[#This Row],[ExitDate]]-Table2[[#This Row],[StartDate]])/365.25 -> 0.82135524 | H52: Area Sales Manager | I52: Hannah Snyder | J52: ahmed.hawkins@bilearner.com | K52: PL | L52: Active | M52: Full-Time | N52: Zone B | O52: Temporary | P52: Retirement | Q52: Sales | R52: Aerial | S52: 15-10-1974 | T52: CO | U52: Lineman | V52: Male | W52: 46645 | X52: Fully Meets | Y52: 1 | Z52: 3527 | AA52: 27-02-2023 | AB52: 1 | AC52: 3 | AD52: 44932 | AE52: Project Management | AF52: Internal | AG52: Failed | AH52: Berryland | AI52: Scott Richardson | AJ52: 4 | AK52: 396.28
A53: 102 | B53: Callum | C53: Mcdaniel | D53: 43833 | E53: 44067 | F53: =Table2[[#This Row],[ExitDate]]-Table2[[#This Row],[StartDate]] -> 234 | G53: =(Table2[[#This Row],[ExitDate]]-Table2[[#This Row],[StartDate]])/365.25 -> 0.64065708 | H53: Area Sales Manager | I53: Samuel Moore | J53: callum.mcdaniel@bilearner.com | K53: SVG | L53: Active | M53: Part-Time | N53: Zone C | O53: Full-Time | P53: Voluntary | Q53: Sales | R53: Field Operations | S53: 18-06-1994 | T53: IN | U53: Top Hand | V53: Male | W53: 67282 | X53: Fully Meets | Y53: 2 | Z53: 3529 | AA53: 15-07-2023 | AB53: 2 | AC53: 3 | AD53: 44808 | AE53: Project Management | AF53: Internal | AG53: Incomplete | AH53: South Andretown | AI53: Julie Hoffman | AJ53: 1 | AK53: 515.56
A54: 106 | B54: Slade | C54: Griffith | D54: 44348 | E54: 45123 | F54: =Table2[[#This Row],[ExitDate]]-Table2[[#This Row],[StartDate]] -> 775 | G54: =(Table2[[#This Row],[ExitDate]]-Table2[[#This Row],[StartDate]])/365.25 -> 2.1218344 | H54: Area Sales Manager | I54: Kelsey Gibson | J54: slade.griffith@bilearner.com | K54: MSC | L54: Active | M54: Contract | N54: Zone B | O54: Full-Time | P54: Voluntary | Q54: Sales | R54: General - Sga | S54: 24452 | T54: ND | U54: Administrator | V54: Male | W54: 65183 | X54: Fully Meets | Y54: 2 | Z54: 3533 | AA54: 45139 | AB54: 2 | AC54: 5 | AD54: 45057 | AE54: Leadership Development | AF54: Internal | AG54: Completed | AH54: North Janet | AI54: Jamie Dougherty | AJ54: 4 | AK54: 418.4
A55: 108 | B55: Veronica | C55: Rowe | D55: 43445 | E55: 44714 | F55: =Table2[[#This Row],[ExitDate]]-Table2[[#This Row],[StartDate]] -> 1269 | G55: =(Table2[[#This Row],[ExitDate]]-Table2[[#This Row],[StartDate]])/365.25 -> 3.4743326 | H55: Area Sales Manager | I55: Brian Morton | J55: veronica.rowe@bilearner.com | K55: PYZ | L55: Active | M55: Full-Time | N55: Zone A | O55: Temporary | P55: Retirement | Q55: Sales | R55: Fielders | S55: 34367 | T55: KY | U55: Engineer | V55: Female | W55: 29811 | X55: Fully Meets | Y55: 4 | Z55: 3535 | AA55: 44572 | AB55: 1 | AC55: 5 | AD55: 45102 | AE55: Technical Skills | AF55: External | AG55: Incomplete | AH55: Derrickview | AI55: Katherine Valentine | AJ55: 1 | AK55: 936.96
A56: 110 | B56: Neveah | C56: Rowe | D56: 44709 | E56: 44981 | F56: =Table2[[#This Row],[ExitDate]]-Table2[[#This Row],[StartDate]] -> 272 | G56: =(Table2[[#This Row],[ExitDate]]-Table2[[#This Row],[StartDate]])/365.25 -> 0.74469541 | H56: Area Sales Manager | I56: Dawn Perez | J56: neveah.rowe@bilearner.com | K56: NEL | L56: Future Start | M56: Contract | N56: Zone C | O56: Part-Time | P56: Retirement | Q56: Sales | R56: Field Operations | S56: 20035 | T56: TX | U56: Foreman | V56: Male | W56: 63882 | X56: Fully Meets | Y56: 2 | Z56: 3537 | AA56: 44813 | AB56: 4 | AC56: 2 | AD56: 44963 | AE56: Leadership Development | AF56: Internal | AG56: Completed | AH56: Griffintown | AI56: Janice Leblanc | AJ56: 4 | AK56: 853.77
A57: 111 | B57: Keith | C57: Baxter | D57: 43632 | E57: 44625 | F57: =Table2[[#This Row],[ExitDate]]-Table2[[#This Row],[StartDate]] -> 993 | G57: =(Table2[[#This Row],[ExitDate]]-Table2[[#This Row],[StartDate]])/365.25 -> 2.7186858 | H57: Area Sales Manager | I57: Diane Parker | J57: keith.baxter@bilearner.com | K57: PL | L57: Future Start | M57: Part-Time | N57: Zone C | O57: Part-Time | P57: Resignation | Q57: Sales | R57: Fielders | S57: 29-08-1959 | T57: TX | U57: Engineer | V57: Male | W57: 62328 | X57: Fully Meets | Y57: 2 | Z57: 3538 | AA57: 20-04-2023 | AB57: 1 | AC57: 5 | AD57: 44840 | AE57: Technical Skills | AF57: Internal | AG57: Failed | AH57: East Crystal | AI57: Joshua Mcguire | AJ57: 4 | AK57: 141.07
A58: 113 | B58: Maya | C58: Mccann | D58: 43902 | E58: 44843 | F58: =Table2[[#This Row],[ExitDate]]-Table2[[#This Row],[StartDate]] -> 941 | G58: =(Table2[[#This Row],[ExitDate]]-Table2[[#This Row],[StartDate]])/365.25 -> 2.5763176 | H58: Area Sales Manager | I58: Dakota Robinson | J58: maya.mccann@bilearner.com | K58: CCDR | L58: Active | M58: Full-Time | N58: Zone B | O58: Part-Time | P58: Retirement | Q58: Sales | R58: Splicing | S58: 30565 | T58: CO | U58: Supervisor | V58: Male | W58: 18721 | X58: Exceeds | Y58: 4 | Z58: 3540 | AA58: 25-06-2023 | AB58: 2 | AC58: 2 | AD58: 44860 | AE58: Communication Skills | AF58: External | AG58: Incomplete | AH58: West Josephmouth | AI58: Kristin Rodriguez | AJ58: 2 | AK58: 903.46
A59: 114 | B59: Aaron | C59: Weber | D59: 43927 | E59: 45131 | F59: =Table2[[#This Row],[ExitDate]]-Table2[[#This Row],[StartDate]] -> 1204 | G59: =(Table2[[#This Row],[ExitDate]]-Table2[[#This Row],[StartDate]])/365.25 -> 3.2963723 | H59: Area Sales Manager | I59: Melanie Garcia | J59: aaron.weber@bilearner.com | K59: SVG | L59: Active | M59: Full-Time | N59: Zone B | O59: Full-Time | P59: Involuntary | Q59: Sales | R59: Field Operations | S59: 27-10-1991 | T59: IN | U59: Technician | V59: Male | W59: 78938 | X59: Exceeds | Y59: 2 | Z59: 3541 | AA59: 28-11-2022 | AB59: 1 | AC59: 3 | AD59: 45068 | AE59: Customer Service | AF59: External | AG59: Passed | AH59: East Timothy | AI59: Ronald Butler | AJ59: 4 | AK59: 380.3
A60: 117 | B60: Samara | C60: Mcbride | D60: 45106 | E60: 45116 | F60: =Table2[[#This Row],[ExitDate]]-Table2[[#This Row],[StartDate]] -> 10 | G60: =(Table2[[#This Row],[ExitDate]]-Table2[[#This Row],[StartDate]])/365.25 -> 0.027378508 | H60: Area Sales Manager | I60: Laura Salinas | J60: samara.mcbride@bilearner.com | K60: TNS | L60: Active | M60: Contract | N60: Zone A | O60: Temporary | P60: Retirement | Q60: Sales | R60: Aerial | S60: 16-09-2000 | T60: CA | U60: Foreman | V60: Male | W60: 13902 | X60: Fully Meets | Y60: 2 | Z60: 3544 | AA60: 14-09-2022 | AB60: 3 | AC60: 5 | AD60: 45048 | AE60: Leadership Development | AF60: External | AG60: Passed | AH60: Rayborough | AI60: Mrs. Nicole Simon | AJ60: 3 | AK60: 842.93
A61: 119 | B61: Paris | C61: Carr | D61: 44408 | E61: 44953 | F61: =Table2[[#This Row],[ExitDate]]-Table2[[#This Row],[StartDate]] -> 545 | G61: =(Table2[[#This Row],[ExitDate]]-Table2[[#This Row],[StartDate]])/365.25 -> 1.4921287 | H61: Area Sales Manager | I61: Jeffrey Huffman | J61: paris.carr@bilearner.com | K61: CCDR | L61: Active | M61: Full-Time | N61: Zone B | O61: Part-Time | P61: Voluntary | Q61: Sales | R61: General - Con | S61: 14-07-1980 | T61: ND | U61: Foreman | V61: Male | W61: 35786 | X61: Exceeds | Y61: 1 | Z61: 3546 | AA61: 45204 | AB61: 2 | AC61: 5 | AD61: 44886 | AE61: Project Management | AF61: External | AG61: Passed | AH61: New Faith | AI61: Stephanie Horton | AJ61: 4 | AK61: 426.45
A62: 121 | B62: Sanaa | C62: Glass | D62: 44388 | E62: 44844 | F62: =Table2[[#This Row],[ExitDate]]-Table2[[#This Row],[StartDate]] -> 456 | G62: =(Table2[[#This Row],[ExitDate]]-Table2[[#This Row],[StartDate]])/365.25 -> 1.24846 | H62: Area Sales Manager | I62: Stephen Garcia | J62: sanaa.glass@bilearner.com | K62: WBL | L62: Active | M62: Part-Time | N62: Zone A | O62: Full-Time | P62: Resignation | Q62: Sales | R62: General - Con | S62: 25-01-1964 | T62: KY | U62: Technician | V62: Female | W62: 40135 | X62: Fully Meets | Y62: 1 | Z62: 3548 | AA62: 44722 | AB62: 5 | AC62: 5 | AD62: 44789 | AE62: Leadership Development | AF62: External | AG62: Passed | AH62: Lake Tinamouth | AI62: Corey Hernandez | AJ62: 3 | AK62: 368.8
A63: 122 | B63: Ryan | C63: Lynch | D63: 43388 | E63: 44122 | F63: =Table2[[#This Row],[ExitDate]]-Table2[[#This Row],[StartDate]] -> 734 | G63: =(Table2[[#This Row],[ExitDate]]-Table2[[#This Row],[StartDate]])/365.25 -> 2.0095825 | H63: Area Sales Manager | I63: Tracy Castro MD | J63: ryan.lynch@bilearner.com | K63: TNS | L63: Active | M63: Full-Time | N63: Zone C | O63: Full-Time | P63: Retirement | Q63: Sales | R63: Field Operations | S63: 17-03-1955 | T63: GA | U63: Technician | V63: Female | W63: 72975 | X63: Fully Meets | Y63: 2 | Z63: 3549 | AA63: 19-04-2023 | AB63: 1 | AC63: 4 | AD63: 44867 | AE63: Communication Skills | AF63: External | AG63: Failed | AH63: Claudiashire | AI63: John Gutierrez DDS | AJ63: 5 | AK63: 788.67
A64: 123 | B64: Charlie | C64: Atkinson | D64: 44526 | E64: 44848 | F64: =Table2[[#This Row],[ExitDate]]-Table2[[#This Row],[StartDate]] -> 322 | G64: =(Table2[[#This Row],[ExitDate]]-Table2[[#This Row],[StartDate]])/365.25 -> 0.88158795 | H64: Area Sales Manager | I64: Jennifer Hicks | J64: charlie.atkinson@bilearner.com | K64: SVG | L64: Future Start | M64: Part-Time | N64: Zone C | O64: Temporary | P64: Resignation | Q64: Sales | R64: Wireline Construction | S64: 26-03-1988 | T64: TX | U64: Billing | V64: Male | W64: 57754 | X64: Fully Meets | Y64: 1 | Z64: 3550 | AA64: 23-01-2023 | AB64: 3 | AC64: 5 | AD64: 45025 | AE64: Project Management | AF64: Internal | AG64: Completed | AH64: New Bonnie | AI64: Lisa Gibbs | AJ64: 4 | AK64: 363.11
A65: 125 | B65: Harper | C65: Ramos | D65: 43877 | E65: 43985 | F65: =Table2[[#This Row],[ExitDate]]-Table2[[#This Row],[StartDate]] -> 108 | G65: =(Table2[[#This Row],[ExitDate]]-Table2[[#This Row],[StartDate]])/365.25 -> 0.29568789 | H65: Area Sales Manager | I65: Maria Chan | J65: harper.ramos@bilearner.com | K65: PL | L65: Active | M65: Full-Time | N65: Zone B | O65: Full-Time | P65: Retirement | Q65: Sales | R65: Field Operations | S65: 15653 | T65: CO | U65: Foreman | V65: Male | W65: 28714 | X65: Needs Improvement | Y65: 1 | Z65: 3552 | AA65: 14-10-2022 | AB65: 3 | AC65: 4 | AD65: 44891 | AE65: Leadership Development | AF65: External | AG65: Failed | AH65: Charlottebury | AI65: John Miller | AJ65: 4 | AK65: 480.87
A66: 128 | B66: Matilda | C66: Randall | D66: 44932 | E66: 45053 | F66: =Table2[[#This Row],[ExitDate]]-Table2[[#This Row],[StartDate]] -> 121 | G66: =(Table2[[#This Row],[ExitDate]]-Table2[[#This Row],[StartDate]])/365.25 -> 0.33127995 | H66: Area Sales Manager | I66: Daniel Wolf | J66: matilda.randall@bilearner.com | K66: EW | L66: Active | M66: Full-Time | N66: Zone C | O66: Temporary | P66: Resignation | Q66: Sales | R66: General - Eng | S66: 32448 | T66: IN | U66: Drafter | V66: Female | W66: 48104 | X66: Fully Meets | Y66: 4 | Z66: 3555 | AA66: 13-01-2023 | AB66: 2 | AC66: 5 | AD66: 44989 | AE66: Leadership Development | AF66: External | AG66: Passed | AH66: Nashview | AI66: Darlene Vega | AJ66: 4 | AK66: 566.12
A67: 129 | B67: Damien | C67: Howe | D67: 43664 | E67: 43845 | F67: =Table2[[#This Row],[ExitDate]]-Table2[[#This Row],[StartDate]] -> 181 | G67: =(Table2[[#This Row],[ExitDate]]-Table2[[#This Row],[StartDate]])/365.25 -> 0.49555099 | H67: Area Sales Manager | I67: Sarah Petersen | J67: damien.howe@bilearner.com | K67: CCDR | L67: Active | M67: Full-Time | N67: Zone B | O67: Temporary | P67: Retirement | Q67: Sales | R67: Wireline Construction | S67: 16-06-1961 | T67: CA | U67: Vp | V67: Male | W67: 86009 | X67: Exceeds | Y67: 2 | Z67: 3556 | AA67: 45236 | AB67: 2 | AC67: 2 | AD67: 44968 | AE67: Customer Service | AF67: Internal | AG67: Incomplete | AH67: Christinastad | AI67: Mandy Morrison | AJ67: 1 | AK67: 513.92
A68: 132 | B68: Wilson K | C68: Adinolfi | D68: 43775 | E68: 44080 | F68: =Table2[[#This Row],[ExitDate]]-Table2[[#This Row],[StartDate]] -> 305 | G68: =(Table2[[#This Row],[ExitDate]]-Table2[[#This Row],[StartDate]])/365.25 -> 0.83504449 | H68: Production Technician I | I68: Andrea Gutierrez | J68: wilson k.adinolfi@bilearner.com | K68: NEL | L68: Active | M68: Part-Time | N68: Zone C | O68: Full-Time | P68: Retirement | Q68: Production | R68: Field Operations | S68: 18-11-1991 | T68: MA | U68: Assistant | V68: Male | W68: 1960 | X68: Fully Meets | Y68: 2 | Z68: 3559 | AA68: 27-12-2022 | AB68: 3 | AC68: 2 | AD68: 44895 | AE68: Project Management | AF68: External | AG68: Failed | AH68: West Michelletown | AI68: John Allen | AJ68: 2 | AK68: 959.81
A69: 135 | B69: Jean | C69: Crimmings | D69: 43606 | E69: 44931 | F69: =Table2[[#This Row],[ExitDate]]-Table2[[#This Row],[StartDate]] -> 1325 | G69: =(Table2[[#This Row],[ExitDate]]-Table2[[#This Row],[StartDate]])/365.25 -> 3.6276523 | H69: Production Technician I | I69: Stephen Rodriguez | J69: jean.crimmings@bilearner.com | K69: CCDR | L69: Future Start | M69: Contract | N69: Zone B | O69: Full-Time | P69: Retirement | Q69: Production | R69: Shop (Fleet) | S69: 19971 | T69: MA | U69: Manager | V69: Female | W69: 1821 | X69: Exceeds | Y69: 2 | Z69: 3562 | AA69: 27-11-2022 | AB69: 2 | AC69: 1 | AD69: 44928 | AE69: Project Management | AF69: External | AG69: Failed | AH69: West William | AI69: Jason Gallegos | AJ69: 3 | AK69: 808.05
A70: 137 | B70: Susan | C70: Lundy | D70: 43491 | E70: 44167 | F70: =Table2[[#This Row],[ExitDate]]-Table2[[#This Row],[StartDate]] -> 676 | G70: =(Table2[[#This Row],[ExitDate]]-Table2[[#This Row],[StartDate]])/365.25 -> 1.8507871 | H70: Production Technician II | I70: Diana Johnson | J70: susan.lundy@bilearner.com | K70: SVG | L70: Voluntarily Terminated | M70: Full-Time | N70: Zone C | O70: Temporary | P70: Resignation | Q70: Production | R70: Aerial | S70: 34526 | T70: MA | U70: Lineman | V70: Female | W70: 2122 | X70: Fully Meets | Y70: 1 | Z70: 3564 | AA70: 45263 | AB70: 4 | AC70: 4 | AD70: 44905 | AE70: Technical Skills | AF70: External | AG70: Incomplete | AH70: North Richard | AI70: Kimberly Thomas | AJ70: 4 | AK70: 106.14
A71: 141 | B71: Quinn | C71: Rarrick | D71: 45118 | E71: 45136 | F71: =Table2[[#This Row],[ExitDate]]-Table2[[#This Row],[StartDate]] -> 18 | G71: =(Table2[[#This Row],[ExitDate]]-Table2[[#This Row],[StartDate]])/365.25 -> 0.049281314 | H71: Production Technician I | I71: Susan Brown | J71: quinn.rarrick@bilearner.com | K71: EW | L71: Voluntarily Terminated | M71: Full-Time | N71: Zone B | O71: Part-Time | P71: Involuntary | Q71: Production | R71: Field Operations | S71: 27253 | T71: MA | U71: Foreman | V71: Male | W71: 2478 | X71: Fully Meets | Y71: 2 | Z71: 3568 | AA71: 45109 | AB71: 2 | AC71: 4 | AD71: 44796 | AE71: Project Management | AF71: Internal | AG71: Incomplete | AH71: Frenchside | AI71: Anthony Nixon | AJ71: 2 | AK71: 201.76
A72: 142 | B72: Beatrice | C72: Chace | D72: 43505 | E72: 44071 | F72: =Table2[[#This Row],[ExitDate]]-Table2[[#This Row],[StartDate]] -> 566 | G72: =(Table2[[#This Row],[ExitDate]]-Table2[[#This Row],[StartDate]])/365.25 -> 1.5496235 | H72: Production Technician I | I72: Margaret Hampton | J72: beatrice.chace@bilearner.com | K72: MSC | L72: Active | M72: Part-Time | N72: Zone B | O72: Temporary | P72: Involuntary | Q72: Production | R72: Catv | S72: 19-07-1995 | T72: MA | U72: Supervisor | V72: Female | W72: 2763 | X72: Fully Meets | Y72: 2 | Z72: 3569 | AA72: 24-12-2022 | AB72: 1 | AC72: 3 | AD72: 44874 | AE72: Technical Skills | AF72: External | AG72: Incomplete | AH72: Fernandezborough | AI72: Rachel Foster | AJ72: 4 | AK72: 730.04
A73: 143 | B73: Adrienne J | C73: Homberger | D73: 43574 | E73: 44495 | F73: =Table2[[#This Row],[ExitDate]]-Table2[[#This Row],[StartDate]] -> 921 | G73: =(Table2[[#This Row],[ExitDate]]-Table2[[#This Row],[StartDate]])/365.25 -> 2.5215606 | H73: Production Technician II | I73: Brandon Miller | J73: adrienne j.homberger@bilearner.com | K73: TNS | L73: Voluntarily Terminated | M73: Full-Time | N73: Zone B | O73: Temporary | P73: Voluntary | Q73: Production | R73: Fielders | S73: 23-11-1974 | T73: MA | U73: Engineer | V73: Female | W73: 2445 | X73: Fully Meets | Y73: 1 | Z73: 3570 | AA73: 44958 | AB73: 2 | AC73: 5 | AD73: 45014 | AE73: Project Management | AF73: External | AG73: Failed | AH73: Port Kristopherfurt | AI73: Matthew Ramirez | AJ73: 2 | AK73: 796.88
A74: 144 | B74: Marilyn | C74: Linares | D74: 44749 | E74: 45124 | F74: =Table2[[#This Row],[ExitDate]]-Table2[[#This Row],[StartDate]] -> 375 | G74: =(Table2[[#This Row],[ExitDate]]-Table2[[#This Row],[StartDate]])/365.25 -> 1.026694 | H74: Production Technician I | I74: Dr. Matthew Schmitt | J74: marilyn.linares@bilearner.com | K74: NEL | L74: Voluntarily Terminated | M74: Part-Time | N74: Zone C | O74: Full-Time | P74: Resignation | Q74: Production | R74: Field Operations | S74: 29-08-1947 | T74: MA | U74: Engineer | V74: Female | W74: 1886 | X74: Fully Meets | Y74: 4 | Z74: 3571 | AA74: 23-11-2022 | AB74: 4 | AC74: 1 | AD74: 45142 | AE74: Project Management | AF74: External | AG74: Completed | AH74: North William | AI74: Tanya Melendez | AJ74: 3 | AK74: 834.44
A75: 145 | B75: Timothy | C75: Sullivan | D75: 43536 | E75: 43970 | F75: =Table2[[#This Row],[ExitDate]]-Table2[[#This Row],[StartDate]] -> 434 | G75: =(Table2[[#This Row],[ExitDate]]-Table2[[#This Row],[StartDate]])/365.25 -> 1.1882272 | H75: Production Technician I | I75: Shawn Berry | J75: timothy.sullivan@bilearner.com | K75: WBL | L75: Active | M75: Contract | N75: Zone A | O75: Part-Time | P75: Retirement | Q75: Production | R75: Fielders | S75: 34521 | T75: MA | U75: Engineer | V75: Male | W75: 2747 | X75: Fully Meets | Y75: 5 | Z75: 3572 | AA75: 44693 | AB75: 5 | AC75: 5 | AD75: 45065 | AE75: Leadership Development | AF75: Internal | AG75: Failed | AH75: Port Dennis | AI75: Brady Newton | AJ75: 5 | AK75: 569.17
A76: 146 | B76: Jennifer | C76: Medeiros | D76: 43899 | E76: 44486 | F76: =Table2[[#This Row],[ExitDate]]-Table2[[#This Row],[StartDate]] -> 587 | G76: =(Table2[[#This Row],[ExitDate]]-Table2[[#This Row],[StartDate]])/365.25 -> 1.6071184 | H76: Production Technician I | I76: Brittany Martin | J76: jennifer.medeiros@bilearner.com | K76: NEL | L76: Active | M76: Contract | N76: Zone B | O76: Full-Time | P76: Involuntary | Q76: Production | R76: Field Operations | S76: 26-10-1983 | T76: MA | U76: Driller | V76: Female | W76: 2346 | X76: Exceeds | Y76: 4 | Z76: 3573 | AA76: 31-12-2022 | AB76: 4 | AC76: 1 | AD76: 44840 | AE76: Customer Service | AF76: Internal | AG76: Completed | AH76: Port Desireeburgh | AI76: Francis Cox | AJ76: 4 | AK76: 386.07
A77: 147 | B77: Anna | C77: Von Massenbach | D77: 44334 | E77: 44565 | F77: =Table2[[#This Row],[ExitDate]]-Table2[[#This Row],[StartDate]] -> 231 | G77: =(Table2[[#This Row],[ExitDate]]-Table2[[#This Row],[StartDate]])/365.25 -> 0.63244353 | H77: Production Technician I | I77: Timothy Weaver | J77: anna.von massenbach@bilearner.com | K77: WBL | L77: Future Start | M77: Contract | N77: Zone B | O77: Full-Time | P77: Involuntary | Q77: Production | R77: Underground | S77: 18784 | T77: MA | U77: Laborer | V77: Female | W77: 2124 | X77: Fully Meets | Y77: 1 | Z77: 3574 | AA77: 45114 | AB77: 3 | AC77: 3 | AD77: 44809 | AE77: Customer Service | AF77: Internal | AG77: Completed | AH77: Port Amy | AI77: Sharon Mcfarland | AJ77: 1 | AK77: 309.56
A78: 148 | B78: George | C78: Johnson | D78: 44314 | E78: 44579 | F78: =Table2[[#This Row],[ExitDate]]-Table2[[#This Row],[StartDate]] -> 265 | G78: =(Table2[[#This Row],[ExitDate]]-Table2[[#This Row],[StartDate]])/365.25 -> 0.72553046 | H78: Production Technician I | I78: Amanda Smith | J78: george.johnson@bilearner.com | K78: MSC | L78: Voluntarily Terminated | M78: Part-Time | N78: Zone A | O78: Temporary | P78: Resignation | Q78: Production | R78: Field Operations | S78: 31900 | T78: MA | U78: Groundman | V78: Male | W78: 2445 | X78: Exceeds | Y78: 5 | Z78: 3575 | AA78: 26-06-2023 | AB78: 5 | AC78: 1 | AD78: 44907 | AE78: Technical Skills | AF78: Internal | AG78: Incomplete | AH78: South Paulport | AI78: Brian Hood | AJ78: 3 | AK78: 583.21
A79: 149 | B79: Angela | C79: Erilus | D79: 44398 | E79: 45042 | F79: =Table2[[#This Row],[ExitDate]]-Table2[[#This Row],[StartDate]] -> 644 | G79: =(Table2[[#This Row],[ExitDate]]-Table2[[#This Row],[StartDate]])/365.25 -> 1.7631759 | H79: Production Technician II | I79: Marc Cummings | J79: angela.erilus@bilearner.com | K79: PL | L79: Active | M79: Full-Time | N79: Zone B | O79: Full-Time | P79: Voluntary | Q79: Production | R79: Engineers | S79: 26-04-1992 | T79: MA | U79: Project Manager | V79: Female | W79: 2133 | X79: Exceeds | Y79: 4 | Z79: 3576 | AA79: 23-03-2023 | AB79: 2 | AC79: 3 | AD79: 44959 | AE79: Project Management | AF79: External | AG79: Completed | AH79: East Taylor | AI79: Jesse Sullivan | AJ79: 5 | AK79: 398.65
A80: 154 | B80: Ross | C80: Strickland | D80: 44155 | E80: 45047 | F80: =Table2[[#This Row],[ExitDate]]-Table2[[#This Row],[StartDate]] -> 892 | G80: =(Table2[[#This Row],[ExitDate]]-Table2[[#This Row],[StartDate]])/365.25 -> 2.4421629 | H80: Production Technician I | I80: Paul Walker | J80: ross.strickland@bilearner.com | K80: SVG | L80: Active | M80: Full-Time | N80: Zone A | O80: Part-Time | P80: Voluntary | Q80: Production | R80: Wireline Construction | S80: 15921 | T80: MA | U80: Foreman | V80: Male | W80: 18389 | X80: Fully Meets | Y80: 2 | Z80: 3581 | AA80: 29-08-2022 | AB80: 3 | AC80: 4 | AD80: 44955 | AE80: Communication Skills | AF80: External | AG80: Completed | AH80: Michaelberg | AI80: Todd Ramirez | AJ80: 1 | AK80: 122.07
A81: 155 | B81: Augustus | C81: Drake | D81: 44062 | E81: 44685 | F81: =Table2[[#This Row],[ExitDate]]-Table2[[#This Row],[StartDate]] -> 623 | G81: =(Table2[[#This Row],[ExitDate]]-Table2[[#This Row],[StartDate]])/365.25 -> 1.705681 | H81: Production Technician I | I81: Elizabeth Robertson | J81: augustus.drake@bilearner.com | K81: TNS | L81: Active | M81: Part-Time | N81: Zone B | O81: Part-Time | P81: Retirement | Q81: Production | R81: Yard (Material Handling) | S81: 25089 | T81: MA | U81: Laborer | V81: Male | W81: 90676 | X81: Fully Meets | Y81: 4 | Z81: 3582 | AA81: 17-09-2022 | AB81: 2 | AC81: 2 | AD81: 44813 | AE81: Communication Skills | AF81: Internal | AG81: Completed | AH81: Lopezborough | AI81: Erik Reeves | AJ81: 4 | AK81: 875.02
A82: 156 | B82: Gracelyn | C82: Huynh | D82: 44314 | E82: 44669 | F82: =Table2[[#This Row],[ExitDate]]-Table2[[#This Row],[StartDate]] -> 355 | G82: =(Table2[[#This Row],[ExitDate]]-Table2[[#This Row],[StartDate]])/365.25 -> 0.97193703 | H82: Production Technician I | I82: Tasha Mayer | J82: gracelyn.huynh@bilearner.com | K82: WBL | L82: Active | M82: Full-Time | N82: Zone C | O82: Temporary | P82: Retirement | Q82: Production | R82: Field Operations | S82: 20-11-1958 | T82: MA | U82: Construction Manager | V82: Female | W82: 16011 | X82: Needs Improvement | Y82: 4 | Z82: 3583 | AA82: 45053 | AB82: 4 | AC82: 1 | AD82: 45003 | AE82: Communication Skills | AF82: Internal | AG82: Incomplete | AH82: Philipburgh | AI82: Jennifer Woods | AJ82: 4 | AK82: 116.4
A83: 159 | B83: Jaqueline | C83: Terrell | D83: 43497 | E83: 43506 | F83: =Table2[[#This Row],[ExitDate]]-Table2[[#This Row],[StartDate]] -> 9 | G83: =(Table2[[#This Row],[ExitDate]]-Table2[[#This Row],[StartDate]])/365.25 -> 0.024640657 | H83: Production Technician I | I83: Veronica Wiley | J83: jaqueline.terrell@bilearner.com | K83: EW | L83: Active | M83: Part-Time | N83: Zone B | O83: Full-Time | P83: Resignation | Q83: Production | R83: People Services | S83: 27-12-2000 | T83: MA | U83: Manager | V83: Female | W83: 24711 | X83: Fully Meets | Y83: 2 | Z83: 3586 | AA83: 31-01-2023 | AB83: 4 | AC83: 2 | AD83: 44834 | AE83: Communication Skills | AF83: External | AG83: Completed | AH83: Browntown | AI83: Tamara Hayes | AJ83: 1 | AK83: 502.7
A84: 160 | B84: Quinn | C84: Mccullough | D84: 44326 | E84: 44547 | F84: =Table2[[#This Row],[ExitDate]]-Table2[[#This Row],[StartDate]] -> 221 | G84: =(Table2[[#This Row],[ExitDate]]-Table2[[#This Row],[StartDate]])/365.25 -> 0.60506502 | H84: Production Technician I | I84: Katherine Gay | J84: quinn.mccullough@bilearner.com | K84: MSC | L84: Active | M84: Full-Time | N84: Zone B | O84: Temporary | P84: Resignation | Q84: Production | R84: General - Eng | S84: 25-12-1977 | T84: MA | U84: Administrative | V84: Male | W84: 74564 | X84: Fully Meets | Y84: 2 | Z84: 3587 | AA84: 24-05-2023 | AB84: 1 | AC84: 2 | AD84: 45007 | AE84: Leadership Development | AF84: External | AG84: Completed | AH84: New Larryshire | AI84: Darren Lam | AJ84: 5 | AK84: 570.04
A85: 161 | B85: Selena | C85: Greer | D85: 43641 | E85: 43692 | F85: =Table2[[#This Row],[ExitDate]]-Table2[[#This Row],[StartDate]] -> 51 | G85: =(Table2[[#This Row],[ExitDate]]-Table2[[#This Row],[StartDate]])/365.25 -> 0.13963039 | H85: Production Technician I | I85: Paul Lopez | J85: selena.greer@bilearner.com | K85: NEL | L85: Active | M85: Full-Time | N85: Zone C | O85: Full-Time | P85: Retirement | Q85: Production | R85: Shop (Fleet) | S85: 26514 | T85: MA | U85: Mechanic | V85: Male | W85: 14504 | X85: Fully Meets | Y85: 2 | Z85: 3588 | AA85: 45204 | AB85: 4 | AC85: 2 | AD85: 45008 | AE85: Communication Skills | AF85: External | AG85: Passed | AH85: Montgomeryland | AI85: Casey Johnston | AJ85: 1 | AK85: 538.83
A86: 163 | B86: Dominik | C86: Mullen | D86: 44252 | E86: 44847 | F86: =Table2[[#This Row],[ExitDate]]-Table2[[#This Row],[StartDate]] -> 595 | G86: =(Table2[[#This Row],[ExitDate]]-Table2[[#This Row],[StartDate]])/365.25 -> 1.6290212 | H86: Production Technician I | I86: Jessica Allen | J86: dominik.mullen@bilearner.com | K86: PYZ | L86: Future Start | M86: Part-Time | N86: Zone C | O86: Full-Time | P86: Retirement | Q86: Production | R86: Field Operations | S86: 31-05-1995 | T86: MA | U86: Laborer | V86: Male | W86: 66167 | X86: Fully Meets | Y86: 4 | Z86: 3590 | AA86: 44724 | AB86: 2 | AC86: 5 | AD86: 45018 | AE86: Leadership Development | AF86: External | AG86: Completed | AH86: North Janetbury | AI86: Michelle Baker | AJ86: 1 | AK86: 274.33
A87: 164 | B87: Abdullah | C87: Ellison | D87: 44523 | E87: 45075 | F87: =Table2[[#This Row],[ExitDate]]-Table2[[#This Row],[StartDate]] -> 552 | G87: =(Table2[[#This Row],[ExitDate]]-Table2[[#This Row],[StartDate]])/365.25 -> 1.5112936 | H87: Production Technician I | I87: Dr. William Thompson | J87: abdullah.ellison@bilearner.com | K87: SVG | L87: Future Start | M87: Contract | N87: Zone B | O87: Part-Time | P87: Voluntary | Q87: Production | R87: Field Operations | S87: 14-11-1998 | T87: MA | U87: Supervisor | V87: Female | W87: 21634 | X87: Needs Improvement | Y87: 5 | Z87: 3591 | AA87: 27-07-2023 | AB87: 2 | AC87: 1 | AD87: 44986 | AE87: Customer Service | AF87: Internal | AG87: Failed | AH87: Michaelfurt | AI87: Amy Murray | AJ87: 1 | AK87: 247.01
A88: 165 | B88: Andre | C88: Guzman | D88: 44474 | E88: 44730 | F88: =Table2[[#This Row],[ExitDate]]-Table2[[#This Row],[StartDate]] -> 256 | G88: =(Table2[[#This Row],[ExitDate]]-Table2[[#This Row],[StartDate]])/365.25 -> 0.7008898 | H88: Production Technician I | I88: Mrs. Audrey Gonzalez DDS | J88: andre.guzman@bilearner.com | K88: TNS | L88: Future Start | M88: Contract | N88: Zone B | O88: Full-Time | P88: Voluntary | Q88: Production | R88: Field Operations | S88: 23-12-1998 | T88: MA | U88: Technician | V88: Male | W88: 9454 | X88: Fully Meets | Y88: 3 | Z88: 3592 | AA88: 15-11-2022 | AB88: 4 | AC88: 1 | AD88: 44956 | AE88: Leadership Development | AF88: External | AG88: Incomplete | AH88: Williamsborough | AI88: Daniel Wilson | AJ88: 1 | AK88: 734.68
A89: 168 | B89: Fisher | C89: Stafford | D89: 44096 | E89: 44818 | F89: =Table2[[#This Row],[ExitDate]]-Table2[[#This Row],[StartDate]] -> 722 | G89: =(Table2[[#This Row],[ExitDate]]-Table2[[#This Row],[StartDate]])/365.25 -> 1.9767283 | H89: Production Technician I | I89: Nicole Delgado | J89: fisher.stafford@bilearner.com | K89: WBL | L89: Active | M89: Contract | N89: Zone A | O89: Temporary | P89: Resignation | Q89: Production | R89: Engineers | S89: 19027 | T89: MA | U89: Technician | V89: Male | W89: 56703 | X89: Fully Meets | Y89: 1 | Z89: 3595 | AA89: 19-01-2023 | AB89: 2 | AC89: 3 | AD89: 44978 | AE89: Technical Skills | AF89: External | AG89: Passed | AH89: Popetown | AI89: Angela Sanchez | AJ89: 2 | AK89: 252.88
A90: 170 | B90: Brenton | C90: Monroe | D90: 43988 | E90: 44300 | F90: =Table2[[#This Row],[ExitDate]]-Table2[[#This Row],[StartDate]] -> 312 | G90: =(Table2[[#This Row],[ExitDate]]-Table2[[#This Row],[StartDate]])/365.25 -> 0.85420945 | H90: Production Technician II | I90: Autumn Decker | J90: brenton.monroe@bilearner.com | K90: PYZ | L90: Future Start | M90: Contract | N90: Zone C | O90: Part-Time | P90: Retirement | Q90: Production | R90: General - Con | S90: 31-10-1986 | T90: MA | U90: Foreman | V90: Female | W90: 17650 | X90: Fully Meets | Y90: 1 | Z90: 3597 | AA90: 27-10-2022 | AB90: 5 | AC90: 4 | AD90: 44988 | AE90: Technical Skills | AF90: External | AG90: Incomplete | AH90: Port Jennifershire | AI90: Katrina Maldonado | AJ90: 4 | AK90: 505.59
A91: 171 | B91: Derick | C91: Rocha | D91: 43371 | E91: 45143 | F91: =Table2[[#This Row],[ExitDate]]-Table2[[#This Row],[StartDate]] -> 1772 | G91: =(Table2[[#This Row],[ExitDate]]-Table2[[#This Row],[StartDate]])/365.25 -> 4.8514716 | H91: Production Technician II | I91: Alex Moore | J91: derick.rocha@bilearner.com | K91: SVG | L91: Voluntarily Terminated | M91: Part-Time | N91: Zone A | O91: Full-Time | P91: Resignation | Q91: Production | R91: Project Management - Eng | S91: 18424 | T91: MA | U91: Supervisor | V91: Female | W91: 72750 | X91: Needs Improvement | Y91: 1 | Z91: 3598 | AA91: 44933 | AB91: 2 | AC91: 5 | AD91: 44845 | AE91: Technical Skills | AF91: Internal | AG91: Passed | AH91: Aliciahaven | AI91: Matthew Alvarado | AJ91: 3 | AK91: 373.87
A92: 175 | B92: Helena | C92: Davenport | D92: 44297 | E92: 45070 | F92: =Table2[[#This Row],[ExitDate]]-Table2[[#This Row],[StartDate]] -> 773 | G92: =(Table2[[#This Row],[ExitDate]]-Table2[[#This Row],[StartDate]])/365.25 -> 2.1163587 | H92: Production Technician II | I92: Crystal Mcneil | J92: helena.davenport@bilearner.com | K92: CCDR | L92: Voluntarily Terminated | M92: Full-Time | N92: Zone B | O92: Part-Time | P92: Involuntary | Q92: Production | R92: Engineers | S92: 34678 | T92: MA | U92: Engineer | V92: Female | W92: 30766 | X92: Fully Meets | Y92: 5 | Z92: 3602 | AA92: 45024 | AB92: 3 | AC92: 3 | AD92: 45025 | AE92: Technical Skills | AF92: External | AG92: Incomplete | AH92: New Michael | AI92: Joyce Williams | AJ92: 1 | AK92: 632.59
A93: 176 | B93: Houston | C93: Aguirre | D93: 43433 | E93: 43517 | F93: =Table2[[#This Row],[ExitDate]]-Table2[[#This Row],[StartDate]] -> 84 | G93: =(Table2[[#This Row],[ExitDate]]-Table2[[#This Row],[StartDate]])/365.25 -> 0.22997947 | H93: Production Technician II | I93: Christine Costa | J93: houston.aguirre@bilearner.com | K93: EW | L93: Voluntarily Terminated | M93: Full-Time | N93: Zone A | O93: Part-Time | P93: Resignation | Q93: Production | R93: Field Operations | S93: 15-02-1977 | T93: MA | U93: Technician | V93: Female | W93: 58348 | X93: Fully Meets | Y93: 2 | Z93: 3603 | AA93: 44783 | AB93: 5 | AC93: 1 | AD93: 44836 | AE93: Technical Skills | AF93: External | AG93: Incomplete | AH93: East Kristaton | AI93: Daniel Daugherty | AJ93: 3 | AK93: 680.48
A94: 177 | B94: Kane | C94: Owen | D94: 43481 | E94: 44804 | F94: =Table2[[#This Row],[ExitDate]]-Table2[[#This Row],[StartDate]] -> 1323 | G94: =(Table2[[#This Row],[ExitDate]]-Table2[[#This Row],[StartDate]])/365.25 -> 3.6221766 | H94: Production Technician II | I94: Mark Hale | J94: kane.owen@bilearner.com | K94: MSC | L94: Active | M94: Part-Time | N94: Zone B | O94: Full-Time | P94: Resignation | Q94: Production | R94: Field Operations | S94: 17779 | T94: MA | U94: Foreman | V94: Female | W94: 44626 | X94: Needs Improvement | Y94: 4 | Z94: 3604 | AA94: 15-12-2022 | AB94: 3 | AC94: 5 | AD94: 45008 | AE94: Project Management | AF94: External | AG94: Failed | AH94: Lake Scotttown | AI94: Ryan Russell | AJ94: 3 | AK94: 287.71
A95: 179 | B95: Clarissa | C95: Winters | D95: 43678 | E95: 44946 | F95: =Table2[[#This Row],[ExitDate]]-Table2[[#This Row],[StartDate]] -> 1268 | G95: =(Table2[[#This Row],[ExitDate]]-Table2[[#This Row],[StartDate]])/365.25 -> 3.4715948 | H95: Production Technician I | I95: Eric Gonzales | J95: clarissa.winters@bilearner.com | K95: SVG | L95: Voluntarily Terminated | M95: Part-Time | N95: Zone C | O95: Full-Time | P95: Involuntary | Q95: Production | R95: Billable Consultants | S95: 13-03-1965 | T95: MA | U95: Engineer | V95: Male | W95: 95618 | X95: Fully Meets | Y95: 3 | Z95: 3606 | AA95: 27-03-2023 | AB95: 3 | AC95: 5 | AD95: 44865 | AE95: Project Management | AF95: Internal | AG95: Passed | AH95: New Derrick | AI95: Elizabeth Powell | AJ95: 2 | AK95: 255.6
A96: 180 | B96: Frankie | C96: Atkins | D96: 43634 | E96: 44300 | F96: =Table2[[#This Row],[ExitDate]]-Table2[[#This Row],[StartDate]] -> 666 | G96: =(Table2[[#This Row],[ExitDate]]-Table2[[#This Row],[StartDate]])/365.25 -> 1.8234086 | H96: Production Technician I | I96: Christopher Murray | J96: frankie.atkins@bilearner.com | K96: EW | L96: Active | M96: Full-Time | N96: Zone A | O96: Full-Time | P96: Resignation | Q96: Production | R96: Project Management - Con | S96: 27827 | T96: MA | U96: Coordinator | V96: Male | W96: 15195 | X96: Fully Meets | Y96: 5 | Z96: 3607 | AA96: 18-07-2023 | AB96: 2 | AC96: 4 | AD96: 45050 | AE96: Customer Service | AF96: External | AG96: Passed | AH96: Port Tammyside | AI96: Andre Maxwell | AJ96: 4 | AK96: 321.91
A97: 187 | B97: Bridget | C97: Deleon | D97: 43838 | E97: 44379 | F97: =Table2[[#This Row],[ExitDate]]-Table2[[#This Row],[StartDate]] -> 541 | G97: =(Table2[[#This Row],[ExitDate]]-Table2[[#This Row],[StartDate]])/365.25 -> 1.4811773 | H97: Production Technician I | I97: Clifford Martinez | J97: bridget.deleon@bilearner.com | K97: BPC | L97: Active | M97: Contract | N97: Zone B | O97: Temporary | P97: Voluntary | Q97: Production | R97: Project Management - Con | S97: 31-08-1973 | T97: MA | U97: Field Project Manager | V97: Male | W97: 23691 | X97: Fully Meets | Y97: 2 | Z97: 3614 | AA97: 45023 | AB97: 4 | AC97: 5 | AD97: 45081 | AE97: Leadership Development | AF97: External | AG97: Passed | AH97: Emilymouth | AI97: Paul Bradley | AJ97: 3 | AK97: 868.85
A98: 188 | B98: Martin | C98: Weber | D98: 44329 | E98: 44826 | F98: =Table2[[#This Row],[ExitDate]]-Table2[[#This Row],[StartDate]] -> 497 | G98: =(Table2[[#This Row],[ExitDate]]-Table2[[#This Row],[StartDate]])/365.25 -> 1.3607118 | H98: Production Technician I | I98: Lee Hudson | J98: martin.weber@bilearner.com | K98: CCDR | L98: Future Start | M98: Full-Time | N98: Zone B | O98: Part-Time | P98: Retirement | Q98: Production | R98: General - Con | S98: 14-05-1986 | T98: MA | U98: Manager | V98: Male | W98: 74388 | X98: Exceeds | Y98: 2 | Z98: 3615 | AA98: 45079 | AB98: 3 | AC98: 1 | AD98: 44912 | AE98: Communication Skills | AF98: Internal | AG98: Passed | AH98: New Paul | AI98: James Young | AJ98: 4 | AK98: 701.34
A99: 192 | B99: Karissa | C99: Bowers | D99: 45008 | E99: 45047 | F99: =Table2[[#This Row],[ExitDate]]-Table2[[#This Row],[StartDate]] -> 39 | G99: =(Table2[[#This Row],[ExitDate]]-Table2[[#This Row],[StartDate]])/365.25 -> 0.10677618 | H99: Production Technician I | I99: Robert Wright | J99: karissa.bowers@bilearner.com | K99: TNS | L99: Active | M99: Full-Time | N99: Zone A | O99: Full-Time | P99: Involuntary | Q99: Production | R99: General - Con | S99: 17-03-1984 | T99: MA | U99: Technician | V99: Male | W99: 76278 | X99: Fully Meets | Y99: 3 | Z99: 3619 | AA99: 30-04-2023 | AB99: 1 | AC99: 5 | AD99: 44875 | AE99: Project Management | AF99: Internal | AG99: Passed | AH99: Davismouth | AI99: Ashley Ball | AJ99: 2 | AK99: 656.68
A100: 193 | B100: Noel | C100: Ramirez | D100: 45007 | E100: 45121 | F100: =Table2[[#This Row],[ExitDate]]-Table2[[#This Row],[StartDate]] -> 114 | G100: =(Table2[[#This Row],[ExitDate]]-Table2[[#This Row],[StartDate]])/365.25 -> 0.31211499 | H100: Production Technician I | I100: Mr. Nicholas Austin | J100: noel.ramirez@bilearner.com | K100: PYZ | L100: Active | M100: Part-Time | N100: Zone A | O100: Temporary | P100: Involuntary | Q100: Production | R100: General - Eng | S100: 34678 | T100: MA | U100: Specialist | V100: Male | W100: 77580 | X100: Fully Meets | Y100: 2 | Z100: 3620 | AA100: 29-08-2022 | AB100: 1 | AC100: 2 | AD100: 44915 | AE100: Technical Skills | AF100: Internal | AG100: Completed | AH100: North Ebony | AI100: Christine Carter | AJ100: 3 | AK100: 654.22
...

Sheet Messy_HR_Dataset_Detailed
A1: ID | B1: FirstName | C1: LastName | D1: StartDate | E1: ExitDate | F1: Turnover | G1: Tenure (years) | H1: Title | I1: Supervisor | J1: ADEmail | K1: BusinessUnit | L1: EmployeeStatus | M1: EmployeeType | N1: PayZone | O1: EmployeeClassificationType | P1: TerminationType | Q1: DepartmentType | R1: Division | S1: DOB | T1: State | U1: JobFunctionDescription | V1: GenderCode | W1: LocationCode | X1: Performance Score | Y1: Current Employee Rating | Z1: Employee ID | AA1: Survey Date | AB1: Engagement Score | AC1: Satisfaction Score | AD1: Training Date | AE1: Training Program Name | AF1: Training Type | AG1: Training Outcome | AH1: Location | AI1: Trainer | AJ1: Training Duration(Days) | AK1: Training Cost
A2: 6 | B2: Latia | C2: Costa | D2: 44657 | E2: 45110 | F2: =Messy_HR_Dataset_Detailed!$E2-Messy_HR_Dataset_Detailed!$D2 -> 453 | G2: =(Messy_HR_Dataset_Detailed!$E2-Messy_HR_Dataset_Detailed!$D2)/365.25 -> 1.2402464 | H2: Area Sales Manager | I2: Jacob Braun | J2: latia.costa@bilearner.com | K2: WBL | L2: Active | M2: Full-Time | N2: Zone B | O2: Temporary | P2: Involuntary | Q2: Sales | R2: General - Eng | S2: 15348 | T2: CA | U2: Technician | V2: Female | W2: 90007 | X2: Exceeds | Y2: 4 | Z2: 3433 | AA2: 25-03-2023 | AB2: 1 | AC2: 5 | AD2: 44779 | AE2: Customer Service | AF2: External | AG2: Passed | AH2: Lancehaven | AI2: David Stewart | AJ2: 5 | AK2: 295.08
A3: 7 | B3: Sharlene | C3: Terry | D3: 44141 | E3: 44955 | F3: =Messy_HR_Dataset_Detailed!$E3-Messy_HR_Dataset_Detailed!$D3 -> 814 | G3: =(Messy_HR_Dataset_Detailed!$E3-Messy_HR_Dataset_Detailed!$D3)/365.25 -> 2.2286105 | H3: Area Sales Manager | I3: Tracy Marquez | J3: sharlene.terry@bilearner.com | K3: CCDR | L3: Active | M3: Contract | N3: Zone C | O3: Full-Time | P3: Involuntary | Q3: Sales | R3: Engineers | S3: 21004 | T3: OR | U3: Engineer | V3: Female | W3: 97756 | X3: Fully Meets | Y3: 2 | Z3: 3434 | AA3: 21-04-2023 | AB3: 1 | AC3: 4 | AD3: 44841 | AE3: Leadership Development | AF3: Internal | AG3: Passed | AH3: Jeremyshire | AI3: Stephanie Garza | AJ3: 3 | AK3: 790.15
A4: 9 | B4: Joseph | C4: Martins | D4: 44582 | E4: 45106 | F4: =Messy_HR_Dataset_Detailed!$E4-Messy_HR_Dataset_Detailed!$D4 -> 524 | G4: =(Messy_HR_Dataset_Detailed!$E4-Messy_HR_Dataset_Detailed!$D4)/365.25 -> 1.4346338 | H4: Area Sales Manager | I4: George Jenkins | J4: joseph.martins@bilearner.com | K4: BPC | L4: Active | M4: Part-Time | N4: Zone B | O4: Temporary | P4: Resignation | Q4: Sales | R4: Engineers | S4: 18213 | T4: TX | U4: Engineer | V4: Male | W4: 78207 | X4: Fully Meets | Y4: 5 | Z4: 3436 | AA4: 30-07-2023 | AB4: 5 | AC4: 5 | AD4: 45025 | AE4: Leadership Development | AF4: Internal | AG4: Failed | AH4: Nicolebury | AI4: Megan Wilson | AJ4: 5 | AK4: 192.61
A5: 11 | B5: Dheepa | C5: Nguyen | D5: 43322 | E5: 43773 | F5: =Messy_HR_Dataset_Detailed!$E5-Messy_HR_Dataset_Detailed!$D5 -> 451 | G5: =(Messy_HR_Dataset_Detailed!$E5-Messy_HR_Dataset_Detailed!$D5)/365.25 -> 1.2347707 | H5: Area Sales Manager | I5: Brian Miller | J5: dheepa.nguyen@bilearner.com | K5: MSC | L5: Active | M5: Full-Time | N5: Zone C | O5: Temporary | P5: Retirement | Q5: Sales | R5: General - Con | S5: 17688 | T5: GA | U5: Technician | V5: Female | W5: 30428 | X5: Fully Meets | Y5: 3 | Z5: 3438 | AA5: 28-10-2022 | AB5: 4 | AC5: 2 | AD5: 44839 | AE5: Technical Skills | AF5: Internal | AG5: Failed | AH5: Nunezmouth | AI5: Sharon Flores DDS | AJ5: 2 | AK5: 208.17
A6: 12 | B6: Bartholemew | C6: Khemmich | D6: 44706 | E6: 44892 | F6: =Messy_HR_Dataset_Detailed!$E6-Messy_HR_Dataset_Detailed!$D6 -> 186 | G6: =(Messy_HR_Dataset_Detailed!$E6-Messy_HR_Dataset_Detailed!$D6)/365.25 -> 0.50924025 | H6: Area Sales Manager | I6: Charles Parks | J6: bartholemew.khemmich@bilearner.com | K6: EW | L6: Active | M6: Full-Time | N6: Zone A | O6: Temporary | P6: Involuntary | Q6: Sales | R6: Splicing | S6: 24-11-1981 | T6: CO | U6: Splicer | V6: Male | W6: 80820 | X6: Fully Meets | Y6: 3 | Z6: 3439 | AA6: 30-10-2022 | AB6: 1 | AC6: 2 | AD6: 44994 | AE6: Technical Skills | AF6: External | AG6: Incomplete | AH6: Port Margaretview | AI6: Kimberly Garcia | AJ6: 1 | AK6: 421.07
A7: 13 | B7: Xana | C7: Potts | D7: 43804 | E7: 44974 | F7: =Messy_HR_Dataset_Detailed!$E7-Messy_HR_Dataset_Detailed!$D7 -> 1170 | G7: =(Messy_HR_Dataset_Detailed!$E7-Messy_HR_Dataset_Detailed!$D7)/365.25 -> 3.2032854 | H7: Area Sales Manager | I7: Gregory Walker | J7: xana.potts@bilearner.com | K7: CCDR | L7: Active | M7: Contract | N7: Zone A | O7: Full-Time | P7: Resignation | Q7: Sales | R7: Finance & Accounting | S7: 18790 | T7: KY | U7: Controller | V7: Female | W7: 40220 | X7: Fully Meets | Y7: 3 | Z7: 3440 | AA7: 24-09-2022 | AB7: 1 | AC7: 4 | AD7: 45075 | AE7: Communication Skills | AF7: External | AG7: Failed | AH7: Nancyview | AI7: Christopher Underwood | AJ7: 1 | AK7: 649.03
A8: 15 | B8: Kaylah | C8: Moon | D8: 43655 | E8: 44728 | F8: =Messy_HR_Dataset_Detailed!$E8-Messy_HR_Dataset_Detailed!$D8 -> 1073 | G8: =(Messy_HR_Dataset_Detailed!$E8-Messy_HR_Dataset_Detailed!$D8)/365.25 -> 2.9377139 | H8: Area Sales Manager | I8: Ashley Scott | J8: kaylah.moon@bilearner.com | K8: PYZ | L8: Active | M8: Full-Time | N8: Zone A | O8: Full-Time | P8: Retirement | Q8: IT/IS | R8: Field Operations | S8: 24-11-1952 | T8: MA | U8: Laborer | V8: Male | W8: 2810 | X8: Exceeds | Y8: 2 | Z8: 3442 | AA8: 31-10-2022 | AB8: 2 | AC8: 5 | AD8: 44991 | AE8: Project Management | AF8: External | AG8: Failed | AH8: Port Davidshire | AI8: Victoria Berry | AJ8: 4 | AK8: 286.87
A9: 16 | B9: Kristen | C9: Tate | D9: 44291 | E9: 45058 | F9: =Messy_HR_Dataset_Detailed!$E9-Messy_HR_Dataset_Detailed!$D9 -> 767 | G9: =(Messy_HR_Dataset_Detailed!$E9-Messy_HR_Dataset_Detailed!$D9)/365.25 -> 2.0999316 | H9: Area Sales Manager | I9: Lauren Jones | J9: kristen.tate@bilearner.com | K9: WBL | L9: Active | M9: Full-Time | N9: Zone C | O9: Part-Time | P9: Voluntary | Q9: IT/IS | R9: Project Management - Con | S9: 34550 | T9: KY | U9: Coordinator | V9: Male | W9: 2621 | X9: Fully Meets | Y9: 3 | Z9: 3443 | AA9: 29-04-2023 | AB9: 2 | AC9: 2 | AD9: 44975 | AE9: Technical Skills | AF9: External | AG9: Failed | AH9: East Katie | AI9: Gary Thornton | AJ9: 3 | AK9: 402.13
A10: 17 | B10: Bobby | C10: Rodgers | D10: 44528 | E10: 44596 | F10: =Messy_HR_Dataset_Detailed!$E10-Messy_HR_Dataset_Detailed!$D10 -> 68 | G10: =(Messy_HR_Dataset_Detailed!$E10-Messy_HR_Dataset_Detailed!$D10)/365.25 -> 0.18617385 | H10: Area Sales Manager | I10: Matthew Jackson | J10: bobby.rodgers@bilearner.com | K10: NEL | L10: Active | M10: Contract | N10: Zone A | O10: Part-Time | P10: Voluntary | Q10: Sales | R10: Engineers | S10: 15-11-1983 | T10: KY | U10: Director | V10: Male | W10: 44553 | X10: Fully Meets | Y10: 3 | Z10: 3444 | AA10: 14-12-2022 | AB10: 1 | AC10: 2 | AD10: 44867 | AE10: Technical Skills | AF10: External | AG10: Failed | AH10: Jacobburgh | AI10: William Willis | AJ10: 2 | AK10: 388.84
A11: 20 | B11: Mariela | C11: Schultz | D11: 43977 | E11: 45095 | F11: =Messy_HR_Dataset_Detailed!$E11-Messy_HR_Dataset_Detailed!$D11 -> 1118 | G11: =(Messy_HR_Dataset_Detailed!$E11-Messy_HR_Dataset_Detailed!$D11)/365.25 -> 3.0609172 | H11: Area Sales Manager | I11: Michelle Evans MD | J11: mariela.schultz@bilearner.com | K11: CCDR | L11: Future Start | M11: Part-Time | N11: Zone C | O11: Part-Time | P11: Involuntary | Q11: Sales | R11: General - Con | S11: 17-02-1964 | T11: TX | U11: Technician | V11: Female | W11: 43481 | X11: Fully Meets | Y11: 3 | Z11: 3447 | AA11: 45143 | AB11: 5 | AC11: 1 | AD11: 45018 | AE11: Customer Service | AF11: Internal | AG11: Incomplete | AH11: Kristenton | AI11: Kimberly Doyle | AJ11: 3 | AK11: 353.21
A12: 21 | B12: Angela | C12: Molina | D12: 43739 | E12: 44141 | F12: =Messy_HR_Dataset_Detailed!$E12-Messy_HR_Dataset_Detailed!$D12 -> 402 | G12: =(Messy_HR_Dataset_Detailed!$E12-Messy_HR_Dataset_Detailed!$D12)/365.25 -> 1.100616 | H12: Area Sales Manager | I12: Patricia Cook | J12: angela.molina@bilearner.com | K12: SVG | L12: Future Start | M12: Full-Time | N12: Zone A | O12: Temporary | P12: Retirement | Q12: Sales | R12: Engineers | S12: 21524 | T12: TX | U12: Specialist | V12: Male | W12: 50705 | X12: Fully Meets | Y12: 3 | Z12: 3448 | AA12: 28-03-2023 | AB12: 5 | AC12: 1 | AD12: 45062 | AE12: Communication Skills | AF12: Internal | AG12: Completed | AH12: West Jamesview | AI12: Lindsay Williams | AJ12: 4 | AK12: 911.05
A13: 22 | B13: Gerald | C13: Preston | D13: 45056 | E13: 45073 | F13: =Messy_HR_Dataset_Detailed!$E13-Messy_HR_Dataset_Detailed!$D13 -> 17 | G13: =(Messy_HR_Dataset_Detailed!$E13-Messy_HR_Dataset_Detailed!$D13)/365.25 -> 0.046543463 | H13: Area Sales Manager | I13: Ashley Reeves | J13: gerald.preston@bilearner.com | K13: EW | L13: Future Start | M13: Contract | N13: Zone B | O13: Temporary | P13: Involuntary | Q13: Sales | R13: General - Eng | S13: 18-09-1992 | T13: CO | U13: Technician | V13: Male | W13: 5168 | X13: Fully Meets | Y13: 5 | Z13: 3449 | AA13: 30-06-2023 | AB13: 3 | AC13: 2 | AD13: 44836 | AE13: Communication Skills | AF13: External | AG13: Completed | AH13: Josebury | AI13: Joseph Faulkner | AJ13: 3 | AK13: 242.21
A14: 23 | B14: Reilly | C14: Moyer | D14: 44075 | E14: 44899 | F14: =Messy_HR_Dataset_Detailed!$E14-Messy_HR_Dataset_Detailed!$D14 -> 824 | G14: =(Messy_HR_Dataset_Detailed!$E14-Messy_HR_Dataset_Detailed!$D14)/365.25 -> 2.255989 | H14: Area Sales Manager | I14: Stanley Harvey | J14: reilly.moyer@bilearner.com | K14: MSC | L14: Active | M14: Contract | N14: Zone C | O14: Temporary | P14: Resignation | Q14: Sales | R14: Field Operations | S14: 34646 | T14: CO | U14: Operator | V14: Male | W14: 11765 | X14: Exceeds | Y14: 2 | Z14: 3450 | AA14: 18-01-2023 | AB14: 4 | AC14: 3 | AD14: 44938 | AE14: Technical Skills | AF14: Internal | AG14: Completed | AH14: South Benjaminfurt | AI14: Laura Davis | AJ14: 4 | AK14: 186.07
A15: 24 | B15: Carlee | C15: French | D15: 44245 | E15: 44876 | F15: =Messy_HR_Dataset_Detailed!$E15-Messy_HR_Dataset_Detailed!$D15 -> 631 | G15: =(Messy_HR_Dataset_Detailed!$E15-Messy_HR_Dataset_Detailed!$D15)/365.25 -> 1.7275838 | H15: Area Sales Manager | I15: Michael Bradshaw | J15: carlee.french@bilearner.com | K15: TNS | L15: Active | M15: Contract | N15: Zone C | O15: Full-Time | P15: Voluntary | Q15: Sales | R15: General - Con | S15: 15-01-1968 | T15: CO | U15: Technician | V15: Male | W15: 71071 | X15: Exceeds | Y15: 3 | Z15: 3451 | AA15: 29-04-2023 | AB15: 5 | AC15: 1 | AD15: 45007 | AE15: Technical Skills | AF15: External | AG15: Completed | AH15: Duncanview | AI15: d | AJ15: 1 | AK15: 921.97
A16: 28 | B16: Charity | C16: Miranda | D16: 44376 | E16: 44747 | F16: =Messy_HR_Dataset_Detailed!$E16-Messy_HR_Dataset_Detailed!$D16 -> 371 | G16: =(Messy_HR_Dataset_Detailed!$E16-Messy_HR_Dataset_Detailed!$D16)/365.25 -> 1.0157426 | H16: Area Sales Manager | I16: Daniel Rodriguez | J16: charity.miranda@bilearner.com | K16: WBL | L16: Active | M16: Full-Time | N16: Zone C | O16: Temporary | P16: Resignation | Q16: Sales | R16: Project Management - Eng | S16: 18-01-1999 | T16: KY | U16: Manager | V16: Male | W16: 3763 | X16: Exceeds | Y16: 4 | Z16: 3455 | AA16: 44903 | AB16: 2 | AC16: 1 | AD16: 45002 | AE16: Project Management | AF16: External | AG16: Passed | AH16: Wadefurt | AI16: Timothy Moreno | AJ16: 1 | AK16: 220.41
A17: 31 | B17: Cory | C17: Robinson | D17: 44679 | E17: 45070 | F17: =Messy_HR_Dataset_Detailed!$E17-Messy_HR_Dataset_Detailed!$D17 -> 391 | G17: =(Messy_HR_Dataset_Detailed!$E17-Messy_HR_Dataset_Detailed!$D17)/365.25 -> 1.0704997 | H17: Area Sales Manager | I17: Elizabeth Anderson | J17: cory.robinson@bilearner.com | K17: BPC | L17: Future Start | M17: Contract | N17: Zone A | O17: Full-Time | P17: Voluntary | Q17: Sales | R17: Field Operations | S17: 35407 | T17: TX | U17: Laborer | V17: Female | W17: 5194 | X17: Needs Improvement | Y17: 3 | Z17: 3458 | AA17: 14-02-2023 | AB17: 2 | AC17: 5 | AD17: 44897 | AE17: Communication Skills | AF17: Internal | AG17: Failed | AH17: North Deborahville | AI17: Joseph Ward | AJ17: 2 | AK17: 409.27
A18: 32 | B18: Saniya | C18: Yu | D18: 44304 | E18: 44733 | F18: =Messy_HR_Dataset_Detailed!$E18-Messy_HR_Dataset_Detailed!$D18 -> 429 | G18: =(Messy_HR_Dataset_Detailed!$E18-Messy_HR_Dataset_Detailed!$D18)/365.25 -> 1.174538 | H18: Area Sales Manager | I18: Erin Bailey | J18: saniya.yu@bilearner.com | K18: CCDR | L18: Future Start | M18: Part-Time | N18: Zone A | O18: Full-Time | P18: Retirement | Q18: Sales | R18: General - Con | S18: 16317 | T18: TX | U18: Splicer | V18: Male | W18: 8779 | X18: Exceeds | Y18: 2 | Z18: 3459 | AA18: 26-10-2022 | AB18: 4 | AC18: 4 | AD18: 45091 | AE18: Communication Skills | AF18: Internal | AG18: Passed | AH18: Chapmanbury | AI18: Joseph Thomas | AJ18: 4 | AK18: 168.32
A19: 34 | B19: Lincoln | C19: Compton | D19: 43664 | E19: 44470 | F19: =Messy_HR_Dataset_Detailed!$E19-Messy_HR_Dataset_Detailed!$D19 -> 806 | G19: =(Messy_HR_Dataset_Detailed!$E19-Messy_HR_Dataset_Detailed!$D19)/365.25 -> 2.2067077 | H19: Area Sales Manager | I19: Tammy Conner | J19: lincoln.compton@bilearner.com | K19: EW | L19: Future Start | M19: Full-Time | N19: Zone C | O19: Part-Time | P19: Resignation | Q19: Sales | R19: General - Con | S19: 29-12-1997 | T19: CO | U19: Foreman | V19: Male | W19: 78046 | X19: Needs Improvement | Y19: 1 | Z19: 3461 | AA19: 24-04-2023 | AB19: 1 | AC19: 4 | AD19: 44931 | AE19: Technical Skills | AF19: External | AG19: Completed | AH19: Taylorland | AI19: Micheal Munoz | AJ19: 2 | AK19: 948.43
A20: 35 | B20: Aliana | C20: Nolan | D20: 43356 | E20: 44456 | F20: =Messy_HR_Dataset_Detailed!$E20-Messy_HR_Dataset_Detailed!$D20 -> 1100 | G20: =(Messy_HR_Dataset_Detailed!$E20-Messy_HR_Dataset_Detailed!$D20)/365.25 -> 3.0116359 | H20: Area Sales Manager | I20: Brianna Mathews | J20: aliana.nolan@bilearner.com | K20: MSC | L20: Active | M20: Contract | N20: Zone A | O20: Full-Time | P20: Involuntary | Q20: Sales | R20: Field Operations | S20: 15592 | T20: CO | U20: Coordinator | V20: Male | W20: 27270 | X20: Needs Improvement | Y20: 3 | Z20: 3462 | AA20: 44784 | AB20: 3 | AC20: 3 | AD20: 45126 | AE20: Project Management | AF20: External | AG20: Completed | AH20: Erinville | AI20: Stacey Esparza | AJ20: 1 | AK20: 320.01
A21: 36 | B21: Kayden | C21: Dodson | D21: 43951 | E21: 44395 | F21: =Messy_HR_Dataset_Detailed!$E21-Messy_HR_Dataset_Detailed!$D21 -> 444 | G21: =(Messy_HR_Dataset_Detailed!$E21-Messy_HR_Dataset_Detailed!$D21)/365.25 -> 1.2156057 | H21: Area Sales Manager | I21: Jessica Peters | J21: kayden.dodson@bilearner.com | K21: TNS | L21: Active | M21: Part-Time | N21: Zone A | O21: Temporary | P21: Retirement | Q21: Sales | R21: Field Operations | S21: 21-06-1951 | T21: IN | U21: Tower Hand | V21: Male | W21: 12703 | X21: Fully Meets | Y21: 1 | Z21: 3463 | AA21: 18-09-2022 | AB21: 4 | AC21: 3 | AD21: 44802 | AE21: Technical Skills | AF21: Internal | AG21: Incomplete | AH21: Harperchester | AI21: Heather Edwards | AJ21: 4 | AK21: 926.19
A22: 37 | B22: James | C22: Duke | D22: 43437 | E22: 44813 | F22: =Messy_HR_Dataset_Detailed!$E22-Messy_HR_Dataset_Detailed!$D22 -> 1376 | G22: =(Messy_HR_Dataset_Detailed!$E22-Messy_HR_Dataset_Detailed!$D22)/365.25 -> 3.7672827 | H22: Area Sales Manager | I22: Mark Harris | J22: james.duke@bilearner.com | K22: PYZ | L22: Active | M22: Contract | N22: Zone B | O22: Full-Time | P22: Involuntary | Q22: Sales | R22: Shop (Fleet) | S22: 17-06-1998 | T22: MA | U22: Mechanic | V22: Male | W22: 66835 | X22: Needs Improvement | Y22: 5 | Z22: 3464 | AA22: 29-12-2022 | AB22: 2 | AC22: 5 | AD22: 44878 | AE22: Customer Service | AF22: External | AG22: Passed | AH22: Trevorside | AI22: Michaela Wright | AJ22: 2 | AK22: 290.47
A23: 39 | B23: Clayton | C23: Walker | D23: 44664 | E23: 45026 | F23: =Messy_HR_Dataset_Detailed!$E23-Messy_HR_Dataset_Detailed!$D23 -> 362 | G23: =(Messy_HR_Dataset_Detailed!$E23-Messy_HR_Dataset_Detailed!$D23)/365.25 -> 0.99110198 | H23: Area Sales Manager | I23: Jon Holden | J23: clayton.walker@bilearner.com | K23: PYZ | L23: Active | M23: Part-Time | N23: Zone C | O23: Full-Time | P23: Retirement | Q23: IT/IS | R23: Aerial | S23: 26-01-1979 | T23: KY | U23: Supervisor | V23: Male | W23: 64288 | X23: Exceeds | Y23: 4 | Z23: 3466 | AA23: 45024 | AB23: 1 | AC23: 3 | AD23: 44902 | AE23: Customer Service | AF23: External | AG23: Passed | AH23: West Angelaside | AI23: Erika Jackson | AJ23: 3 | AK23: 447.66
A24: 42 | B24: Ryland | C24: Shepherd | D24: 44041 | E24: 44931 | F24: =Messy_HR_Dataset_Detailed!$E24-Messy_HR_Dataset_Detailed!$D24 -> 890 | G24: =(Messy_HR_Dataset_Detailed!$E24-Messy_HR_Dataset_Detailed!$D24)/365.25 -> 2.4366872 | H24: Area Sales Manager | I24: James Berry | J24: ryland.shepherd@bilearner.com | K24: PL | L24: Future Start | M24: Contract | N24: Zone B | O24: Full-Time | P24: Resignation | Q24: Sales | R24: Field Operations | S24: 21-02-1945 | T24: TX | U24: Driver | V24: Female | W24: 81905 | X24: Needs Improvement | Y24: 3 | Z24: 3469 | AA24: 44934 | AB24: 5 | AC24: 5 | AD24: 44788 | AE24: Communication Skills | AF24: Internal | AG24: Failed | AH24: North Jeanetteville | AI24: Lisa Barnes | AJ24: 2 | AK24: 552.54
A25: 43 | B25: Esteban | C25: Gilbert | D25: 43418 | E25: 43766 | F25: =Messy_HR_Dataset_Detailed!$E25-Messy_HR_Dataset_Detailed!$D25 -> 348 | G25: =(Messy_HR_Dataset_Detailed!$E25-Messy_HR_Dataset_Detailed!$D25)/365.25 -> 0.95277207 | H25: Area Sales Manager | I25: Gail Ali | J25: esteban.gilbert@bilearner.com | K25: BPC | L25: Future Start | M25: Contract | N25: Zone C | O25: Part-Time | P25: Retirement | Q25: Sales | R25: Field Operations | S25: 31-05-1997 | T25: TX | U25: Technician | V25: Female | W25: 12491 | X25: Needs Improvement | Y25: 3 | Z25: 3470 | AA25: 45082 | AB25: 1 | AC25: 2 | AD25: 44830 | AE25: Project Management | AF25: External | AG25: Passed | AH25: New Molly | AI25: Katie Wong MD | AJ25: 1 | AK25: 986.96
A26: 48 | B26: Vance | C26: Trujillo | D26: 44460 | E26: 45029 | F26: =Messy_HR_Dataset_Detailed!$E26-Messy_HR_Dataset_Detailed!$D26 -> 569 | G26: =(Messy_HR_Dataset_Detailed!$E26-Messy_HR_Dataset_Detailed!$D26)/365.25 -> 1.5578371 | H26: Area Sales Manager | I26: Rebecca Simpson | J26: vance.trujillo@bilearner.com | K26: TNS | L26: Active | M26: Full-Time | N26: Zone C | O26: Temporary | P26: Resignation | Q26: Sales | R26: General - Con | S26: 25-12-1957 | T26: IN | U26: Foreman | V26: Male | W26: 90406 | X26: Fully Meets | Y26: 2 | Z26: 3475 | AA26: 25-01-2023 | AB26: 4 | AC26: 3 | AD26: 44867 | AE26: Customer Service | AF26: Internal | AG26: Passed | AH26: South Taylorfurt | AI26: Jenna Sherman | AJ26: 2 | AK26: 648.76
A27: 49 | B27: Charlie | C27: Koch | D27: 45089 | E27: 45113 | F27: =Messy_HR_Dataset_Detailed!$E27-Messy_HR_Dataset_Detailed!$D27 -> 24 | G27: =(Messy_HR_Dataset_Detailed!$E27-Messy_HR_Dataset_Detailed!$D27)/365.25 -> 0.065708419 | H27: Area Sales Manager | I27: Samantha Cardenas | J27: charlie.koch@bilearner.com | K27: PYZ | L27: Active | M27: Part-Time | N27: Zone A | O27: Temporary | P27: Voluntary | Q27: Sales | R27: Fielders | S27: 20-06-1945 | T27: MA | U27: Engineer | V27: Male | W27: 95774 | X27: Needs Improvement | Y27: 2 | Z27: 3476 | AA27: 44988 | AB27: 5 | AC27: 5 | AD27: 44883 | AE27: Leadership Development | AF27: Internal | AG27: Incomplete | AH27: Stephanieshire | AI27: Dr. Margaret Allen | AJ27: 4 | AK27: 533.5
A28: 51 | B28: Thomas | C28: Chandler | D28: 43360 | E28: 43474 | F28: =Messy_HR_Dataset_Detailed!$E28-Messy_HR_Dataset_Detailed!$D28 -> 114 | G28: =(Messy_HR_Dataset_Detailed!$E28-Messy_HR_Dataset_Detailed!$D28)/365.25 -> 0.31211499 | H28: Area Sales Manager | I28: Richard Hodges | J28: thomas.chandler@bilearner.com | K28: WBL | L28: Active | M28: Full-Time | N28: Zone C | O28: Temporary | P28: Resignation | Q28: Sales | R28: Wireline Construction | S28: 21103 | T28: KY | U28: Groundman | V28: Female | W28: 45149 | X28: Fully Meets | Y28: 2 | Z28: 3478 | AA28: 29-11-2022 | AB28: 3 | AC28: 4 | AD28: 44839 | AE28: Technical Skills | AF28: External | AG28: Incomplete | AH28: Port Matthew | AI28: Daniel Solomon | AJ28: 1 | AK28: 526.74
A29: 52 | B29: Sarai | C29: Stone | D29: 44775 | E29: 45018 | F29: =Messy_HR_Dataset_Detailed!$E29-Messy_HR_Dataset_Detailed!$D29 -> 243 | G29: =(Messy_HR_Dataset_Detailed!$E29-Messy_HR_Dataset_Detailed!$D29)/365.25 -> 0.66529774 | H29: Area Sales Manager | I29: Madison Wilson | J29: sarai.stone@bilearner.com | K29: NEL | L29: Active | M29: Contract | N29: Zone A | O29: Part-Time | P29: Involuntary | Q29: Sales | R29: Project Management - Con | S29: 17-05-1962 | T29: TX | U29: Technician | V29: Female | W29: 96336 | X29: Fully Meets | Y29: 2 | Z29: 3479 | AA29: 44631 | AB29: 4 | AC29: 4 | AD29: 44944 | AE29: Communication Skills | AF29: Internal | AG29: Passed | AH29: Stephanieburgh | AI29: Michael Dixon | AJ29: 3 | AK29: 443.45
A30: 53 | B30: Jerimiah | C30: Harmon | D30: 44812 | E30: 44850 | F30: =Messy_HR_Dataset_Detailed!$E30-Messy_HR_Dataset_Detailed!$D30 -> 38 | G30: =(Messy_HR_Dataset_Detailed!$E30-Messy_HR_Dataset_Detailed!$D30)/365.25 -> 0.10403833 | H30: Area Sales Manager | I30: Eric King | J30: jerimiah.harmon@bilearner.com | K30: PL | L30: Future Start | M30: Full-Time | N30: Zone C | O30: Temporary | P30: Retirement | Q30: Sales | R30: Catv | S30: 17053 | T30: TX | U30: Supervisor | V30: Female | W30: 75671 | X30: Fully Meets | Y30: 1 | Z30: 3480 | AA30: 25-07-2023 | AB30: 1 | AC30: 5 | AD30: 44987 | AE30: Leadership Development | AF30: External | AG30: Failed | AH30: North Amyfurt | AI30: Robert Hill | AJ30: 1 | AK30: 887.15
A31: 54 | B31: Leland | C31: Allen | D31: 43531 | E31: 44347 | F31: =Messy_HR_Dataset_Detailed!$E31-Messy_HR_Dataset_Detailed!$D31 -> 816 | G31: =(Messy_HR_Dataset_Detailed!$E31-Messy_HR_Dataset_Detailed!$D31)/365.25 -> 2.2340862 | H31: Area Sales Manager | I31: Brandon Harris | J31: leland.allen@bilearner.com | K31: BPC | L31: Future Start | M31: Full-Time | N31: Zone C | O31: Part-Time | P31: Voluntary | Q31: Sales | R31: Wireline Construction | S31: 24058 | T31: TX | U31: Splicer | V31: Male | W31: 61149 | X31: Fully Meets | Y31: 4 | Z31: 3481 | AA31: 44960 | AB31: 5 | AC31: 2 | AD31: 45075 | AE31: Technical Skills | AF31: External | AG31: Incomplete | AH31: East Charleston | AI31: Glenda Ryan | AJ31: 5 | AK31: 758.95
A32: 55 | B32: Cristal | C32: Bolton | D32: 43767 | E32: 44234 | F32: =Messy_HR_Dataset_Detailed!$E32-Messy_HR_Dataset_Detailed!$D32 -> 467 | G32: =(Messy_HR_Dataset_Detailed!$E32-Messy_HR_Dataset_Detailed!$D32)/365.25 -> 1.2785763 | H32: Area Sales Manager | I32: Matthew Flores | J32: cristal.bolton@bilearner.com | K32: CCDR | L32: Future Start | M32: Full-Time | N32: Zone A | O32: Temporary | P32: Resignation | Q32: Sales | R32: Catv | S32: 33179 | T32: TX | U32: Lineman | V32: Male | W32: 57302 | X32: Needs Improvement | Y32: 2 | Z32: 3482 | AA32: 22-10-2022 | AB32: 4 | AC32: 5 | AD32: 44988 | AE32: Technical Skills | AF32: Internal | AG32: Failed | AH32: Saraland | AI32: Jennifer Brown | AJ32: 1 | AK32: 627.11
A33: 59 | B33: Brendon | C33: Mcconnell | D33: 44865 | E33: 45085 | F33: =Messy_HR_Dataset_Detailed!$E33-Messy_HR_Dataset_Detailed!$D33 -> 220 | G33: =(Messy_HR_Dataset_Detailed!$E33-Messy_HR_Dataset_Detailed!$D33)/365.25 -> 0.60232717 | H33: Area Sales Manager | I33: Victoria Krause | J33: brendon.mcconnell@bilearner.com | K33: TNS | L33: Active | M33: Part-Time | N33: Zone C | O33: Temporary | P33: Involuntary | Q33: Sales | R33: Fielders | S33: 14-11-1990 | T33: IN | U33: Engineer | V33: Male | W33: 19665 | X33: Fully Meets | Y33: 4 | Z33: 3486 | AA33: 27-08-2022 | AB33: 3 | AC33: 1 | AD33: 45130 | AE33: Project Management | AF33: Internal | AG33: Completed | AH33: Lake Angelafort | AI33: Daniel Jones | AJ33: 5 | AK33: 812.59
A34: 68 | B34: Tia | C34: Ellis | D34: 45099 | E34: 45129 | F34: =Messy_HR_Dataset_Detailed!$E34-Messy_HR_Dataset_Detailed!$D34 -> 30 | G34: =(Messy_HR_Dataset_Detailed!$E34-Messy_HR_Dataset_Detailed!$D34)/365.25 -> 0.082135524 | H34: Area Sales Manager | I34: Daniel Cabrera | J34: tia.ellis@bilearner.com | K34: TNS | L34: Active | M34: Part-Time | N34: Zone B | O34: Temporary | P34: Retirement | Q34: Sales | R34: Wireline Construction | S34: 27-01-1993 | T34: IN | U34: Laborer | V34: Male | W34: 1115 | X34: Fully Meets | Y34: 4 | Z34: 3495 | AA34: 44782 | AB34: 4 | AC34: 3 | AD34: 44916 | AE34: Customer Service | AF34: External | AG34: Passed | AH34: Port Andrew | AI34: Christian Higgins | AJ34: 1 | AK34: 701.55
A35: 71 | B35: Joel | C35: Mcmillan | D35: 45042 | E35: 45099 | F35: =Messy_HR_Dataset_Detailed!$E35-Messy_HR_Dataset_Detailed!$D35 -> 57 | G35: =(Messy_HR_Dataset_Detailed!$E35-Messy_HR_Dataset_Detailed!$D35)/365.25 -> 0.15605749 | H35: Area Sales Manager | I35: Peter Harvey | J35: joel.mcmillan@bilearner.com | K35: PYZ | L35: Active | M35: Full-Time | N35: Zone A | O35: Full-Time | P35: Voluntary | Q35: Sales | R35: General - Sga | S35: 17-10-1998 | T35: KY | U35: Laborer | V35: Female | W35: 36087 | X35: Fully Meets | Y35: 2 | Z35: 3498 | AA35: 19-06-2023 | AB35: 3 | AC35: 3 | AD35: 45076 | AE35: Project Management | AF35: External | AG35: Failed | AH35: Yorkport | AI35: Amy Clark | AJ35: 1 | AK35: 208.43
A36: 72 | B36: Maci | C36: Frost | D36: 43368 | E36: 44550 | F36: =Messy_HR_Dataset_Detailed!$E36-Messy_HR_Dataset_Detailed!$D36 -> 1182 | G36: =(Messy_HR_Dataset_Detailed!$E36-Messy_HR_Dataset_Detailed!$D36)/365.25 -> 3.2361396 | H36: Area Sales Manager | I36: Patrick Daniel | J36: maci.frost@bilearner.com | K36: WBL | L36: Active | M36: Part-Time | N36: Zone C | O36: Temporary | P36: Involuntary | Q36: Sales | R36: Field Operations | S36: 16-01-1971 | T36: KY | U36: Technician | V36: Female | W36: 61457 | X36: Fully Meets | Y36: 5 | Z36: 3499 | AA36: 21-07-2023 | AB36: 5 | AC36: 3 | AD36: 44956 | AE36: Technical Skills | AF36: Internal | AG36: Incomplete | AH36: East Bradley | AI36: Angela Lee | AJ36: 2 | AK36: 762.45
A37: 73 | B37: Nevaeh | C37: Lucas | D37: 43424 | E37: 44003 | F37: =Messy_HR_Dataset_Detailed!$E37-Messy_HR_Dataset_Detailed!$D37 -> 579 | G37: =(Messy_HR_Dataset_Detailed!$E37-Messy_HR_Dataset_Detailed!$D37)/365.25 -> 1.5852156 | H37: Area Sales Manager | I37: Bryan Douglas | J37: nevaeh.lucas@bilearner.com | K37: NEL | L37: Active | M37: Full-Time | N37: Zone B | O37: Part-Time | P37: Voluntary | Q37: Sales | R37: Shop (Fleet) | S37: 25-02-2000 | T37: TX | U37: Mechanic | V37: Female | W37: 80424 | X37: Fully Meets | Y37: 1 | Z37: 3500 | AA37: 14-05-2023 | AB37: 4 | AC37: 1 | AD37: 45092 | AE37: Leadership Development | AF37: External | AG37: Incomplete | AH37: Smithchester | AI37: Larry Morales | AJ37: 4 | AK37: 779.79
A38: 74 | B38: Garrett | C38: Zimmerman | D38: 44073 | E38: 44803 | F38: =Messy_HR_Dataset_Detailed!$E38-Messy_HR_Dataset_Detailed!$D38 -> 730 | G38: =(Messy_HR_Dataset_Detailed!$E38-Messy_HR_Dataset_Detailed!$D38)/365.25 -> 1.9986311 | H38: Area Sales Manager | I38: Destiny Hopkins | J38: garrett.zimmerman@bilearner.com | K38: PL | L38: Future Start | M38: Part-Time | N38: Zone A | O38: Part-Time | P38: Retirement | Q38: Sales | R38: General - Con | S38: 19-04-1959 | T38: TX | U38: Technician | V38: Male | W38: 6240 | X38: Fully Meets | Y38: 4 | Z38: 3501 | AA38: 20-02-2023 | AB38: 2 | AC38: 3 | AD38: 45086 | AE38: Project Management | AF38: External | AG38: Passed | AH38: South Kaylachester | AI38: Troy Adams | AJ38: 3 | AK38: 135.95
A39: 79 | B39: Laila | C39: Woodard | D39: 43704 | E39: 45056 | F39: =Messy_HR_Dataset_Detailed!$E39-Messy_HR_Dataset_Detailed!$D39 -> 1352 | G39: =(Messy_HR_Dataset_Detailed!$E39-Messy_HR_Dataset_Detailed!$D39)/365.25 -> 3.7015743 | H39: Area Sales Manager | I39: Jordan Vega | J39: laila.woodard@bilearner.com | K39: MSC | L39: Active | M39: Full-Time | N39: Zone B | O39: Temporary | P39: Voluntary | Q39: Sales | R39: Field Operations | S39: 32301 | T39: IN | U39: Technician | V39: Male | W39: 38740 | X39: Fully Meets | Y39: 2 | Z39: 3506 | AA39: 27-06-2023 | AB39: 2 | AC39: 2 | AD39: 45067 | AE39: Leadership Development | AF39: Internal | AG39: Completed | AH39: Deleonport | AI39: Jonathan Peterson | AJ39: 1 | AK39: 781.81
A40: 80 | B40: Ivan | C40: Huff | D40: 44252 | E40: 45023 | F40: =Messy_HR_Dataset_Detailed!$E40-Messy_HR_Dataset_Detailed!$D40 -> 771 | G40: =(Messy_HR_Dataset_Detailed!$E40-Messy_HR_Dataset_Detailed!$D40)/365.25 -> 2.110883 | H40: Area Sales Manager | I40: John Miller | J40: ivan.huff@bilearner.com | K40: TNS | L40: Active | M40: Full-Time | N40: Zone A | O40: Full-Time | P40: Retirement | Q40: Sales | R40: Project Management - Con | S40: 24-03-1973 | T40: CA | U40: Manager | V40: Male | W40: 9437 | X40: Fully Meets | Y40: 4 | Z40: 3507 | AA40: 31-03-2023 | AB40: 2 | AC40: 5 | AD40: 45071 | AE40: Project Management | AF40: Internal | AG40: Passed | AH40: Loriberg | AI40: Michael Copeland | AJ40: 4 | AK40: 651.77
A41: 84 | B41: Karli | C41: Barker | D41: 44425 | E41: 44561 | F41: =Messy_HR_Dataset_Detailed!$E41-Messy_HR_Dataset_Detailed!$D41 -> 136 | G41: =(Messy_HR_Dataset_Detailed!$E41-Messy_HR_Dataset_Detailed!$D41)/365.25 -> 0.37234771 | H41: Area Sales Manager | I41: Shawn Dudley | J41: karli.barker@bilearner.com | K41: WBL | L41: Active | M41: Part-Time | N41: Zone B | O41: Full-Time | P41: Resignation | Q41: Sales | R41: Finance & Accounting | S41: 18-02-1997 | T41: KY | U41: Director | V41: Female | W41: 41111 | X41: Fully Meets | Y41: 4 | Z41: 3511 | AA41: 45235 | AB41: 5 | AC41: 4 | AD41: 45023 | AE41: Technical Skills | AF41: Internal | AG41: Completed | AH41: Anthonyville | AI41: Juan Peck | AJ41: 3 | AK41: 344.44
A42: 85 | B42: Tyrone | C42: Sosa | D42: 45033 | E42: 45099 | F42: =Messy_HR_Dataset_Detailed!$E42-Messy_HR_Dataset_Detailed!$D42 -> 66 | G42: =(Messy_HR_Dataset_Detailed!$E42-Messy_HR_Dataset_Detailed!$D42)/365.25 -> 0.18069815 | H42: Area Sales Manager | I42: Lindsay Chang | J42: tyrone.sosa@bilearner.com | K42: NEL | L42: Future Start | M42: Contract | N42: Zone C | O42: Temporary | P42: Voluntary | Q42: Sales | R42: Yard (Material Handling) | S42: 25-10-1996 | T42: TX | U42: Coordinator | V42: Female | W42: 58860 | X42: Fully Meets | Y42: 2 | Z42: 3512 | AA42: 20-02-2023 | AB42: 5 | AC42: 1 | AD42: 44890 | AE42: Communication Skills | AF42: Internal | AG42: Failed | AH42: Bryantport | AI42: Sharon Miller | AJ42: 2 | AK42: 206.44
A43: 86 | B43: Damaris | C43: Cisneros | D43: 44806 | E43: 45070 | F43: =Messy_HR_Dataset_Detailed!$E43-Messy_HR_Dataset_Detailed!$D43 -> 264 | G43: =(Messy_HR_Dataset_Detailed!$E43-Messy_HR_Dataset_Detailed!$D43)/365.25 -> 0.72279261 | H43: Area Sales Manager | I43: Sharon Ruiz | J43: damaris.cisneros@bilearner.com | K43: PL | L43: Future Start | M43: Contract | N43: Zone C | O43: Temporary | P43: Involuntary | Q43: Sales | R43: General - Con | S43: 13-11-1959 | T43: TX | U43: Laborer | V43: Male | W43: 93051 | X43: Fully Meets | Y43: 5 | Z43: 3513 | AA43: 45235 | AB43: 4 | AC43: 1 | AD43: 45080 | AE43: Communication Skills | AF43: External | AG43: Completed | AH43: East Adam | AI43: Katie Harrington | AJ43: 1 | AK43: 599
A44: 88 | B44: Kinsley | C44: Flowers | D44: 44629 | E44: 44905 | F44: =Messy_HR_Dataset_Detailed!$E44-Messy_HR_Dataset_Detailed!$D44 -> 276 | G44: =(Messy_HR_Dataset_Detailed!$E44-Messy_HR_Dataset_Detailed!$D44)/365.25 -> 0.75564682 | H44: Area Sales Manager | I44: Mary Reilly | J44: kinsley.flowers@bilearner.com | K44: CCDR | L44: Future Start | M44: Part-Time | N44: Zone A | O44: Part-Time | P44: Retirement | Q44: Sales | R44: Finance & Accounting | S44: 29-04-1997 | T44: CO | U44: Controller | V44: Male | W44: 59593 | X44: Fully Meets | Y44: 4 | Z44: 3515 | AA44: 44992 | AB44: 3 | AC44: 5 | AD44: 44961 | AE44: Customer Service | AF44: Internal | AG44: Completed | AH44: West Keith | AI44: Elizabeth Cook | AJ44: 1 | AK44: 143.96
A45: 89 | B45: Deborah | C45: Love | D45: 44658 | E45: 44948 | F45: =Messy_HR_Dataset_Detailed!$E45-Messy_HR_Dataset_Detailed!$D45 -> 290 | G45: =(Messy_HR_Dataset_Detailed!$E45-Messy_HR_Dataset_Detailed!$D45)/365.25 -> 0.79397673 | H45: Area Sales Manager | I45: Eric Goodman | J45: deborah.love@bilearner.com | K45: SVG | L45: Active | M45: Contract | N45: Zone B | O45: Part-Time | P45: Retirement | Q45: Sales | R45: Project Management - Con | S45: 25-06-1988 | T45: CO | U45: Coordinator | V45: Male | W45: 96350 | X45: Fully Meets | Y45: 5 | Z45: 3516 | AA45: 15-11-2022 | AB45: 2 | AC45: 3 | AD45: 45099 | AE45: Technical Skills | AF45: Internal | AG45: Incomplete | AH45: Lake Stephen | AI45: Gregory Kramer | AJ45: 1 | AK45: 570.42
A46: 91 | B46: Roberto | C46: Michael | D46: 44296 | E46: 44746 | F46: =Messy_HR_Dataset_Detailed!$E46-Messy_HR_Dataset_Detailed!$D46 -> 450 | G46: =(Messy_HR_Dataset_Detailed!$E46-Messy_HR_Dataset_Detailed!$D46)/365.25 -> 1.2320329 | H46: Area Sales Manager | I46: Cheryl Henry | J46: roberto.michael@bilearner.com | K46: MSC | L46: Active | M46: Contract | N46: Zone B | O46: Part-Time | P46: Involuntary | Q46: Sales | R46: General - Eng | S46: 24-05-1969 | T46: CA | U46: Coordinator | V46: Female | W46: 13249 | X46: Fully Meets | Y46: 2 | Z46: 3518 | AA46: 13-05-2023 | AB46: 4 | AC46: 2 | AD46: 45104 | AE46: Customer Service | AF46: Internal | AG46: Completed | AH46: Port Vanessafort | AI46: Michael Parker | AJ46: 3 | AK46: 826.58
A47: 92 | B47: Elaine | C47: Ewing | D47: 44549 | E47: 44622 | F47: =Messy_HR_Dataset_Detailed!$E47-Messy_HR_Dataset_Detailed!$D47 -> 73 | G47: =(Messy_HR_Dataset_Detailed!$E47-Messy_HR_Dataset_Detailed!$D47)/365.25 -> 0.19986311 | H47: Area Sales Manager | I47: Dan Hernandez | J47: elaine.ewing@bilearner.com | K47: TNS | L47: Active | M47: Part-Time | N47: Zone C | O47: Temporary | P47: Resignation | Q47: Sales | R47: Aerial | S47: 28-03-1951 | T47: CA | U47: Groundman | V47: Male | W47: 17123 | X47: Fully Meets | Y47: 2 | Z47: 3519 | AA47: 45205 | AB47: 1 | AC47: 3 | AD47: 44906 | AE47: Leadership Development | AF47: External | AG47: Incomplete | AH47: Deborahshire | AI47: Patrick Reeves | AJ47: 4 | AK47: 930.69
A48: 93 | B48: Caiden | C48: Munoz | D48: 44178 | E48: 44939 | F48: =Messy_HR_Dataset_Detailed!$E48-Messy_HR_Dataset_Detailed!$D48 -> 761 | G48: =(Messy_HR_Dataset_Detailed!$E48-Messy_HR_Dataset_Detailed!$D48)/365.25 -> 2.0835044 | H48: Area Sales Manager | I48: Teresa Daniel | J48: caiden.munoz@bilearner.com | K48: TNS | L48: Active | M48: Full-Time | N48: Zone C | O48: Temporary | P48: Involuntary | Q48: Sales | R48: Project Management - Con | S48: 23014 | T48: ND | U48: Manager | V48: Female | W48: 18983 | X48: Fully Meets | Y48: 1 | Z48: 3520 | AA48: 17-09-2022 | AB48: 5 | AC48: 1 | AD48: 44815 | AE48: Customer Service | AF48: External | AG48: Incomplete | AH48: North Anthonybury | AI48: Robin Sims | AJ48: 1 | AK48: 607.93
A49: 96 | B49: Rohan | C49: Chapman | D49: 44372 | E49: 44798 | F49: =Messy_HR_Dataset_Detailed!$E49-Messy_HR_Dataset_Detailed!$D49 -> 426 | G49: =(Messy_HR_Dataset_Detailed!$E49-Messy_HR_Dataset_Detailed!$D49)/365.25 -> 1.1663244 | H49: Area Sales Manager | I49: Tony Mcconnell | J49: rohan.chapman@bilearner.com | K49: CCDR | L49: Active | M49: Full-Time | N49: Zone A | O49: Temporary | P49: Resignation | Q49: Sales | R49: General - Con | S49: 19-12-1978 | T49: KY | U49: Laborer | V49: Female | W49: 23092 | X49: Fully Meets | Y49: 2 | Z49: 3523 | AA49: 27-02-2023 | AB49: 3 | AC49: 2 | AD49: 45117 | AE49: Leadership Development | AF49: External | AG49: Incomplete | AH49: South William | AI49: Felicia Berg | AJ49: 2 | AK49: 451.18
A50: 97 | B50: Emmanuel | C50: Franklin | D50: 44403 | E50: 44685 | F50: =Messy_HR_Dataset_Detailed!$E50-Messy_HR_Dataset_Detailed!$D50 -> 282 | G50: =(Messy_HR_Dataset_Detailed!$E50-Messy_HR_Dataset_Detailed!$D50)/365.25 -> 0.77207392 | H50: Area Sales Manager | I50: Adam Gibson | J50: emmanuel.franklin@bilearner.com | K50: EW | L50: Future Start | M50: Contract | N50: Zone B | O50: Full-Time | P50: Resignation | Q50: Sales | R50: Field Operations | S50: 36475 | T50: TX | U50: Laborer | V50: Male | W50: 6074 | X50: Fully Meets | Y50: 2 | Z50: 3524 | AA50: 19-05-2023 | AB50: 3 | AC50: 2 | AD50: 44928 | AE50: Communication Skills | AF50: Internal | AG50: Completed | AH50: Wilsonmouth | AI50: Jessica Vazquez | AJ50: 5 | AK50: 124.65
A51: 98 | B51: Clayton | C51: Mccormick | D51: 44745 | E51: 44936 | F51: =Messy_HR_Dataset_Detailed!$E51-Messy_HR_Dataset_Detailed!$D51 -> 191 | G51: =(Messy_HR_Dataset_Detailed!$E51-Messy_HR_Dataset_Detailed!$D51)/365.25 -> 0.5229295 | H51: Area Sales Manager | I51: Stephanie Duke | J51: clayton.mccormick@bilearner.com | K51: MSC | L51: Future Start | M51: Contract | N51: Zone B | O51: Temporary | P51: Retirement | Q51: Sales | R51: General - Con | S51: 29-01-1967 | T51: TX | U51: Foreman | V51: Male | W51: 72264 | X51: Fully Meets | Y51: 2 | Z51: 3525 | AA51: 44928 | AB51: 1 | AC51: 2 | AD51: 44843 | AE51: Leadership Development | AF51: External | AG51: Incomplete | AH51: East Michaelburgh | AI51: Tara Christensen | AJ51: 4 | AK51: 237.75
A52: 100 | B52: Ahmed | C52: Hawkins | D52: 43952 | E52: 44252 | F52: =Messy_HR_Dataset_Detailed!$E52-Messy_HR_Dataset_Detailed!$D52 -> 300 | G52: =(Messy_HR_Dataset_Detailed!$E52-Messy_HR_Dataset_Detailed!$D52)/365.25 -> 0.82135524 | H52: Area Sales Manager | I52: Hannah Snyder | J52: ahmed.hawkins@bilearner.com | K52: PL | L52: Active | M52: Full-Time | N52: Zone B | O52: Temporary | P52: Retirement | Q52: Sales | R52: Aerial | S52: 15-10-1974 | T52: CO | U52: Lineman | V52: Male | W52: 46645 | X52: Fully Meets | Y52: 1 | Z52: 3527 | AA52: 27-02-2023 | AB52: 1 | AC52: 3 | AD52: 44932 | AE52: Project Management | AF52: Internal | AG52: Failed | AH52: Berryland | AI52: Scott Richardson | AJ52: 4 | AK52: 396.28
A53: 102 | B53: Callum | C53: Mcdaniel | D53: 43833 | E53: 44067 | F53: =Messy_HR_Dataset_Detailed!$E53-Messy_HR_Dataset_Detailed!$D53 -> 234 | G53: =(Messy_HR_Dataset_Detailed!$E53-Messy_HR_Dataset_Detailed!$D53)/365.25 -> 0.64065708 | H53: Area Sales Manager | I53: Samuel Moore | J53: callum.mcdaniel@bilearner.com | K53: SVG | L53: Active | M53: Part-Time | N53: Zone C | O53: Full-Time | P53: Voluntary | Q53: Sales | R53: Field Operations | S53: 18-06-1994 | T53: IN | U53: Top Hand | V53: Male | W53: 67282 | X53: Fully Meets | Y53: 2 | Z53: 3529 | AA53: 15-07-2023 | AB53: 2 | AC53: 3 | AD53: 44808 | AE53: Project Management | AF53: Internal | AG53: Incomplete | AH53: South Andretown | AI53: Julie Hoffman | AJ53: 1 | AK53: 515.56
A54: 106 | B54: Slade | C54: Griffith | D54: 44348 | E54: 45123 | F54: =Messy_HR_Dataset_Detailed!$E54-Messy_HR_Dataset_Detailed!$D54 -> 775 | G54: =(Messy_HR_Dataset_Detailed!$E54-Messy_HR_Dataset_Detailed!$D54)/365.25 -> 2.1218344 | H54: Area Sales Manager | I54: Kelsey Gibson | J54: slade.griffith@bilearner.com | K54: MSC | L54: Active | M54: Contract | N54: Zone B | O54: Full-Time | P54: Voluntary | Q54: Sales | R54: General - Sga | S54: 24452 | T54: ND | U54: Administrator | V54: Male | W54: 65183 | X54: Fully Meets | Y54: 2 | Z54: 3533 | AA54: 45139 | AB54: 2 | AC54: 5 | AD54: 45057 | AE54: Leadership Development | AF54: Internal | AG54: Completed | AH54: North Janet | AI54: Jamie Dougherty | AJ54: 4 | AK54: 418.4
A55: 108 | B55: Veronica | C55: Rowe | D55: 43445 | E55: 44714 | F55: =Messy_HR_Dataset_Detailed!$E55-Messy_HR_Dataset_Detailed!$D55 -> 1269 | G55: =(Messy_HR_Dataset_Detailed!$E55-Messy_HR_Dataset_Detailed!$D55)/365.25 -> 3.4743326 | H55: Area Sales Manager | I55: Brian Morton | J55: veronica.rowe@bilearner.com | K55: PYZ | L55: Active | M55: Full-Time | N55: Zone A | O55: Temporary | P55: Retirement | Q55: Sales | R55: Fielders | S55: 34367 | T55: KY | U55: Engineer | V55: Female | W55: 29811 | X55: Fully Meets | Y55: 4 | Z55: 3535 | AA55: 44572 | AB55: 1 | AC55: 5 | AD55: 45102 | AE55: Technical Skills | AF55: External | AG55: Incomplete | AH55: Derrickview | AI55: Katherine Valentine | AJ55: 1 | AK55: 936.96
A56: 110 | B56: Neveah | C56: Rowe | D56: 44709 | E56: 44981 | F56: =Messy_HR_Dataset_Detailed!$E56-Messy_HR_Dataset_Detailed!$D56 -> 272 | G56: =(Messy_HR_Dataset_Detailed!$E56-Messy_HR_Dataset_Detailed!$D56)/365.25 -> 0.74469541 | H56: Area Sales Manager | I56: Dawn Perez | J56: neveah.rowe@bilearner.com | K56: NEL | L56: Future Start | M56: Contract | N56: Zone C | O56: Part-Time | P56: Retirement | Q56: Sales | R56: Field Operations | S56: 20035 | T56: TX | U56: Foreman | V56: Male | W56: 63882 | X56: Fully Meets | Y56: 2 | Z56: 3537 | AA56: 44813 | AB56: 4 | AC56: 2 | AD56: 44963 | AE56: Leadership Development | AF56: Internal | AG56: Completed | AH56: Griffintown | AI56: Janice Leblanc | AJ56: 4 | AK56: 853.77
A57: 111 | B57: Keith | C57: Baxter | D57: 43632 | E57: 44625 | F57: =Messy_HR_Dataset_Detailed!$E57-Messy_HR_Dataset_Detailed!$D57 -> 993 | G57: =(Messy_HR_Dataset_Detailed!$E57-Messy_HR_Dataset_Detailed!$D57)/365.25 -> 2.7186858 | H57: Area Sales Manager | I57: Diane Parker | J57: keith.baxter@bilearner.com | K57: PL | L57: Future Start | M57: Part-Time | N57: Zone C | O57: Part-Time | P57: Resignation | Q57: Sales | R57: Fielders | S57: 29-08-1959 | T57: TX | U57: Engineer | V57: Male | W57: 62328 | X57: Fully Meets | Y57: 2 | Z57: 3538 | AA57: 20-04-2023 | AB57: 1 | AC57: 5 | AD57: 44840 | AE57: Technical Skills | AF57: Internal | AG57: Failed | AH57: East Crystal | AI57: Joshua Mcguire | AJ57: 4 | AK57: 141.07
A58: 113 | B58: Maya | C58: Mccann | D58: 43902 | E58: 44843 | F58: =Messy_HR_Dataset_Detailed!$E58-Messy_HR_Dataset_Detailed!$D58 -> 941 | G58: =(Messy_HR_Dataset_Detailed!$E58-Messy_HR_Dataset_Detailed!$D58)/365.25 -> 2.5763176 | H58: Area Sales Manager | I58: Dakota Robinson | J58: maya.mccann@bilearner.com | K58: CCDR | L58: Active | M58: Full-Time | N58: Zone B | O58: Part-Time | P58: Retirement | Q58: Sales | R58: Splicing | S58: 30565 | T58: CO | U58: Supervisor | V58: Male | W58: 18721 | X58: Exceeds | Y58: 4 | Z58: 3540 | AA58: 25-06-2023 | AB58: 2 | AC58: 2 | AD58: 44860 | AE58: Communication Skills | AF58: External | AG58: Incomplete | AH58: West Josephmouth | AI58: Kristin Rodriguez | AJ58: 2 | AK58: 903.46
A59: 114 | B59: Aaron | C59: Weber | D59: 43927 | E59: 45131 | F59: =Messy_HR_Dataset_Detailed!$E59-Messy_HR_Dataset_Detailed!$D59 -> 1204 | G59: =(Messy_HR_Dataset_Detailed!$E59-Messy_HR_Dataset_Detailed!$D59)/365.25 -> 3.2963723 | H59: Area Sales Manager | I59: Melanie Garcia | J59: aaron.weber@bilearner.com | K59: SVG | L59: Active | M59: Full-Time | N59: Zone B | O59: Full-Time | P59: Involuntary | Q59: Sales | R59: Field Operations | S59: 27-10-1991 | T59: IN | U59: Technician | V59: Male | W59: 78938 | X59: Exceeds | Y59: 2 | Z59: 3541 | AA59: 28-11-2022 | AB59: 1 | AC59: 3 | AD59: 45068 | AE59: Customer Service | AF59: External | AG59: Passed | AH59: East Timothy | AI59: Ronald Butler | AJ59: 4 | AK59: 380.3
A60: 117 | B60: Samara | C60: Mcbride | D60: 45106 | E60: 45116 | F60: =Messy_HR_Dataset_Detailed!$E60-Messy_HR_Dataset_Detailed!$D60 -> 10 | G60: =(Messy_HR_Dataset_Detailed!$E60-Messy_HR_Dataset_Detailed!$D60)/365.25 -> 0.027378508 | H60: Area Sales Manager | I60: Laura Salinas | J60: samara.mcbride@bilearner.com | K60: TNS | L60: Active | M60: Contract | N60: Zone A | O60: Temporary | P60: Retirement | Q60: Sales | R60: Aerial | S60: 16-09-2000 | T60: CA | U60: Foreman | V60: Male | W60: 13902 | X60: Fully Meets | Y60: 2 | Z60: 3544 | AA60: 14-09-2022 | AB60: 3 | AC60: 5 | AD60: 45048 | AE60: Leadership Development | AF60: External | AG60: Passed | AH60: Rayborough | AI60: Mrs. Nicole Simon | AJ60: 3 | AK60: 842.93
A61: 119 | B61: Paris | C61: Carr | D61: 44408 | E61: 44953 | F61: =Messy_HR_Dataset_Detailed!$E61-Messy_HR_Dataset_Detailed!$D61 -> 545 | G61: =(Messy_HR_Dataset_Detailed!$E61-Messy_HR_Dataset_Detailed!$D61)/365.25 -> 1.4921287 | H61: Area Sales Manager | I61: Jeffrey Huffman | J61: paris.carr@bilearner.com | K61: CCDR | L61: Active | M61: Full-Time | N61: Zone B | O61: Part-Time | P61: Voluntary | Q61: Sales | R61: General - Con | S61: 14-07-1980 | T61: ND | U61: Foreman | V61: Male | W61: 35786 | X61: Exceeds | Y61: 1 | Z61: 3546 | AA61: 45204 | AB61: 2 | AC61: 5 | AD61: 44886 | AE61: Project Management | AF61: External | AG61: Passed | AH61: New Faith | AI61: Stephanie Horton | AJ61: 4 | AK61: 426.45
A62: 121 | B62: Sanaa | C62: Glass | D62: 44388 | E62: 44844 | F62: =Messy_HR_Dataset_Detailed!$E62-Messy_HR_Dataset_Detailed!$D62 -> 456 | G62: =(Messy_HR_Dataset_Detailed!$E62-Messy_HR_Dataset_Detailed!$D62)/365.25 -> 1.24846 | H62: Area Sales Manager | I62: Stephen Garcia | J62: sanaa.glass@bilearner.com | K62: WBL | L62: Active | M62: Part-Time | N62: Zone A | O62: Full-Time | P62: Resignation | Q62: Sales | R62: General - Con | S62: 25-01-1964 | T62: KY | U62: Technician | V62: Female | W62: 40135 | X62: Fully Meets | Y62: 1 | Z62: 3548 | AA62: 44722 | AB62: 5 | AC62: 5 | AD62: 44789 | AE62: Leadership Development | AF62: External | AG62: Passed | AH62: Lake Tinamouth | AI62: Corey Hernandez | AJ62: 3 | AK62: 368.8
A63: 122 | B63: Ryan | C63: Lynch | D63: 43388 | E63: 44122 | F63: =Messy_HR_Dataset_Detailed!$E63-Messy_HR_Dataset_Detailed!$D63 -> 734 | G63: =(Messy_HR_Dataset_Detailed!$E63-Messy_HR_Dataset_Detailed!$D63)/365.25 -> 2.0095825 | H63: Area Sales Manager | I63: Tracy Castro MD | J63: ryan.lynch@bilearner.com | K63: TNS | L63: Active | M63: Full-Time | N63: Zone C | O63: Full-Time | P63: Retirement | Q63: Sales | R63: Field Operations | S63: 17-03-1955 | T63: GA | U63: Technician | V63: Female | W63: 72975 | X63: Fully Meets | Y63: 2 | Z63: 3549 | AA63: 19-04-2023 | AB63: 1 | AC63: 4 | AD63: 44867 | AE63: Communication Skills | AF63: External | AG63: Failed | AH63: Claudiashire | AI63: John Gutierrez DDS | AJ63: 5 | AK63: 788.67
A64: 123 | B64: Charlie | C64: Atkinson | D64: 44526 | E64: 44848 | F64: =Messy_HR_Dataset_Detailed!$E64-Messy_HR_Dataset_Detailed!$D64 -> 322 | G64: =(Messy_HR_Dataset_Detailed!$E64-Messy_HR_Dataset_Detailed!$D64)/365.25 -> 0.88158795 | H64: Area Sales Manager | I64: Jennifer Hicks | J64: charlie.atkinson@bilearner.com | K64: SVG | L64: Future Start | M64: Part-Time | N64: Zone C | O64: Temporary | P64: Resignation | Q64: Sales | R64: Wireline Construction | S64: 26-03-1988 | T64: TX | U64: Billing | V64: Male | W64: 57754 | X64: Fully Meets | Y64: 1 | Z64: 3550 | AA64: 23-01-2023 | AB64: 3 | AC64: 5 | AD64: 45025 | AE64: Project Management | AF64: Internal | AG64: Completed | AH64: New Bonnie | AI64: Lisa Gibbs | AJ64: 4 | AK64: 363.11
A65: 125 | B65: Harper | C65: Ramos | D65: 43877 | E65: 43985 | F65: =Messy_HR_Dataset_Detailed!$E65-Messy_HR_Dataset_Detailed!$D65 -> 108 | G65: =(Messy_HR_Dataset_Detailed!$E65-Messy_HR_Dataset_Detailed!$D65)/365.25 -> 0.29568789 | H65: Area Sales Manager | I65: Maria Chan | J65: harper.ramos@bilearner.com | K65: PL | L65: Active | M65: Full-Time | N65: Zone B | O65: Full-Time | P65: Retirement | Q65: Sales | R65: Field Operations | S65: 15653 | T65: CO | U65: Foreman | V65: Male | W65: 28714 | X65: Needs Improvement | Y65: 1 | Z65: 3552 | AA65: 14-10-2022 | AB65: 3 | AC65: 4 | AD65: 44891 | AE65: Leadership Development | AF65: External | AG65: Failed | AH65: Charlottebury | AI65: John Miller | AJ65: 4 | AK65: 480.87
A66: 128 | B66: Matilda | C66: Randall | D66: 44932 | E66: 45053 | F66: =Messy_HR_Dataset_Detailed!$E66-Messy_HR_Dataset_Detailed!$D66 -> 121 | G66: =(Messy_HR_Dataset_Detailed!$E66-Messy_HR_Dataset_Detailed!$D66)/365.25 -> 0.33127995 | H66: Area Sales Manager | I66: Daniel Wolf | J66: matilda.randall@bilearner.com | K66: EW | L66: Active | M66: Full-Time | N66: Zone C | O66: Temporary | P66: Resignation | Q66: Sales | R66: General - Eng | S66: 32448 | T66: IN | U66: Drafter | V66: Female | W66: 48104 | X66: Fully Meets | Y66: 4 | Z66: 3555 | AA66: 13-01-2023 | AB66: 2 | AC66: 5 | AD66: 44989 | AE66: Leadership Development | AF66: External | AG66: Passed | AH66: Nashview | AI66: Darlene Vega | AJ66: 4 | AK66: 566.12
A67: 129 | B67: Damien | C67: Howe | D67: 43664 | E67: 43845 | F67: =Messy_HR_Dataset_Detailed!$E67-Messy_HR_Dataset_Detailed!$D67 -> 181 | G67: =(Messy_HR_Dataset_Detailed!$E67-Messy_HR_Dataset_Detailed!$D67)/365.25 -> 0.49555099 | H67: Area Sales Manager | I67: Sarah Petersen | J67: damien.howe@bilearner.com | K67: CCDR | L67: Active | M67: Full-Time | N67: Zone B | O67: Temporary | P67: Retirement | Q67: Sales | R67: Wireline Construction | S67: 16-06-1961 | T67: CA | U67: Vp | V67: Male | W67: 86009 | X67: Exceeds | Y67: 2 | Z67: 3556 | AA67: 45236 | AB67: 2 | AC67: 2 | AD67: 44968 | AE67: Customer Service | AF67: Internal | AG67: Incomplete | AH67: Christinastad | AI67: Mandy Morrison | AJ67: 1 | AK67: 513.92
A68: 132 | B68: Wilson K | C68: Adinolfi | D68: 43775 | E68: 44080 | F68: =Messy_HR_Dataset_Detailed!$E68-Messy_HR_Dataset_Detailed!$D68 -> 305 | G68: =(Messy_HR_Dataset_Detailed!$E68-Messy_HR_Dataset_Detailed!$D68)/365.25 -> 0.83504449 | H68: Production Technician I | I68: Andrea Gutierrez | J68: wilson k.adinolfi@bilearner.com | K68: NEL | L68: Active | M68: Part-Time | N68: Zone C | O68: Full-Time | P68: Retirement | Q68: Production | R68: Field Operations | S68: 18-11-1991 | T68: MA | U68: Assistant | V68: Male | W68: 1960 | X68: Fully Meets | Y68: 2 | Z68: 3559 | AA68: 27-12-2022 | AB68: 3 | AC68: 2 | AD68: 44895 | AE68: Project Management | AF68: External | AG68: Failed | AH68: West Michelletown | AI68: John Allen | AJ68: 2 | AK68: 959.81
A69: 135 | B69: Jean | C69: Crimmings | D69: 43606 | E69: 44931 | F69: =Messy_HR_Dataset_Detailed!$E69-Messy_HR_Dataset_Detailed!$D69 -> 1325 | G69: =(Messy_HR_Dataset_Detailed!$E69-Messy_HR_Dataset_Detailed!$D69)/365.25 -> 3.6276523 | H69: Production Technician I | I69: Stephen Rodriguez | J69: jean.crimmings@bilearner.com | K69: CCDR | L69: Future Start | M69: Contract | N69: Zone B | O69: Full-Time | P69: Retirement | Q69: Production | R69: Shop (Fleet) | S69: 19971 | T69: MA | U69: Manager | V69: Female | W69: 1821 | X69: Exceeds | Y69: 2 | Z69: 3562 | AA69: 27-11-2022 | AB69: 2 | AC69: 1 | AD69: 44928 | AE69: Project Management | AF69: External | AG69: Failed | AH69: West William | AI69: Jason Gallegos | AJ69: 3 | AK69: 808.05
A70: 137 | B70: Susan | C70: Lundy | D70: 43491 | E70: 44167 | F70: =Messy_HR_Dataset_Detailed!$E70-Messy_HR_Dataset_Detailed!$D70 -> 676 | G70: =(Messy_HR_Dataset_Detailed!$E70-Messy_HR_Dataset_Detailed!$D70)/365.25 -> 1.8507871 | H70: Production Technician II | I70: Diana Johnson | J70: susan.lundy@bilearner.com | K70: SVG | L70: Voluntarily Terminated | M70: Full-Time | N70: Zone C | O70: Temporary | P70: Resignation | Q70: Production | R70: Aerial | S70: 34526 | T70: MA | U70: Lineman | V70: Female | W70: 2122 | X70: Fully Meets | Y70: 1 | Z70: 3564 | AA70: 45263 | AB70: 4 | AC70: 4 | AD70: 44905 | AE70: Technical Skills | AF70: External | AG70: Incomplete | AH70: North Richard | AI70: Kimberly Thomas | AJ70: 4 | AK70: 106.14
A71: 141 | B71: Quinn | C71: Rarrick | D71: 45118 | E71: 45136 | F71: =Messy_HR_Dataset_Detailed!$E71-Messy_HR_Dataset_Detailed!$D71 -> 18 | G71: =(Messy_HR_Dataset_Detailed!$E71-Messy_HR_Dataset_Detailed!$D71)/365.25 -> 0.049281314 | H71: Production Technician I | I71: Susan Brown | J71: quinn.rarrick@bilearner.com | K71: EW | L71: Voluntarily Terminated | M71: Full-Time | N71: Zone B | O71: Part-Time | P71: Involuntary | Q71: Production | R71: Field Operations | S71: 27253 | T71: MA | U71: Foreman | V71: Male | W71: 2478 | X71: Fully Meets | Y71: 2 | Z71: 3568 | AA71: 45109 | AB71: 2 | AC71: 4 | AD71: 44796 | AE71: Project Management | AF71: Internal | AG71: Incomplete | AH71: Frenchside | AI71: Anthony Nixon | AJ71: 2 | AK71: 201.76
A72: 142 | B72: Beatrice | C72: Chace | D72: 43505 | E72: 44071 | F72: =Messy_HR_Dataset_Detailed!$E72-Messy_HR_Dataset_Detailed!$D72 -> 566 | G72: =(Messy_HR_Dataset_Detailed!$E72-Messy_HR_Dataset_Detailed!$D72)/365.25 -> 1.5496235 | H72: Production Technician I | I72: Margaret Hampton | J72: beatrice.chace@bilearner.com | K72: MSC | L72: Active | M72: Part-Time | N72: Zone B | O72: Temporary | P72: Involuntary | Q72: Production | R72: Catv | S72: 19-07-1995 | T72: MA | U72: Supervisor | V72: Female | W72: 2763 | X72: Fully Meets | Y72: 2 | Z72: 3569 | AA72: 24-12-2022 | AB72: 1 | AC72: 3 | AD72: 44874 | AE72: Technical Skills | AF72: External | AG72: Incomplete | AH72: Fernandezborough | AI72: Rachel Foster | AJ72: 4 | AK72: 730.04
A73: 143 | B73: Adrienne J | C73: Homberger | D73: 43574 | E73: 44495 | F73: =Messy_HR_Dataset_Detailed!$E73-Messy_HR_Dataset_Detailed!$D73 -> 921 | G73: =(Messy_HR_Dataset_Detailed!$E73-Messy_HR_Dataset_Detailed!$D73)/365.25 -> 2.5215606 | H73: Production Technician II | I73: Brandon Miller | J73: adrienne j.homberger@bilearner.com | K73: TNS | L73: Voluntarily Terminated | M73: Full-Time | N73: Zone B | O73: Temporary | P73: Voluntary | Q73: Production | R73: Fielders | S73: 23-11-1974 | T73: MA | U73: Engineer | V73: Female | W73: 2445 | X73: Fully Meets | Y73: 1 | Z73: 3570 | AA73: 44958 | AB73: 2 | AC73: 5 | AD73: 45014 | AE73: Project Management | AF73: External | AG73: Failed | AH73: Port Kristopherfurt | AI73: Matthew Ramirez | AJ73: 2 | AK73: 796.88
A74: 144 | B74: Marilyn | C74: Linares | D74: 44749 | E74: 45124 | F74: =Messy_HR_Dataset_Detailed!$E74-Messy_HR_Dataset_Detailed!$D74 -> 375 | G74: =(Messy_HR_Dataset_Detailed!$E74-Messy_HR_Dataset_Detailed!$D74)/365.25 -> 1.026694 | H74: Production Technician I | I74: Dr. Matthew Schmitt | J74: marilyn.linares@bilearner.com | K74: NEL | L74: Voluntarily Terminated | M74: Part-Time | N74: Zone C | O74: Full-Time | P74: Resignation | Q74: Production | R74: Field Operations | S74: 29-08-1947 | T74: MA | U74: Engineer | V74: Female | W74: 1886 | X74: Fully Meets | Y74: 4 | Z74: 3571 | AA74: 23-11-2022 | AB74: 4 | AC74: 1 | AD74: 45142 | AE74: Project Management | AF74: External | AG74: Completed | AH74: North William | AI74: Tanya Melendez | AJ74: 3 | AK74: 834.44
A75: 145 | B75: Timothy | C75: Sullivan | D75: 43536 | E75: 43970 | F75: =Messy_HR_Dataset_Detailed!$E75-Messy_HR_Dataset_Detailed!$D75 -> 434 | G75: =(Messy_HR_Dataset_Detailed!$E75-Messy_HR_Dataset_Detailed!$D75)/365.25 -> 1.1882272 | H75: Production Technician I | I75: Shawn Berry | J75: timothy.sullivan@bilearner.com | K75: WBL | L75: Active | M75: Contract | N75: Zone A | O75: Part-Time | P75: Retirement | Q75: Production | R75: Fielders | S75: 34521 | T75: MA | U75: Engineer | V75: Male | W75: 2747 | X75: Fully Meets | Y75: 5 | Z75: 3572 | AA75: 44693 | AB75: 5 | AC75: 5 | AD75: 45065 | AE75: Leadership Development | AF75: Internal | AG75: Failed | AH75: Port Dennis | AI75: Brady Newton | AJ75: 5 | AK75: 569.17
A76: 146 | B76: Jennifer | C76: Medeiros | D76: 43899 | E76: 44486 | F76: =Messy_HR_Dataset_Detailed!$E76-Messy_HR_Dataset_Detailed!$D76 -> 587 | G76: =(Messy_HR_Dataset_Detailed!$E76-Messy_HR_Dataset_Detailed!$D76)/365.25 -> 1.6071184 | H76: Production Technician I | I76: Brittany Martin | J76: jennifer.medeiros@bilearner.com | K76: NEL | L76: Active | M76: Contract | N76: Zone B | O76: Full-Time | P76: Involuntary | Q76: Production | R76: Field Operations | S76: 26-10-1983 | T76: MA | U76: Driller | V76: Female | W76: 2346 | X76: Exceeds | Y76: 4 | Z76: 3573 | AA76: 31-12-2022 | AB76: 4 | AC76: 1 | AD76: 44840 | AE76: Customer Service | AF76: Internal | AG76: Completed | AH76: Port Desireeburgh | AI76: Francis Cox | AJ76: 4 | AK76: 386.07
A77: 147 | B77: Anna | C77: Von Massenbach | D77: 44334 | E77: 44565 | F77: =Messy_HR_Dataset_Detailed!$E77-Messy_HR_Dataset_Detailed!$D77 -> 231 | G77: =(Messy_HR_Dataset_Detailed!$E77-Messy_HR_Dataset_Detailed!$D77)/365.25 -> 0.63244353 | H77: Production Technician I | I77: Timothy Weaver | J77: anna.von massenbach@bilearner.com | K77: WBL | L77: Future Start | M77: Contract | N77: Zone B | O77: Full-Time | P77: Involuntary | Q77: Production | R77: Underground | S77: 18784 | T77: MA | U77: Laborer | V77: Female | W77: 2124 | X77: Fully Meets | Y77: 1 | Z77: 3574 | AA77: 45114 | AB77: 3 | AC77: 3 | AD77: 44809 | AE77: Customer Service | AF77: Internal | AG77: Completed | AH77: Port Amy | AI77: Sharon Mcfarland | AJ77: 1 | AK77: 309.56
A78: 148 | B78: George | C78: Johnson | D78: 44314 | E78: 44579 | F78: =Messy_HR_Dataset_Detailed!$E78-Messy_HR_Dataset_Detailed!$D78 -> 265 | G78: =(Messy_HR_Dataset_Detailed!$E78-Messy_HR_Dataset_Detailed!$D78)/365.25 -> 0.72553046 | H78: Production Technician I | I78: Amanda Smith | J78: george.johnson@bilearner.com | K78: MSC | L78: Voluntarily Terminated | M78: Part-Time | N78: Zone A | O78: Temporary | P78: Resignation | Q78: Production | R78: Field Operations | S78: 31900 | T78: MA | U78: Groundman | V78: Male | W78: 2445 | X78: Exceeds | Y78: 5 | Z78: 3575 | AA78: 26-06-2023 | AB78: 5 | AC78: 1 | AD78: 44907 | AE78: Technical Skills | AF78: Internal | AG78: Incomplete | AH78: South Paulport | AI78: Brian Hood | AJ78: 3 | AK78: 583.21
A79: 149 | B79: Angela | C79: Erilus | D79: 44398 | E79: 45042 | F79: =Messy_HR_Dataset_Detailed!$E79-Messy_HR_Dataset_Detailed!$D79 -> 644 | G79: =(Messy_HR_Dataset_Detailed!$E79-Messy_HR_Dataset_Detailed!$D79)/365.25 -> 1.7631759 | H79: Production Technician II | I79: Marc Cummings | J79: angela.erilus@bilearner.com | K79: PL | L79: Active | M79: Full-Time | N79: Zone B | O79: Full-Time | P79: Voluntary | Q79: Production | R79: Engineers | S79: 26-04-1992 | T79: MA | U79: Project Manager | V79: Female | W79: 2133 | X79: Exceeds | Y79: 4 | Z79: 3576 | AA79: 23-03-2023 | AB79: 2 | AC79: 3 | AD79: 44959 | AE79: Project Management | AF79: External | AG79: Completed | AH79: East Taylor | AI79: Jesse Sullivan | AJ79: 5 | AK79: 398.65
A80: 154 | B80: Ross | C80: Strickland | D80: 44155 | E80: 45047 | F80: =Messy_HR_Dataset_Detailed!$E80-Messy_HR_Dataset_Detailed!$D80 -> 892 | G80: =(Messy_HR_Dataset_Detailed!$E80-Messy_HR_Dataset_Detailed!$D80)/365.25 -> 2.4421629 | H80: Production Technician I | I80: Paul Walker | J80: ross.strickland@bilearner.com | K80: SVG | L80: Active | M80: Full-Time | N80: Zone A | O80: Part-Time | P80: Voluntary | Q80: Production | R80: Wireline Construction | S80: 15921 | T80: MA | U80: Foreman | V80: Male | W80: 18389 | X80: Fully Meets | Y80: 2 | Z80: 3581 | AA80: 29-08-2022 | AB80: 3 | AC80: 4 | AD80: 44955 | AE80: Communication Skills | AF80: External | AG80: Completed | AH80: Michaelberg | AI80: Todd Ramirez | AJ80: 1 | AK80: 122.07
A81: 155 | B81: Augustus | C81: Drake | D81: 44062 | E81: 44685 | F81: =Messy_HR_Dataset_Detailed!$E81-Messy_HR_Dataset_Detailed!$D81 -> 623 | G81: =(Messy_HR_Dataset_Detailed!$E81-Messy_HR_Dataset_Detailed!$D81)/365.25 -> 1.705681 | H81: Production Technician I | I81: Elizabeth Robertson | J81: augustus.drake@bilearner.com | K81: TNS | L81: Active | M81: Part-Time | N81: Zone B | O81: Part-Time | P81: Retirement | Q81: Production | R81: Yard (Material Handling) | S81: 25089 | T81: MA | U81: Laborer | V81: Male | W81: 90676 | X81: Fully Meets | Y81: 4 | Z81: 3582 | AA81: 17-09-2022 | AB81: 2 | AC81: 2 | AD81: 44813 | AE81: Communication Skills | AF81: Internal | AG81: Completed | AH81: Lopezborough | AI81: Erik Reeves | AJ81: 4 | AK81: 875.02
A82: 156 | B82: Gracelyn | C82: Huynh | D82: 44314 | E82: 44669 | F82: =Messy_HR_Dataset_Detailed!$E82-Messy_HR_Dataset_Detailed!$D82 -> 355 | G82: =(Messy_HR_Dataset_Detailed!$E82-Messy_HR_Dataset_Detailed!$D82)/365.25 -> 0.97193703 | H82: Production Technician I | I82: Tasha Mayer | J82: gracelyn.huynh@bilearner.com | K82: WBL | L82: Active | M82: Full-Time | N82: Zone C | O82: Temporary | P82: Retirement | Q82: Production | R82: Field Operations | S82: 20-11-1958 | T82: MA | U82: Construction Manager | V82: Female | W82: 16011 | X82: Needs Improvement | Y82: 4 | Z82: 3583 | AA82: 45053 | AB82: 4 | AC82: 1 | AD82: 45003 | AE82: Communication Skills | AF82: Internal | AG82: Incomplete | AH82: Philipburgh | AI82: Jennifer Woods | AJ82: 4 | AK82: 116.4
A83: 159 | B83: Jaqueline | C83: Terrell | D83: 43497 | E83: 43506 | F83: =Messy_HR_Dataset_Detailed!$E83-Messy_HR_Dataset_Detailed!$D83 -> 9 | G83: =(Messy_HR_Dataset_Detailed!$E83-Messy_HR_Dataset_Detailed!$D83)/365.25 -> 0.024640657 | H83: Production Technician I | I83: Veronica Wiley | J83: jaqueline.terrell@bilearner.com | K83: EW | L83: Active | M83: Part-Time | N83: Zone B | O83: Full-Time | P83: Resignation | Q83: Production | R83: People Services | S83: 27-12-2000 | T83: MA | U83: Manager | V83: Female | W83: 24711 | X83: Fully Meets | Y83: 2 | Z83: 3586 | AA83: 31-01-2023 | AB83: 4 | AC83: 2 | AD83: 44834 | AE83: Communication Skills | AF83: External | AG83: Completed | AH83: Browntown | AI83: Tamara Hayes | AJ83: 1 | AK83: 502.7
A84: 160 | B84: Quinn | C84: Mccullough | D84: 44326 | E84: 44547 | F84: =Messy_HR_Dataset_Detailed!$E84-Messy_HR_Dataset_Detailed!$D84 -> 221 | G84: =(Messy_HR_Dataset_Detailed!$E84-Messy_HR_Dataset_Detailed!$D84)/365.25 -> 0.60506502 | H84: Production Technician I | I84: Katherine Gay | J84: quinn.mccullough@bilearner.com | K84: MSC | L84: Active | M84: Full-Time | N84: Zone B | O84: Temporary | P84: Resignation | Q84: Production | R84: General - Eng | S84: 25-12-1977 | T84: MA | U84: Administrative | V84: Male | W84: 74564 | X84: Fully Meets | Y84: 2 | Z84: 3587 | AA84: 24-05-2023 | AB84: 1 | AC84: 2 | AD84: 45007 | AE84: Leadership Development | AF84: External | AG84: Completed | AH84: New Larryshire | AI84: Darren Lam | AJ84: 5 | AK84: 570.04
A85: 161 | B85: Selena | C85: Greer | D85: 43641 | E85: 43692 | F85: =Messy_HR_Dataset_Detailed!$E85-Messy_HR_Dataset_Detailed!$D85 -> 51 | G85: =(Messy_HR_Dataset_Detailed!$E85-Messy_HR_Dataset_Detailed!$D85)/365.25 -> 0.13963039 | H85: Production Technician I | I85: Paul Lopez | J85: selena.greer@bilearner.com | K85: NEL | L85: Active | M85: Full-Time | N85: Zone C | O85: Full-Time | P85: Retirement | Q85: Production | R85: Shop (Fleet) | S85: 26514 | T85: MA | U85: Mechanic | V85: Male | W85: 14504 | X85: Fully Meets | Y85: 2 | Z85: 3588 | AA85: 45204 | AB85: 4 | AC85: 2 | AD85: 45008 | AE85: Communication Skills | AF85: External | AG85: Passed | AH85: Montgomeryland | AI85: Casey Johnston | AJ85: 1 | AK85: 538.83
A86: 163 | B86: Dominik | C86: Mullen | D86: 44252 | E86: 44847 | F86: =Messy_HR_Dataset_Detailed!$E86-Messy_HR_Dataset_Detailed!$D86 -> 595 | G86: =(Messy_HR_Dataset_Detailed!$E86-Messy_HR_Dataset_Detailed!$D86)/365.25 -> 1.6290212 | H86: Production Technician I | I86: Jessica Allen | J86: dominik.mullen@bilearner.com | K86: PYZ | L86: Future Start | M86: Part-Time | N86: Zone C | O86: Full-Time | P86: Retirement | Q86: Production | R86: Field Operations | S86: 31-05-1995 | T86: MA | U86: Laborer | V86: Male | W86: 66167 | X86: Fully Meets | Y86: 4 | Z86: 3590 | AA86: 44724 | AB86: 2 | AC86: 5 | AD86: 45018 | AE86: Leadership Development | AF86: External | AG86: Completed | AH86: North Janetbury | AI86: Michelle Baker | AJ86: 1 | AK86: 274.33
A87: 164 | B87: Abdullah | C87: Ellison | D87: 44523 | E87: 45075 | F87: =Messy_HR_Dataset_Detailed!$E87-Messy_HR_Dataset_Detailed!$D87 -> 552 | G87: =(Messy_HR_Dataset_Detailed!$E87-Messy_HR_Dataset_Detailed!$D87)/365.25 -> 1.5112936 | H87: Production Technician I | I87: Dr. William Thompson | J87: abdullah.ellison@bilearner.com | K87: SVG | L87: Future Start | M87: Contract | N87: Zone B | O87: Part-Time | P87: Voluntary | Q87: Production | R87: Field Operations | S87: 14-11-1998 | T87: MA | U87: Supervisor | V87: Female | W87: 21634 | X87: Needs Improvement | Y87: 5 | Z87: 3591 | AA87: 27-07-2023 | AB87: 2 | AC87: 1 | AD87: 44986 | AE87: Customer Service | AF87: Internal | AG87: Failed | AH87: Michaelfurt | AI87: Amy Murray | AJ87: 1 | AK87: 247.01
A88: 165 | B88: Andre | C88: Guzman | D88: 44474 | E88: 44730 | F88: =Messy_HR_Dataset_Detailed!$E88-Messy_HR_Dataset_Detailed!$D88 -> 256 | G88: =(Messy_HR_Dataset_Detailed!$E88-Messy_HR_Dataset_Detailed!$D88)/365.25 -> 0.7008898 | H88: Production Technician I | I88: Mrs. Audrey Gonzalez DDS | J88: andre.guzman@bilearner.com | K88: TNS | L88: Future Start | M88: Contract | N88: Zone B | O88: Full-Time | P88: Voluntary | Q88: Production | R88: Field Operations | S88: 23-12-1998 | T88: MA | U88: Technician | V88: Male | W88: 9454 | X88: Fully Meets | Y88: 3 | Z88: 3592 | AA88: 15-11-2022 | AB88: 4 | AC88: 1 | AD88: 44956 | AE88: Leadership Development | AF88: External | AG88: Incomplete | AH88: Williamsborough | AI88: Daniel Wilson | AJ88: 1 | AK88: 734.68
A89: 168 | B89: Fisher | C89: Stafford | D89: 44096 | E89: 44818 | F89: =Messy_HR_Dataset_Detailed!$E89-Messy_HR_Dataset_Detailed!$D89 -> 722 | G89: =(Messy_HR_Dataset_Detailed!$E89-Messy_HR_Dataset_Detailed!$D89)/365.25 -> 1.9767283 | H89: Production Technician I | I89: Nicole Delgado | J89: fisher.stafford@bilearner.com | K89: WBL | L89: Active | M89: Contract | N89: Zone A | O89: Temporary | P89: Resignation | Q89: Production | R89: Engineers | S89: 19027 | T89: MA | U89: Technician | V89: Male | W89: 56703 | X89: Fully Meets | Y89: 1 | Z89: 3595 | AA89: 19-01-2023 | AB89: 2 | AC89: 3 | AD89: 44978 | AE89: Technical Skills | AF89: External | AG89: Passed | AH89: Popetown | AI89: Angela Sanchez | AJ89: 2 | AK89: 252.88
A90: 170 | B90: Brenton | C90: Monroe | D90: 43988 | E90: 44300 | F90: =Messy_HR_Dataset_Detailed!$E90-Messy_HR_Dataset_Detailed!$D90 -> 312 | G90: =(Messy_HR_Dataset_Detailed!$E90-Messy_HR_Dataset_Detailed!$D90)/365.25 -> 0.85420945 | H90: Production Technician II | I90: Autumn Decker | J90: brenton.monroe@bilearner.com | K90: PYZ | L90: Future Start | M90: Contract | N90: Zone C | O90: Part-Time | P90: Retirement | Q90: Production | R90: General - Con | S90: 31-10-1986 | T90: MA | U90: Foreman | V90: Female | W90: 17650 | X90: Fully Meets | Y90: 1 | Z90: 3597 | AA90: 27-10-2022 | AB90: 5 | AC90: 4 | AD90: 44988 | AE90: Technical Skills | AF90: External | AG90: Incomplete | AH90: Port Jennifershire | AI90: Katrina Maldonado | AJ90: 4 | AK90: 505.59
A91: 171 | B91: Derick | C91: Rocha | D91: 43371 | E91: 45143 | F91: =Messy_HR_Dataset_Detailed!$E91-Messy_HR_Dataset_Detailed!$D91 -> 1772 | G91: =(Messy_HR_Dataset_Detailed!$E91-Messy_HR_Dataset_Detailed!$D91)/365.25 -> 4.8514716 | H91: Production Technician II | I91: Alex Moore | J91: derick.rocha@bilearner.com | K91: SVG | L91: Voluntarily Terminated | M91: Part-Time | N91: Zone A | O91: Full-Time | P91: Resignation | Q91: Production | R91: Project Management - Eng | S91: 18424 | T91: MA | U91: Supervisor | V91: Female | W91: 72750 | X91: Needs Improvement | Y91: 1 | Z91: 3598 | AA91: 44933 | AB91: 2 | AC91: 5 | AD91: 44845 | AE91: Technical Skills | AF91: Internal | AG91: Passed | AH91: Aliciahaven | AI91: Matthew Alvarado | AJ91: 3 | AK91: 373.87
A92: 175 | B92: Helena | C92: Davenport | D92: 44297 | E92: 45070 | F92: =Messy_HR_Dataset_Detailed!$E92-Messy_HR_Dataset_Detailed!$D92 -> 773 | G92: =(Messy_HR_Dataset_Detailed!$E92-Messy_HR_Dataset_Detailed!$D92)/365.25 -> 2.1163587 | H92: Production Technician II | I92: Crystal Mcneil | J92: helena.davenport@bilearner.com | K92: CCDR | L92: Voluntarily Terminated | M92: Full-Time | N92: Zone B | O92: Part-Time | P92: Involuntary | Q92: Production | R92: Engineers | S92: 34678 | T92: MA | U92: Engineer | V92: Female | W92: 30766 | X92: Fully Meets | Y92: 5 | Z92: 3602 | AA92: 45024 | AB92: 3 | AC92: 3 | AD92: 45025 | AE92: Technical Skills | AF92: External | AG92: Incomplete | AH92: New Michael | AI92: Joyce Williams | AJ92: 1 | AK92: 632.59
A93: 176 | B93: Houston | C93: Aguirre | D93: 43433 | E93: 43517 | F93: =Messy_HR_Dataset_Detailed!$E93-Messy_HR_Dataset_Detailed!$D93 -> 84 | G93: =(Messy_HR_Dataset_Detailed!$E93-Messy_HR_Dataset_Detailed!$D93)/365.25 -> 0.22997947 | H93: Production Technician II | I93: Christine Costa | J93: houston.aguirre@bilearner.com | K93: EW | L93: Voluntarily Terminated | M93: Full-Time | N93: Zone A | O93: Part-Time | P93: Resignation | Q93: Production | R93: Field Operations | S93: 15-02-1977 | T93: MA | U93: Technician | V93: Female | W93: 58348 | X93: Fully Meets | Y93: 2 | Z93: 3603 | AA93: 44783 | AB93: 5 | AC93: 1 | AD93: 44836 | AE93: Technical Skills | AF93: External | AG93: Incomplete | AH93: East Kristaton | AI93: Daniel Daugherty | AJ93: 3 | AK93: 680.48
A94: 177 | B94: Kane | C94: Owen | D94: 43481 | E94: 44804 | F94: =Messy_HR_Dataset_Detailed!$E94-Messy_HR_Dataset_Detailed!$D94 -> 1323 | G94: =(Messy_HR_Dataset_Detailed!$E94-Messy_HR_Dataset_Detailed!$D94)/365.25 -> 3.6221766 | H94: Production Technician II | I94: Mark Hale | J94: kane.owen@bilearner.com | K94: MSC | L94: Active | M94: Part-Time | N94: Zone B | O94: Full-Time | P94: Resignation | Q94: Production | R94: Field Operations | S94: 17779 | T94: MA | U94: Foreman | V94: Female | W94: 44626 | X94: Needs Improvement | Y94: 4 | Z94: 3604 | AA94: 15-12-2022 | AB94: 3 | AC94: 5 | AD94: 45008 | AE94: Project Management | AF94: External | AG94: Failed | AH94: Lake Scotttown | AI94: Ryan Russell | AJ94: 3 | AK94: 287.71
A95: 179 | B95: Clarissa | C95: Winters | D95: 43678 | E95: 44946 | F95: =Messy_HR_Dataset_Detailed!$E95-Messy_HR_Dataset_Detailed!$D95 -> 1268 | G95: =(Messy_HR_Dataset_Detailed!$E95-Messy_HR_Dataset_Detailed!$D95)/365.25 -> 3.4715948 | H95: Production Technician I | I95: Eric Gonzales | J95: clarissa.winters@bilearner.com | K95: SVG | L95: Voluntarily Terminated | M95: Part-Time | N95: Zone C | O95: Full-Time | P95: Involuntary | Q95: Production | R95: Billable Consultants | S95: 13-03-1965 | T95: MA | U95: Engineer | V95: Male | W95: 95618 | X95: Fully Meets | Y95: 3 | Z95: 3606 | AA95: 27-03-2023 | AB95: 3 | AC95: 5 | AD95: 44865 | AE95: Project Management | AF95: Internal | AG95: Passed | AH95: New Derrick | AI95: Elizabeth Powell | AJ95: 2 | AK95: 255.6
A96: 180 | B96: Frankie | C96: Atkins | D96: 43634 | E96: 44300 | F96: =Messy_HR_Dataset_Detailed!$E96-Messy_HR_Dataset_Detailed!$D96 -> 666 | G96: =(Messy_HR_Dataset_Detailed!$E96-Messy_HR_Dataset_Detailed!$D96)/365.25 -> 1.8234086 | H96: Production Technician I | I96: Christopher Murray | J96: frankie.atkins@bilearner.com | K96: EW | L96: Active | M96: Full-Time | N96: Zone A | O96: Full-Time | P96: Resignation | Q96: Production | R96: Project Management - Con | S96: 27827 | T96: MA | U96: Coordinator | V96: Male | W96: 15195 | X96: Fully Meets | Y96: 5 | Z96: 3607 | AA96: 18-07-2023 | AB96: 2 | AC96: 4 | AD96: 45050 | AE96: Customer Service | AF96: External | AG96: Passed | AH96: Port Tammyside | AI96: Andre Maxwell | AJ96: 4 | AK96: 321.91
A97: 187 | B97: Bridget | C97: Deleon | D97: 43838 | E97: 44379 | F97: =Messy_HR_Dataset_Detailed!$E97-Messy_HR_Dataset_Detailed!$D97 -> 541 | G97: =(Messy_HR_Dataset_Detailed!$E97-Messy_HR_Dataset_Detailed!$D97)/365.25 -> 1.4811773 | H97: Production Technician I | I97: Clifford Martinez | J97: bridget.deleon@bilearner.com | K97: BPC | L97: Active | M97: Contract | N97: Zone B | O97: Temporary | P97: Voluntary | Q97: Production | R97: Project Management - Con | S97: 31-08-1973 | T97: MA | U97: Field Project Manager | V97: Male | W97: 23691 | X97: Fully Meets | Y97: 2 | Z97: 3614 | AA97: 45023 | AB97: 4 | AC97: 5 | AD97: 45081 | AE97: Leadership Development | AF97: External | AG97: Passed | AH97: Emilymouth | AI97: Paul Bradley | AJ97: 3 | AK97: 868.85
A98: 188 | B98: Martin | C98: Weber | D98: 44329 | E98: 44826 | F98: =Messy_HR_Dataset_Detailed!$E98-Messy_HR_Dataset_Detailed!$D98 -> 497 | G98: =(Messy_HR_Dataset_Detailed!$E98-Messy_HR_Dataset_Detailed!$D98)/365.25 -> 1.3607118 | H98: Production Technician I | I98: Lee Hudson | J98: martin.weber@bilearner.com | K98: CCDR | L98: Future Start | M98: Full-Time | N98: Zone B | O98: Part-Time | P98: Retirement | Q98: Production | R98: General - Con | S98: 14-05-1986 | T98: MA | U98: Manager | V98: Male | W98: 74388 | X98: Exceeds | Y98: 2 | Z98: 3615 | AA98: 45079 | AB98: 3 | AC98: 1 | AD98: 44912 | AE98: Communication Skills | AF98: Internal | AG98: Passed | AH98: New Paul | AI98: James Young | AJ98: 4 | AK98: 701.34
A99: 192 | B99: Karissa | C99: Bowers | D99: 45008 | E99: 45047 | F99: =Messy_HR_Dataset_Detailed!$E99-Messy_HR_Dataset_Detailed!$D99 -> 39 | G99: =(Messy_HR_Dataset_Detailed!$E99-Messy_HR_Dataset_Detailed!$D99)/365.25 -> 0.10677618 | H99: Production Technician I | I99: Robert Wright | J99: karissa.bowers@bilearner.com | K99: TNS | L99: Active | M99: Full-Time | N99: Zone A | O99: Full-Time | P99: Involuntary | Q99: Production | R99: General - Con | S99: 17-03-1984 | T99: MA | U99: Technician | V99: Male | W99: 76278 | X99: Fully Meets | Y99: 3 | Z99: 3619 | AA99: 30-04-2023 | AB99: 1 | AC99: 5 | AD99: 44875 | AE99: Project Management | AF99: Internal | AG99: Passed | AH99: Davismouth | AI99: Ashley Ball | AJ99: 2 | AK99: 656.68
A100: 193 | B100: Noel | C100: Ramirez | D100: 45007 | E100: 45121 | F100: =Messy_HR_Dataset_Detailed!$E100-Messy_HR_Dataset_Detailed!$D100 -> 114 | G100: =(Messy_HR_Dataset_Detailed!$E100-Messy_HR_Dataset_Detailed!$D100)/365.25 -> 0.31211499 | H100: Production Technician I | I100: Mr. Nicholas Austin | J100: noel.ramirez@bilearner.com | K100: PYZ | L100: Active | M100: Part-Time | N100: Zone A | O100: Temporary | P100: Involuntary | Q100: Production | R100: General - Eng | S100: 34678 | T100: MA | U100: Specialist | V100: Male | W100: 77580 | X100: Fully Meets | Y100: 2 | Z100: 3620 | AA100: 29-08-2022 | AB100: 1 | AC100: 2 | AD100: 44915 | AE100: Technical Skills | AF100: Internal | AG100: Completed | AH100: North Ebony | AI100: Christine Carter | AJ100: 3 | AK100: 654.22
...
